Workbook

Sheet Summary
A1: Blockmancer Release 1.0 Asset Checklist
A2: Done? cells use an Excel-friendly checkbox symbol. Default is ☐; change to ☑ when complete.
A4: Category Sheet | B4: Original Category | C4: Total Assets | D4: Done | E4: Remaining | F4: Progress
A5: 00 Global Placeholder | B5: 0. Global Placeholder Assets | C5: =COUNTA('00 Global Placeholder'!$B$5:$B$10000) -> 6 | D5: =COUNTIF('00 Global Placeholder'!$A$5:$A$10000,"☑") -> 0 | E5: =C5-D5 -> 6 | F5: =IFERROR(D5/C5,0) -> 0
A6: 01 BGM | B6: 1. Background Music Assets | C6: =COUNTA('01 BGM'!$B$5:$B$10000) -> 26 | D6: =COUNTIF('01 BGM'!$A$5:$A$10000,"☑") -> 0 | E6: =C6-D6 -> 26 | F6: =IFERROR(D6/C6,0) -> 0
A7: 02 Ambient Audio | B7: 2. Ambient Audio Assets | C7: =COUNTA('02 Ambient Audio'!$B$5:$B$10000) -> 9 | D7: =COUNTIF('02 Ambient Audio'!$A$5:$A$10000,"☑") -> 0 | E7: =C7-D7 -> 9 | F7: =IFERROR(D7/C7,0) -> 0
A8: 03 SFX - Board | B8: 3. Sound Effect Assets — Board | C8: =COUNTA('03 SFX - Board'!$B$5:$B$10000) -> 20 | D8: =COUNTIF('03 SFX - Board'!$A$5:$A$10000,"☑") -> 0 | E8: =C8-D8 -> 20 | F8: =IFERROR(D8/C8,0) -> 0
A9: 04 SFX - Special Blocks | B9: 4. Sound Effect Assets — Special Blocks | C9: =COUNTA('04 SFX - Special Blocks'!$B$5:$B$10000) -> 18 | D9: =COUNTIF('04 SFX - Special Blocks'!$A$5:$A$10000,"☑") -> 0 | E9: =C9-D9 -> 18 | F9: =IFERROR(D9/C9,0) -> 0
A10: 05 SFX - Combat | B10: 5. Sound Effect Assets — Combat | C10: =COUNTA('05 SFX - Combat'!$B$5:$B$10000) -> 17 | D10: =COUNTIF('05 SFX - Combat'!$A$5:$A$10000,"☑") -> 0 | E10: =C10-D10 -> 17 | F10: =IFERROR(D10/C10,0) -> 0
A11: 06 SFX - Spells | B11: 6. Sound Effect Assets — Spells | C11: =COUNTA('06 SFX - Spells'!$B$5:$B$10000) -> 15 | D11: =COUNTIF('06 SFX - Spells'!$A$5:$A$10000,"☑") -> 0 | E11: =C11-D11 -> 15 | F11: =IFERROR(D11/C11,0) -> 0
A12: 07 SFX - UI | B12: 7. Sound Effect Assets — UI | C12: =COUNTA('07 SFX - UI'!$B$5:$B$10000) -> 19 | D12: =COUNTIF('07 SFX - UI'!$A$5:$A$10000,"☑") -> 0 | E12: =C12-D12 -> 19 | F12: =IFERROR(D12/C12,0) -> 0
A13: 08 BG - Scenes | B13: 8. Background Assets — Scenes | C13: =COUNTA('08 BG - Scenes'!$B$5:$B$10000) -> 15 | D13: =COUNTIF('08 BG - Scenes'!$A$5:$A$10000,"☑") -> 0 | E13: =C13-D13 -> 15 | F13: =IFERROR(D13/C13,0) -> 0
A14: 09 BG - Stage Battle Parallax | B14: 9. Background Assets — Stage Battle Parallax | C14: =COUNTA('09 BG - Stage Battle Parallax'!$B$5:$B$10000) -> 18 | D14: =COUNTIF('09 BG - Stage Battle Parallax'!$A$5:$A$10000,"☑") -> 0 | E14: =C14-D14 -> 18 | F14: =IFERROR(D14/C14,0) -> 0
A15: 10 BG - Boss Arenas | B15: 10. Background Assets — Boss Arenas | C15: =COUNTA('10 BG - Boss Arenas'!$B$5:$B$10000) -> 6 | D15: =COUNTIF('10 BG - Boss Arenas'!$A$5:$A$10000,"☑") -> 0 | E15: =C15-D15 -> 6 | F15: =IFERROR(D15/C15,0) -> 0
A16: 11 Map - Map BGs | B16: 11. Map Assets — Map Backgrounds | C16: =COUNTA('11 Map - Map BGs'!$B$5:$B$10000) -> 6 | D16: =COUNTIF('11 Map - Map BGs'!$A$5:$A$10000,"☑") -> 0 | E16: =C16-D16 -> 6 | F16: =IFERROR(D16/C16,0) -> 0
A17: 12 Map - Node States | B17: 12. Map Assets — Node States | C17: =COUNTA('12 Map - Node States'!$B$5:$B$10000) -> 40 | D17: =COUNTIF('12 Map - Node States'!$A$5:$A$10000,"☑") -> 0 | E17: =C17-D17 -> 40 | F17: =IFERROR(D17/C17,0) -> 0
A18: 13 Map - Paths and Decorations | B18: 13. Map Assets — Paths and Decorations | C18: =COUNTA('13 Map - Paths and Decorations'!$B$5:$B$10000) -> 11 | D18: =COUNTIF('13 Map - Paths and Decorations'!$A$5:$A$10000,"☑") -> 0 | E18: =C18-D18 -> 11 | F18: =IFERROR(D18/C18,0) -> 0
A19: 14 - Heroes | B19: 14. Sprite Assets — Playable Heroes | C19: =COUNTA('14 - Heroes'!$B$5:$B$10000) -> 54 | D19: =COUNTIF('14 - Heroes'!$A$5:$A$10000,"☑") -> 0 | E19: =C19-D19 -> 54 | F19: =IFERROR(D19/C19,0) -> 0
A20: 15 - Monsters | B20: 15. Sprite Assets — Regular Monsters | C20: =COUNTA('15 - Monsters'!$B$5:$B$10000) -> 180 | D20: =COUNTIF('15 - Monsters'!$A$5:$A$10000,"☑") -> 0 | E20: =C20-D20 -> 180 | F20: =IFERROR(D20/C20,0) -> 0
A21: 16 - Bosses | B21: 16. Sprite Assets — Bosses | C21: =COUNTA('16 - Bosses'!$B$5:$B$10000) -> 54 | D21: =COUNTIF('16 - Bosses'!$A$5:$A$10000,"☑") -> 0 | E21: =C21-D21 -> 54 | F21: =IFERROR(D21/C21,0) -> 0
A22: 17 - NPCs | B22: 17. Sprite Assets — NPCs | C22: =COUNTA('17 - NPCs'!$B$5:$B$10000) -> 24 | D22: =COUNTIF('17 - NPCs'!$A$5:$A$10000,"☑") -> 0 | E22: =C22-D22 -> 24 | F22: =IFERROR(D22/C22,0) -> 0
A23: 18 - Board Blocks | B23: 18. Sprite Assets — Board Blocks and Board UI | C23: =COUNTA('18 - Board Blocks'!$B$5:$B$10000) -> 86 | D23: =COUNTIF('18 - Board Blocks'!$A$5:$A$10000,"☑") -> 0 | E23: =C23-D23 -> 86 | F23: =IFERROR(D23/C23,0) -> 0
A24: 19 and VFX - Spells | B24: 19. Icon and VFX Assets — Spells | C24: =COUNTA('19 and VFX - Spells'!$B$5:$B$10000) -> 45 | D24: =COUNTIF('19 and VFX - Spells'!$A$5:$A$10000,"☑") -> 0 | E24: =C24-D24 -> 45 | F24: =IFERROR(D24/C24,0) -> 0
A25: 20 - Items | B25: 20. Icon Assets — Items and Reactive Counter Items | C25: =COUNTA('20 - Items'!$B$5:$B$10000) -> 52 | D25: =COUNTIF('20 - Items'!$A$5:$A$10000,"☑") -> 0 | E25: =C25-D25 -> 52 | F25: =IFERROR(D25/C25,0) -> 0
A26: 21 - Relics | B26: 21. Icon Assets — Relics | C26: =COUNTA('21 - Relics'!$B$5:$B$10000) -> 15 | D26: =COUNTIF('21 - Relics'!$A$5:$A$10000,"☑") -> 0 | E26: =C26-D26 -> 15 | F26: =IFERROR(D26/C26,0) -> 0
A27: 22 - Upgrades | B27: 22. Icon Assets — Upgrades | C27: =COUNTA('22 - Upgrades'!$B$5:$B$10000) -> 15 | D27: =COUNTIF('22 - Upgrades'!$A$5:$A$10000,"☑") -> 0 | E27: =C27-D27 -> 15 | F27: =IFERROR(D27/C27,0) -> 0
A28: 23 and - Weapons | B28: 23. Icon and Sprite Assets — Weapons | C28: =COUNTA('23 and - Weapons'!$B$5:$B$10000) -> 20 | D28: =COUNTIF('23 and - Weapons'!$A$5:$A$10000,"☑") -> 0 | E28: =C28-D28 -> 20 | F28: =IFERROR(D28/C28,0) -> 0
A29: 24 - Status Effects | B29: 24. Icon Assets — Status Effects | C29: =COUNTA('24 - Status Effects'!$B$5:$B$10000) -> 10 | D29: =COUNTIF('24 - Status Effects'!$A$5:$A$10000,"☑") -> 0 | E29: =C29-D29 -> 10 | F29: =IFERROR(D29/C29,0) -> 0
A30: 25 - Oopsies | B30: 25. Icon Assets — Oopsies / Silly Drawbacks | C30: =COUNTA('25 - Oopsies'!$B$5:$B$10000) -> 8 | D30: =COUNTIF('25 - Oopsies'!$A$5:$A$10000,"☑") -> 0 | E30: =C30-D30 -> 8 | F30: =IFERROR(D30/C30,0) -> 0
A31: 26 - Festival Chaos Rules | B31: 26. Icon Assets — Festival Chaos Rules | C31: =COUNTA('26 - Festival Chaos Rules'!$B$5:$B$10000) -> 8 | D31: =COUNTIF('26 - Festival Chaos Rules'!$A$5:$A$10000,"☑") -> 0 | E31: =C31-D31 -> 8 | F31: =IFERROR(D31/C31,0) -> 0
A32: 27 - Battle Objectives | B32: 27. Icon Assets — Battle Objectives | C32: =COUNTA('27 - Battle Objectives'!$B$5:$B$10000) -> 10 | D32: =COUNTIF('27 - Battle Objectives'!$A$5:$A$10000,"☑") -> 0 | E32: =C32-D32 -> 10 | F32: =IFERROR(D32/C32,0) -> 0
A33: 28 - Events | B33: 28. Icon Assets — Room Events and Random Gameplay Events | C33: =COUNTA('28 - Events'!$B$5:$B$10000) -> 28 | D33: =COUNTIF('28 - Events'!$A$5:$A$10000,"☑") -> 0 | E33: =C33-D33 -> 28 | F33: =IFERROR(D33/C33,0) -> 0
A34: 29 - Boss Rule Cards | B34: 29. Icon Assets — Boss Rule Cards | C34: =COUNTA('29 - Boss Rule Cards'!$B$5:$B$10000) -> 6 | D34: =COUNTIF('29 - Boss Rule Cards'!$A$5:$A$10000,"☑") -> 0 | E34: =C34-D34 -> 6 | F34: =IFERROR(D34/C34,0) -> 0
A35: 30 - Currency Collect | B35: 30. Icon Assets — Currencies and Collectibles | C35: =COUNTA('30 - Currency Collect'!$B$5:$B$10000) -> 8 | D35: =COUNTIF('30 - Currency Collect'!$A$5:$A$10000,"☑") -> 0 | E35: =C35-D35 -> 8 | F35: =IFERROR(D35/C35,0) -> 0
A36: 31 and - Hub Buildings | B36: 31. Sprite and Icon Assets — Festival Hub Buildings | C36: =COUNTA('31 and - Hub Buildings'!$B$5:$B$10000) -> 40 | D36: =COUNTIF('31 and - Hub Buildings'!$A$5:$A$10000,"☑") -> 0 | E36: =C36-D36 -> 40 | F36: =IFERROR(D36/C36,0) -> 0
A37: 32 UI - Panels Frames | B37: 32. UI Assets — Panels and Frames | C37: =COUNTA('32 UI - Panels Frames'!$B$5:$B$10000) -> 16 | D37: =COUNTIF('32 UI - Panels Frames'!$A$5:$A$10000,"☑") -> 0 | E37: =C37-D37 -> 16 | F37: =IFERROR(D37/C37,0) -> 0
A38: 33 UI - Buttons | B38: 33. UI Assets — Buttons | C38: =COUNTA('33 UI - Buttons'!$B$5:$B$10000) -> 14 | D38: =COUNTIF('33 UI - Buttons'!$A$5:$A$10000,"☑") -> 0 | E38: =C38-D38 -> 14 | F38: =IFERROR(D38/C38,0) -> 0
A39: 34 UI - Controls | B39: 34. UI Assets — Mobile Controls | C39: =COUNTA('34 UI - Controls'!$B$5:$B$10000) -> 14 | D39: =COUNTIF('34 UI - Controls'!$A$5:$A$10000,"☑") -> 0 | E39: =C39-D39 -> 14 | F39: =IFERROR(D39/C39,0) -> 0
A40: 35 UI - HUD | B40: 35. UI Assets — HUD and Meters | C40: =COUNTA('35 UI - HUD'!$B$5:$B$10000) -> 15 | D40: =COUNTIF('35 UI - HUD'!$A$5:$A$10000,"☑") -> 0 | E40: =C40-D40 -> 15 | F40: =IFERROR(D40/C40,0) -> 0
A41: 36 VFX - VFX | B41: 36. VFX Assets — Board, Combat, and Status | C41: =COUNTA('36 VFX - VFX'!$B$5:$B$10000) -> 29 | D41: =COUNTIF('36 VFX - VFX'!$A$5:$A$10000,"☑") -> 0 | E41: =C41-D41 -> 29 | F41: =IFERROR(D41/C41,0) -> 0
A42: 37 Font | B42: 37. Font Assets | C42: =COUNTA('37 Font'!$B$5:$B$10000) -> 4 | D42: =COUNTIF('37 Font'!$A$5:$A$10000,"☑") -> 0 | E42: =C42-D42 -> 4 | F42: =IFERROR(D42/C42,0) -> 0
A43: 38 Store | B43: 38. Store and Platform Assets | C43: =COUNTA('38 Store'!$B$5:$B$10000) -> 11 | D43: =COUNTIF('38 Store'!$A$5:$A$10000,"☑") -> 0 | E43: =C43-D43 -> 11 | F43: =IFERROR(D43/C43,0) -> 0

Sheet 00 Global Placeholder
A1: 0. Global Placeholder Assets
A2: Tracking sheet generated from the uploaded markdown. Done? is unchecked by default.
A4: Done? | B4: Asset Key | C4: Suggested Path | D4: Designer Description | E4: Priority
A5: ☐ | B5: placeholder_texture_missing | C5: public/assets/placeholders/placeholder_texture_missing.png | D5: Checker or cute warning texture for any missing generic image. | E5: P0 fallback
A6: ☐ | B6: placeholder_sprite_actor_idle | C6: public/assets/placeholders/placeholder_sprite_actor_idle.png | D6: Simple neutral character silhouette used when a hero, monster, boss, or NPC sprite is missing. | E6: P0 fallback
A7: ☐ | B7: placeholder_icon_missing | C7: public/assets/placeholders/placeholder_icon_missing.png | D7: Readable missing icon tile with question mark or tiny rune symbol. | E7: P0 fallback
A8: ☐ | B8: placeholder_bg_missing | C8: public/assets/placeholders/placeholder_bg_missing.png | D8: Simple colorful fallback scene background that does not break battle readability. | E8: P0 fallback
A9: ☐ | B9: placeholder_audio_silence | C9: public/assets/placeholders/placeholder_audio_silence.ogg | D9: Silent audio file used when a BGM or SFX key is missing. | E9: P0 fallback
A10: ☐ | B10: placeholder_vfx_sparkle | C10: public/assets/placeholders/placeholder_vfx_sparkle.png | D10: Small generic sparkle burst for missing VFX hooks. | E10: P0 fallback

Sheet 01 BGM
A1: 1. Background Music Assets
A2: Tracking sheet generated from the uploaded markdown. Done? is unchecked by default.
A4: Done? | B4: Asset Key | C4: Suggested Folder | D4: Designer Description | E4: Priority
A5: ☐ | B5: bgm_title_festival_loop | C5: audio/bgm/ | D5: Upbeat magical festival title theme with bright bells and playful rhythm. | E5: P0
A6: ☐ | B6: bgm_main_menu_cozy_loop | C6: audio/bgm/ | D6: Soft cozy menu loop that feels welcoming and low-pressure. | E6: P0
A7: ☐ | B7: bgm_hub_brixonia_loop | C7: audio/bgm/ | D7: Cheerful town hub loop with festival crowd warmth and toy-like melody. | E7: P1
A8: ☐ | B8: bgm_map_adventure_loop | C8: audio/bgm/ | D8: Light adventure map music for choosing roguelike nodes. | E8: P0
A9: ☐ | B9: bgm_tutorial_playful_loop | C9: audio/bgm/ | D9: Simple friendly tutorial loop with clear, non-distracting energy. | E9: P1
A10: ☐ | B10: bgm_shop_marnie_loop | C10: audio/bgm/ | D10: Cute shop music with small bells and merchant charm. | E10: P1
A11: ☐ | B11: bgm_reward_sparkle_loop | C11: audio/bgm/ | D11: Short reward-choice loop with glittery anticipation. | E11: P1
A12: ☐ | B12: bgm_event_silly_loop | C12: audio/bgm/ | D12: Whimsical loop for random events and funny choices. | E12: P1
A13: ☐ | B13: bgm_rest_cozy_loop | C13: audio/bgm/ | D13: Relaxed safe-room loop for rest nodes and recovery. | E13: P1
A14: ☐ | B14: bgm_treasure_twinkle_loop | C14: audio/bgm/ | D14: Sparkly treasure-room loop with magical chest energy. | E14: P1
A15: ☐ | B15: bgm_victory_fanfare | C15: audio/bgm/ | D15: Short bright fanfare for battle victory and room completion. | E15: P0
... A30: ☐ | B30: bgm_boss_king_bloxley_loop | C30: audio/bgm/ | D30: Final boss loop: royal, dramatic, funny, and energetic. | E30: P0

Sheet 02 Ambient Audio
A1: 2. Ambient Audio Assets
A2: Tracking sheet generated from the uploaded markdown. Done? is unchecked by default.
A4: Done? | B4: Asset Key | C4: Suggested Folder | D4: Designer Description | E4: Priority
A5: ☐ | B5: amb_festival_crowd_loop | C5: audio/ambience/ | D5: Looping cozy festival crowd, distant cheering, soft chatter, no harsh voices. | E5: P1
A6: ☐ | B6: amb_stage_sprinkle_sewers_loop | C6: audio/ambience/ | D6: Bubbling candy water, frosting pipe drips, sweet sewer ambience. | E6: P1
A7: ☐ | B7: amb_stage_goblin_workshop_loop | C7: audio/ambience/ | D7: Small machine hums, gear clicks, springs, distant safe-looking explosions. | E7: P1
A8: ☐ | B8: amb_stage_frosty_pantry_loop | C8: audio/ambience/ | D8: Freezer hum, ice sparkle, soft cold wind loop. | E8: P1
A9: ☐ | B9: amb_stage_pillow_castle_loop | C9: audio/ambience/ | D9: Soft fabric rustle, toy squeaks, sleepy castle hush. | E9: P2
A10: ☐ | B10: amb_stage_starfall_arcade_loop | C10: audio/ambience/ | D10: Arcade cabinet beeps, ticket machine sounds, neon hum. | E10: P2
A11: ☐ | B11: amb_stage_bloxley_block_palace_loop | C11: audio/ambience/ | D11: Toy palace ambience with flags, confetti cannons, distant royal trumpets. | E11: P2
A12: ☐ | B12: amb_shop_small_bells_loop | C12: audio/ambience/ | D12: Gentle shop bell and shelf sparkle loop under shop BGM. | E12: P2
A13: ☐ | B13: amb_treasure_sparkle_loop | C13: audio/ambience/ | D13: Low magical shimmer for treasure room. | E13: P2

Sheet 03 SFX - Board
A1: 3. Sound Effect Assets — Board
A2: Tracking sheet generated from the uploaded markdown. Done? is unchecked by default.
A4: Done? | B4: Asset Key | C4: Suggested Folder | D4: Designer Description | E4: Priority
A5: ☐ | B5: sfx_board_piece_spawn | C5: audio/sfx/board/ | D5: Tiny magical plop when a new piece enters the board. | E5: P0
A6: ☐ | B6: sfx_board_piece_move | C6: audio/sfx/board/ | D6: Short soft tick for moving piece left or right. | E6: P0
A7: ☐ | B7: sfx_board_piece_rotate | C7: audio/sfx/board/ | D7: Quick twist/pop sound for rotating a piece. | E7: P0
A8: ☐ | B8: sfx_board_piece_soft_drop | C8: audio/sfx/board/ | D8: Light repeated drop tap for soft drop movement. | E8: P1
A9: ☐ | B9: sfx_board_piece_hard_drop | C9: audio/sfx/board/ | D9: Satisfying thump for instant hard drop. | E9: P0
A10: ☐ | B10: sfx_board_piece_lock | C10: audio/sfx/board/ | D10: Soft lock-in click when a piece lands. | E10: P0
A11: ☐ | B11: sfx_board_hold_piece | C11: audio/sfx/board/ | D11: Magical swap sound for hold action. | E11: P0
A12: ☐ | B12: sfx_board_swap_next_hold | C12: audio/sfx/board/ | D12: Readable queue swap sound for effects that swap Next/Hold. | E12: P1
A13: ☐ | B13: sfx_board_line_clear | C13: audio/sfx/board/ | D13: Bright clear sound for one or small line clear. | E13: P0
A14: ☐ | B14: sfx_board_line_clear_big | C14: audio/sfx/board/ | D14: Bigger sparkling clear sound for multi-line clear. | E14: P0
A15: ☐ | B15: sfx_board_cascade_1 | C15: audio/sfx/board/ | D15: First cascade pop, small and satisfying. | E15: P0
... A24: ☐ | B24: sfx_board_overflow_defeat | C24: audio/sfx/board/ | D24: Soft pile-collapse sound for overflow defeat, not scary. | E24: P0

Sheet 04 SFX - Special Blocks
A1: 4. Sound Effect Assets — Special Blocks
A2: Tracking sheet generated from the uploaded markdown. Done? is unchecked by default.
A4: Done? | B4: Asset Key | C4: Suggested Folder | D4: Designer Description | E4: Priority
A5: ☐ | B5: sfx_block_sprinkle_clear | C5: audio/sfx/blocks/ | D5: Tiny candy sparkle when a Sprinkle Block clears. | E5: P1
A6: ☐ | B6: sfx_block_cupcake_clear | C6: audio/sfx/blocks/ | D6: Soft frosting pop when a Cupcake Block heals. | E6: P1
A7: ☐ | B7: sfx_block_bomb_explode | C7: audio/sfx/blocks/ | D7: Cute toy-bomb pop for Bomb Block explosion. | E7: P0
A8: ☐ | B8: sfx_block_star_clear | C8: audio/sfx/blocks/ | D8: Magical star chime for Star Block clear. | E8: P1
A9: ☐ | B9: sfx_block_jelly_bounce | C9: audio/sfx/blocks/ | D9: Wobbly jelly bounce sound during cascade/fall. | E9: P1
A10: ☐ | B10: sfx_block_ice_crack | C10: audio/sfx/blocks/ | D10: Light ice crack for Ice Block break or thaw. | E10: P1
A11: ☐ | B11: sfx_block_sticky_squish | C11: audio/sfx/blocks/ | D11: Sticky candy squish when Sticky Block moves or clears. | E11: P1
A12: ☐ | B12: sfx_block_crumb_junk_land | C12: audio/sfx/blocks/ | D12: Crumbly junk landing sound, readable but not harsh. | E12: P0
A13: ☐ | B13: sfx_block_royal_spawn | C13: audio/sfx/blocks/ | D13: Small royal trumpet pop when a Royal Block appears. | E13: P1
A14: ☐ | B14: sfx_block_royal_clear | C14: audio/sfx/blocks/ | D14: Regal sparkle when a Royal Block is cleared. | E14: P1
A15: ☐ | B15: sfx_block_confetti_pop | C15: audio/sfx/blocks/ | D15: Party popper burst for Confetti Block effect. | E15: P1
... A22: ☐ | B22: sfx_block_cracked_junk_break | C22: audio/sfx/blocks/ | D22: Second hit crumble sound for Cracked Junk breaking. | E22: P2

Sheet 05 SFX - Combat
A1: 5. Sound Effect Assets — Combat
A2: Tracking sheet generated from the uploaded markdown. Done? is unchecked by default.
A4: Done? | B4: Asset Key | C4: Suggested Folder | D4: Designer Description | E4: Priority
A5: ☐ | B5: sfx_combat_enemy_hit | C5: audio/sfx/combat/ | D5: Readable cute hit impact for enemy damage. | E5: P0
A6: ☐ | B6: sfx_combat_enemy_defeat | C6: audio/sfx/combat/ | D6: Enemy poof/pop defeat sound, playful not violent. | E6: P0
A7: ☐ | B7: sfx_combat_player_hit | C7: audio/sfx/combat/ | D7: Soft player hit cue that feels dangerous but lighthearted. | E7: P0
A8: ☐ | B8: sfx_combat_player_heal | C8: audio/sfx/combat/ | D8: Warm sparkle for healing. | E8: P0
A9: ☐ | B9: sfx_combat_player_shield_gain | C9: audio/sfx/combat/ | D9: Bubble/shield forming sound. | E9: P1
A10: ☐ | B10: sfx_combat_shield_break | C10: audio/sfx/combat/ | D10: Tiny bubble crack when shield breaks. | E10: P1
A11: ☐ | B11: sfx_combat_enemy_intent_warning | C11: audio/sfx/combat/ | D11: Attention cue when enemy intent becomes dangerous. | E11: P0
A12: ☐ | B12: sfx_combat_enemy_attack_basic | C12: audio/sfx/combat/ | D12: Simple enemy attack pop/bonk. | E12: P0
A13: ☐ | B13: sfx_combat_enemy_attack_junk | C13: audio/sfx/combat/ | D13: Crumb junk preparation/drop cue. | E13: P0
A14: ☐ | B14: sfx_combat_enemy_attack_freeze | C14: audio/sfx/combat/ | D14: Frost wave cue for freeze enemy attack. | E14: P1
A15: ☐ | B15: sfx_combat_enemy_attack_sleep | C15: audio/sfx/combat/ | D15: Yawn/sleep sparkle cue for Sleepy attacks. | E15: P1
... A21: ☐ | B21: sfx_combat_defeat | C21: audio/sfx/combat/ | D21: Gentle defeat cue for Game Over transition. | E21: P0

Sheet 06 SFX - Spells
A1: 6. Sound Effect Assets — Spells
A2: Tracking sheet generated from the uploaded markdown. Done? is unchecked by default.
A4: Done? | B4: Asset Key | C4: Suggested Folder | D4: Designer Description | E4: Priority
A5: ☐ | B5: sfx_spl_fireball_cast | C5: audio/sfx/spells/ | D5: Cast sound for Fireball. Fire damage; should feel like Pippa preheating the enemy. | E5: P1
A6: ☐ | B6: sfx_spl_frost_lock_cast | C6: audio/sfx/spells/ | D6: Cast sound for Frost Lock. Control spell; chills fall speed or freezes enemy timing. | E6: P1
A7: ☐ | B7: sfx_spl_bomb_rune_cast | C7: audio/sfx/spells/ | D7: Cast sound for Bomb Rune. Board-clear spell; creates a toy bomb area clear. | E7: P1
A8: ☐ | B8: sfx_spl_clean_cut_cast | C8: audio/sfx/spells/ | D8: Cast sound for Clean Cut. Precise cleanup spell that clears a row or messy pattern. | E8: P1
A9: ☐ | B9: sfx_spl_sprinkle_shower_cast | C9: audio/sfx/spells/ | D9: Cast sound for Sprinkle Shower. Candy mana spell that rains helpful sprinkles. | E9: P1
A10: ☐ | B10: sfx_spl_cupcake_blast_cast | C10: audio/sfx/spells/ | D10: Cast sound for Cupcake Blast. Sweet damage/heal spell with frosting burst. | E10: P1
A11: ☐ | B11: sfx_spl_confetti_pop_cast | C11: audio/sfx/spells/ | D11: Cast sound for Confetti Pop. Party spell that clears random cells with colorful chaos. | E11: P1
A12: ☐ | B12: sfx_spl_bubble_shield_cast | C12: audio/sfx/spells/ | D12: Cast sound for Bubble Shield. Defensive spell that creates a soft protective bubble. | E12: P1
A13: ☐ | B13: sfx_spl_star_spark_cast | C13: audio/sfx/spells/ | D13: Cast sound for Star Spark. Combo-scaling star spell for cascade play. | E13: P1
A14: ☐ | B14: sfx_spl_jelly_bounce_cast | C14: audio/sfx/spells/ | D14: Cast sound for Jelly Bounce. Utility spell that delays enemy or bounces board pressure. | E14: P1
A15: ☐ | B15: sfx_spl_snowcone_burst_cast | C15: audio/sfx/spells/ | D15: Cast sound for Snowcone Burst. Frost burst that delays or freezes enemy action. | E15: P1
... A19: ☐ | B19: sfx_spl_cascade_cheer_cast | C19: audio/sfx/spells/ | D19: Cast sound for Cascade Cheer. Combo support spell that boosts next cascade reward. | E19: P1

Sheet 07 SFX - UI
A1: 7. Sound Effect Assets — UI
A2: Tracking sheet generated from the uploaded markdown. Done? is unchecked by default.
A4: Done? | B4: Asset Key | C4: Suggested Folder | D4: Designer Description | E4: Priority
A5: ☐ | B5: sfx_ui_button_tap | C5: audio/sfx/ui/ | D5: Light tap for common button press. | E5: P0
A6: ☐ | B6: sfx_ui_button_confirm | C6: audio/sfx/ui/ | D6: Positive confirmation cue for accepted action. | E6: P0
A7: ☐ | B7: sfx_ui_button_cancel | C7: audio/sfx/ui/ | D7: Soft back/cancel cue. | E7: P0
A8: ☐ | B8: sfx_ui_button_disabled | C8: audio/sfx/ui/ | D8: Cute blocked cue for invalid/disabled action. | E8: P0
A9: ☐ | B9: sfx_ui_menu_open | C9: audio/sfx/ui/ | D9: Panel opening sound with magical slide. | E9: P1
A10: ☐ | B10: sfx_ui_menu_close | C10: audio/sfx/ui/ | D10: Panel closing sound with soft click. | E10: P1
A11: ☐ | B11: sfx_ui_card_flip | C11: audio/sfx/ui/ | D11: Reward/card reveal flip sound. | E11: P1
A12: ☐ | B12: sfx_ui_reward_pick | C12: audio/sfx/ui/ | D12: Sparkly cue for choosing a reward. | E12: P0
A13: ☐ | B13: sfx_ui_shop_purchase | C13: audio/sfx/ui/ | D13: Cash/register bell for successful purchase. | E13: P0
A14: ☐ | B14: sfx_ui_shop_error | C14: audio/sfx/ui/ | D14: Friendly error cue for not enough gold. | E14: P0
A15: ☐ | B15: sfx_ui_inventory_open | C15: audio/sfx/ui/ | D15: Bag/pouch opening sound for inventory panel. | E15: P1
... A23: ☐ | B23: sfx_ui_map_path_unlock | C23: audio/sfx/ui/ | D23: Map route unlock sparkle/path draw cue. | E23: P1

Sheet 08 BG - Scenes
A1: 8. Background Assets — Scenes
A2: Tracking sheet generated from the uploaded markdown. Done? is unchecked by default.
A4: Done? | B4: Asset Key | C4: Suggested Folder | D4: Designer Description | E4: Priority
A5: ☐ | B5: bg_scene_title_festival | C5: backgrounds/scenes/ | D5: Title screen image showing Brixonia festival, falling stars, and playful blocks. | E5: P0
A6: ☐ | B6: bg_scene_main_menu | C6: backgrounds/scenes/ | D6: Main menu scene with cozy arcade-festival framing. | E6: P0
A7: ☐ | B7: bg_scene_hub_brixonia | C7: backgrounds/scenes/ | D7: Festival hub overview with booths, lanterns, and colorful magical mess. | E7: P1
A8: ☐ | B8: bg_scene_hero_select | C8: backgrounds/scenes/ | D8: Hero select backdrop with stage or festival booth silhouettes. | E8: P1
A9: ☐ | B9: bg_scene_tutorial | C9: backgrounds/scenes/ | D9: Simple classroom/festival demo area for learning controls. | E9: P1
A10: ☐ | B10: bg_scene_reward | C10: backgrounds/scenes/ | D10: Reward backdrop with sparkles, cards, and treasure glow. | E10: P0
A11: ☐ | B11: bg_scene_shop | C11: backgrounds/scenes/ | D11: Marnie’s cozy merchant stall filled with snacks and items. | E11: P0
A12: ☐ | B12: bg_scene_event | C12: backgrounds/scenes/ | D12: Generic event backdrop with flexible festival/dungeon props. | E12: P1
A13: ☐ | B13: bg_scene_rest | C13: backgrounds/scenes/ | D13: Safe rest spot with pillows, snacks, and warm lanterns. | E13: P1
A14: ☐ | B14: bg_scene_treasure | C14: backgrounds/scenes/ | D14: Treasure room with glowing chest and playful sparkles. | E14: P1
A15: ☐ | B15: bg_scene_game_over | C15: backgrounds/scenes/ | D15: Soft defeat backdrop with block pile and encouraging restart tone. | E15: P0
... A19: ☐ | B19: bg_scene_settings | C19: backgrounds/scenes/ | D19: Simple readable settings backdrop with cozy UI frame. | E19: P1

Sheet 09 BG - Stage Battle Parallax
A1: 9. Background Assets — Stage Battle Parallax
A2: Tracking sheet generated from the uploaded markdown. Done? is unchecked by default.
A4: Done? | B4: Asset Key | C4: Suggested Folder | D4: Designer Description | E4: Priority
A5: ☐ | B5: bg_stage_sprinkle_sewers_battle_far | C5: backgrounds/stages/ | D5: Sprinkle Sewers battle background distant parallax layer; show candy sewer with rainbow water, frosting pipes, and cupcake slime colors. | E5: P0
A6: ☐ | B6: bg_stage_sprinkle_sewers_battle_mid | C6: backgrounds/stages/ | D6: Sprinkle Sewers battle background main scenic layer; show candy sewer with rainbow water, frosting pipes, and cupcake slime colors. | E6: P0
A7: ☐ | B7: bg_stage_sprinkle_sewers_battle_near | C7: backgrounds/stages/ | D7: Sprinkle Sewers battle background foreground framing layer; show candy sewer with rainbow water, frosting pipes, and cupcake slime colors. | E7: P0
A8: ☐ | B8: bg_stage_goblin_workshop_battle_far | C8: backgrounds/stages/ | D8: Goblin Workshop battle background distant parallax layer; show goblin machinery, toy bombs, springs, gears, and warning signs. | E8: P0
A9: ☐ | B9: bg_stage_goblin_workshop_battle_mid | C9: backgrounds/stages/ | D9: Goblin Workshop battle background main scenic layer; show goblin machinery, toy bombs, springs, gears, and warning signs. | E9: P0
A10: ☐ | B10: bg_stage_goblin_workshop_battle_near | C10: backgrounds/stages/ | D10: Goblin Workshop battle background foreground framing layer; show goblin machinery, toy bombs, springs, gears, and warning signs. | E10: P0
A11: ☐ | B11: bg_stage_frosty_pantry_battle_far | C11: backgrounds/stages/ | D11: Frosty Pantry battle background distant parallax layer; show magical freezer with ice cream crates, cold mist, and slippery tiles. | E11: P1
A12: ☐ | B12: bg_stage_frosty_pantry_battle_mid | C12: backgrounds/stages/ | D12: Frosty Pantry battle background main scenic layer; show magical freezer with ice cream crates, cold mist, and slippery tiles. | E12: P1
A13: ☐ | B13: bg_stage_frosty_pantry_battle_near | C13: backgrounds/stages/ | D13: Frosty Pantry battle background foreground framing layer; show magical freezer with ice cream crates, cold mist, and slippery tiles. | E13: P1
A14: ☐ | B14: bg_stage_pillow_castle_battle_far | C14: backgrounds/stages/ | D14: Pillow Castle battle background distant parallax layer; show soft pillow fortress with plush toys, blankets, and sleepy fabric shapes. | E14: P1
A15: ☐ | B15: bg_stage_pillow_castle_battle_mid | C15: backgrounds/stages/ | D15: Pillow Castle battle background main scenic layer; show soft pillow fortress with plush toys, blankets, and sleepy fabric shapes. | E15: P1
... A22: ☐ | B22: bg_stage_bloxley_block_palace_battle_near | C22: backgrounds/stages/ | D22: Bloxley’s Block Palace battle background foreground framing layer; show royal block palace with square banners, confetti cannons, and toy flags. | E22: P1

Sheet 10 BG - Boss Arenas
A1: 10. Background Assets — Boss Arenas
A2: Tracking sheet generated from the uploaded markdown. Done? is unchecked by default.
A4: Done? | B4: Asset Key | C4: Suggested Folder | D4: Designer Description | E4: Priority
A5: ☐ | B5: bg_boss_cupcake_slime_king_arena | C5: backgrounds/stages/ | D5: Boss-specific arena for Cupcake Slime King: sticky candy sewer boss arena with frosting puddles and giant cupcake slime throne. | E5: P1
A6: ☐ | B6: bg_boss_prototype_no_7_arena | C6: backgrounds/stages/ | D6: Boss-specific arena for Prototype No. 7: malfunctioning workshop arena with safe-looking machines and bomb props. | E6: P1
A7: ☐ | B7: bg_boss_gelato_golem_arena | C7: backgrounds/stages/ | D7: Boss-specific arena for Gelato Golem: freezer boss arena with melting rainbow gelato and ice platforms. | E7: P1
A8: ☐ | B8: bg_boss_sir_snore_a_lot_arena | C8: backgrounds/stages/ | D8: Boss-specific arena for Sir Snore-a-Lot: pillow castle boss arena with blanket banners and sleepy toy shields. | E8: P1
A9: ☐ | B9: bg_boss_high_score_hydra_arena | C9: backgrounds/stages/ | D9: Boss-specific arena for High Score Hydra: arcade boss arena with scoreboard, neon combo lights, and hydra cabinet energy. | E9: P1
A10: ☐ | B10: bg_boss_king_bloxley_arena | C10: backgrounds/stages/ | D10: Boss-specific arena for King Bloxley: final royal block throne room with symmetry marks and confetti cannons. | E10: P1

Sheet 11 Map - Map BGs
A1: 11. Map Assets — Map Backgrounds
A2: Tracking sheet generated from the uploaded markdown. Done? is unchecked by default.
A4: Done? | B4: Asset Key | C4: Suggested Folder | D4: Designer Description | E4: Priority
A5: ☐ | B5: bg_map_sprinkle_sewers | C5: backgrounds/maps/ | D5: Roguelike map background for Sprinkle Sewers; use icons/paths over this readable stage map. | E5: P0
A6: ☐ | B6: bg_map_goblin_workshop | C6: backgrounds/maps/ | D6: Roguelike map background for Goblin Workshop; use icons/paths over this readable stage map. | E6: P1
A7: ☐ | B7: bg_map_frosty_pantry | C7: backgrounds/maps/ | D7: Roguelike map background for Frosty Pantry; use icons/paths over this readable stage map. | E7: P1
A8: ☐ | B8: bg_map_pillow_castle | C8: backgrounds/maps/ | D8: Roguelike map background for Pillow Castle; use icons/paths over this readable stage map. | E8: P1
A9: ☐ | B9: bg_map_starfall_arcade | C9: backgrounds/maps/ | D9: Roguelike map background for Starfall Arcade; use icons/paths over this readable stage map. | E9: P1
A10: ☐ | B10: bg_map_bloxley_block_palace | C10: backgrounds/maps/ | D10: Roguelike map background for Bloxley’s Block Palace; use icons/paths over this readable stage map. | E10: P1

Sheet 12 Map - Node States
A1: 12. Map Assets — Node States
A2: Tracking sheet generated from the uploaded markdown. Done? is unchecked by default.
A4: Done? | B4: Asset Key | C4: Suggested Folder | D4: Designer Description | E4: Priority
A5: ☐ | B5: map_node_start_locked | C5: map/nodes/ | D5: Start node, safe and friendly entry point. Unavailable gray/low-saturation state. Must be readable at mobile size. | E5: P0
A6: ☐ | B6: map_node_start_available | C6: map/nodes/ | D6: Start node, safe and friendly entry point. Selectable glowing state. Must be readable at mobile size. | E6: P0
A7: ☐ | B7: map_node_start_current | C7: map/nodes/ | D7: Start node, safe and friendly entry point. Current player position state. Must be readable at mobile size. | E7: P0
A8: ☐ | B8: map_node_start_completed | C8: map/nodes/ | D8: Start node, safe and friendly entry point. Completed checked/cleared state. Must be readable at mobile size. | E8: P0
A9: ☐ | B9: map_node_normal_locked | C9: map/nodes/ | D9: Normal battle node with small monster symbol. Unavailable gray/low-saturation state. Must be readable at mobile size. | E9: P0
A10: ☐ | B10: map_node_normal_available | C10: map/nodes/ | D10: Normal battle node with small monster symbol. Selectable glowing state. Must be readable at mobile size. | E10: P0
A11: ☐ | B11: map_node_normal_current | C11: map/nodes/ | D11: Normal battle node with small monster symbol. Current player position state. Must be readable at mobile size. | E11: P0
A12: ☐ | B12: map_node_normal_completed | C12: map/nodes/ | D12: Normal battle node with small monster symbol. Completed checked/cleared state. Must be readable at mobile size. | E12: P0
A13: ☐ | B13: map_node_elite_locked | C13: map/nodes/ | D13: Elite battle node with stronger warning frame. Unavailable gray/low-saturation state. Must be readable at mobile size. | E13: P1
A14: ☐ | B14: map_node_elite_available | C14: map/nodes/ | D14: Elite battle node with stronger warning frame. Selectable glowing state. Must be readable at mobile size. | E14: P1
A15: ☐ | B15: map_node_elite_current | C15: map/nodes/ | D15: Elite battle node with stronger warning frame. Current player position state. Must be readable at mobile size. | E15: P1
... A44: ☐ | B44: map_node_mini_boss_completed | C44: map/nodes/ | D44: Mini-boss or royal guard node before final boss. Completed checked/cleared state. Must be readable at mobile size. | E44: P1

Sheet 13 Map - Paths and Decorations
A1: 13. Map Assets — Paths and Decorations
A2: Tracking sheet generated from the uploaded markdown. Done? is unchecked by default.
A4: Done? | B4: Asset Key | C4: Suggested Folder | D4: Designer Description | E4: Priority
A5: ☐ | B5: map_path_line_locked | C5: map/paths/ | D5: Thin muted line showing locked route connection. | E5: P0
A6: ☐ | B6: map_path_line_available | C6: map/paths/ | D6: Clear readable line showing selectable route connection. | E6: P0
A7: ☐ | B7: map_path_line_completed | C7: map/paths/ | D7: Route line showing already traveled path. | E7: P0
A8: ☐ | B8: map_path_dotted_locked | C8: map/paths/ | D8: Optional dotted locked route style for alternate branches. | E8: P1
A9: ☐ | B9: map_path_glow_available | C9: map/paths/ | D9: Glowing route overlay for newly opened path. | E9: P1
A10: ☐ | B10: map_deco_sprinkle_sewers_cupcake_pipe | C10: map/decorations/ | D10: Small cupcake/frosting pipe decoration for Stage 1 map. | E10: P2
A11: ☐ | B11: map_deco_goblin_workshop_gear | C11: map/decorations/ | D11: Small gear/spring decoration for Stage 2 map. | E11: P2
A12: ☐ | B12: map_deco_frosty_pantry_ice_crate | C12: map/decorations/ | D12: Ice cream crate decoration for Stage 3 map. | E12: P2
A13: ☐ | B13: map_deco_pillow_castle_blanket_flag | C13: map/decorations/ | D13: Blanket flag decoration for Stage 4 map. | E13: P2
A14: ☐ | B14: map_deco_starfall_arcade_neon_sign | C14: map/decorations/ | D14: Neon sign decoration for Stage 5 map. | E14: P2
A15: ☐ | B15: map_deco_bloxley_block_palace_royal_seal | C15: map/decorations/ | D15: Royal seal decoration for Stage 6 map. | E15: P2

Sheet 14 - Heroes
A1: 14. Sprite Assets — Playable Heroes
A2: Tracking sheet generated from the uploaded markdown. Done? is unchecked by default.
A4: Done? | B4: Asset Key | C4: Suggested Folder | D4: Designer Description | E4: Priority
A5: ☐ | B5: spr_hero_milo_blockmancer_idle | C5: sprites/heroes/ | D5: Milo: Neutral battle idle; loopable and readable in top battle panel. Character direction: balanced starter Blockmancer, optimistic apprentice with lemonade-assistant charm. | E5: P0
A6: ☐ | B6: spr_hero_milo_blockmancer_cast | C6: sprites/heroes/ | D6: Milo: Spell-casting pose with clear silhouette and hand/wand motion. Character direction: balanced starter Blockmancer, optimistic apprentice with lemonade-assistant charm. | E6: P0
A7: ☐ | B7: spr_hero_milo_blockmancer_attack | C7: sprites/heroes/ | D7: Milo: Quick attack pose for line-clear damage feedback. Character direction: balanced starter Blockmancer, optimistic apprentice with lemonade-assistant charm. | E7: P0
A8: ☐ | B8: spr_hero_milo_blockmancer_hit | C8: sprites/heroes/ | D8: Milo: Short hurt/flinch pose, cute but readable. Character direction: balanced starter Blockmancer, optimistic apprentice with lemonade-assistant charm. | E8: P0
A9: ☐ | B9: spr_hero_milo_blockmancer_victory | C9: sprites/heroes/ | D9: Milo: Celebration pose for room clear and hero select preview. Character direction: balanced starter Blockmancer, optimistic apprentice with lemonade-assistant charm. | E9: P0
A10: ☐ | B10: spr_hero_milo_blockmancer_defeat | C10: sprites/heroes/ | D10: Milo: Soft defeat/tired pose without grim tone. Character direction: balanced starter Blockmancer, optimistic apprentice with lemonade-assistant charm. | E10: P0
A11: ☐ | B11: spr_hero_milo_blockmancer_portrait | C11: sprites/heroes/ | D11: Milo: Large dialogue/hero-select portrait with expressive face. Character direction: balanced starter Blockmancer, optimistic apprentice with lemonade-assistant charm. | E11: P0
A12: ☐ | B12: spr_hero_milo_blockmancer_silhouette_locked | C12: sprites/heroes/ | D12: Milo: Locked hero silhouette; recognizable but not fully revealed. Character direction: balanced starter Blockmancer, optimistic apprentice with lemonade-assistant charm. | E12: P0
A13: ☐ | B13: ico_hero_milo_blockmancer | C13: icons/heroes/ | D13: Milo small icon for hero select, save slot, HUD, and unlock UI. | E13: P0
A14: ☐ | B14: spr_hero_pippa_pyromancer_idle | C14: sprites/heroes/ | D14: Pippa: Neutral battle idle; loopable and readable in top battle panel. Character direction: festival baker pyromancer, energetic and cupcake-protective. | E14: P1
A15: ☐ | B15: spr_hero_pippa_pyromancer_cast | C15: sprites/heroes/ | D15: Pippa: Spell-casting pose with clear silhouette and hand/wand motion. Character direction: festival baker pyromancer, energetic and cupcake-protective. | E15: P1
... A58: ☐ | B58: ico_hero_lumi_star_witch | C58: icons/heroes/ | D58: Lumi small icon for hero select, save slot, HUD, and unlock UI. | E58: P1

Sheet 15 - Monsters
A1: 15. Sprite Assets — Regular Monsters
A2: Tracking sheet generated from the uploaded markdown. Done? is unchecked by default.
A4: Done? | B4: Asset Key | C4: Suggested Folder | D4: Designer Description | E4: Priority
A5: ☐ | B5: spr_mon_cupcake_slime_idle | C5: sprites/monsters/ | D5: Cupcake Slime: Loopable battle idle, cute and readable in small top battle panel. Direction: slime wearing whipped cream; basic enemy that drops sprinkles. | E5: P0
A6: ☐ | B6: spr_mon_cupcake_slime_attack | C6: sprites/monsters/ | D6: Cupcake Slime: Attack animation pose matching its behavior. Direction: slime wearing whipped cream; basic enemy that drops sprinkles. | E6: P0
A7: ☐ | B7: spr_mon_cupcake_slime_hit | C7: sprites/monsters/ | D7: Cupcake Slime: Short squash/flinch response when damaged. Direction: slime wearing whipped cream; basic enemy that drops sprinkles. | E7: P0
A8: ☐ | B8: spr_mon_cupcake_slime_defeat | C8: sprites/monsters/ | D8: Cupcake Slime: Playful poof or calm-down defeat, no gore. Direction: slime wearing whipped cream; basic enemy that drops sprinkles. | E8: P0
A9: ☐ | B9: ico_mon_cupcake_slime | C9: icons/monsters/ | D9: Cupcake Slime compact icon for bestiary, intent UI, debug spawn, or friendship screen. | E9: P1
A10: ☐ | B10: spr_mon_sugar_bat_idle | C10: sprites/monsters/ | D10: Sugar Bat: Loopable battle idle, cute and readable in small top battle panel. Direction: small candy-rushed bat; disrupts next preview. | E10: P0
A11: ☐ | B11: spr_mon_sugar_bat_attack | C11: sprites/monsters/ | D11: Sugar Bat: Attack animation pose matching its behavior. Direction: small candy-rushed bat; disrupts next preview. | E11: P0
A12: ☐ | B12: spr_mon_sugar_bat_hit | C12: sprites/monsters/ | D12: Sugar Bat: Short squash/flinch response when damaged. Direction: small candy-rushed bat; disrupts next preview. | E12: P0
A13: ☐ | B13: spr_mon_sugar_bat_defeat | C13: sprites/monsters/ | D13: Sugar Bat: Playful poof or calm-down defeat, no gore. Direction: small candy-rushed bat; disrupts next preview. | E13: P0
A14: ☐ | B14: ico_mon_sugar_bat | C14: icons/monsters/ | D14: Sugar Bat compact icon for bestiary, intent UI, debug spawn, or friendship screen. | E14: P1
A15: ☐ | B15: spr_mon_crumb_goblin_idle | C15: sprites/monsters/ | D15: Crumb Goblin: Loopable battle idle, cute and readable in small top battle panel. Direction: tiny cookie crumb goblin; throws crumb junk. | E15: P0
... A184: ☐ | B184: ico_mon_banner_bug | C184: icons/monsters/ | D184: Banner Bug compact icon for bestiary, intent UI, debug spawn, or friendship screen. | E184: P1

Sheet 16 - Bosses
A1: 16. Sprite Assets — Bosses
A2: Tracking sheet generated from the uploaded markdown. Done? is unchecked by default.
A4: Done? | B4: Asset Key | C4: Suggested Folder | D4: Designer Description | E4: Priority
A5: ☐ | B5: spr_boss_cupcake_slime_king_idle | C5: sprites/bosses/ | D5: Cupcake Slime King: Large boss idle loop with strong silhouette and stage personality. Arena/character direction: sticky candy sewer boss arena with frosting puddles and giant cupcake slime throne. | E5: P0
A6: ☐ | B6: spr_boss_cupcake_slime_king_attack | C6: sprites/bosses/ | D6: Cupcake Slime King: Main attack pose for basic boss action. Arena/character direction: sticky candy sewer boss arena with frosting puddles and giant cupcake slime throne. | E6: P0
A7: ☐ | B7: spr_boss_cupcake_slime_king_special | C7: sprites/bosses/ | D7: Cupcake Slime King: Unique mechanic pose for boss gimmick. Arena/character direction: sticky candy sewer boss arena with frosting puddles and giant cupcake slime throne. | E7: P0
A8: ☐ | B8: spr_boss_cupcake_slime_king_phase_2 | C8: sprites/bosses/ | D8: Cupcake Slime King: Altered phase-two visual state, readable but not completely new boss. Arena/character direction: sticky candy sewer boss arena with frosting puddles and giant cupcake slime throne. | E8: P0
A9: ☐ | B9: spr_boss_cupcake_slime_king_hit | C9: sprites/bosses/ | D9: Cupcake Slime King: Heavy hit reaction without scary violence. Arena/character direction: sticky candy sewer boss arena with frosting puddles and giant cupcake slime throne. | E9: P0
A10: ☐ | B10: spr_boss_cupcake_slime_king_defeat | C10: sprites/bosses/ | D10: Cupcake Slime King: Big playful defeat/calm-down animation. Arena/character direction: sticky candy sewer boss arena with frosting puddles and giant cupcake slime throne. | E10: P0
A11: ☐ | B11: spr_boss_cupcake_slime_king_intro_portrait | C11: sprites/bosses/ | D11: Cupcake Slime King: Large intro/rule-card portrait with expressive personality. Arena/character direction: sticky candy sewer boss arena with frosting puddles and giant cupcake slime throne. | E11: P0
A12: ☐ | B12: ico_boss_cupcake_slime_king | C12: icons/bosses/ | D12: Cupcake Slime King compact icon for map boss node, boss rule card, and debug tools. | E12: P1
A13: ☐ | B13: ico_boss_rule_boss_cupcake_slime_king | C13: icons/boss-rules/ | D13: Cupcake Slime King rule-card icon representing the boss gimmick clearly. | E13: P1
A14: ☐ | B14: spr_boss_prototype_no_7_idle | C14: sprites/bosses/ | D14: Prototype No. 7: Large boss idle loop with strong silhouette and stage personality. Arena/character direction: malfunctioning workshop arena with safe-looking machines and bomb props. | E14: P1
A15: ☐ | B15: spr_boss_prototype_no_7_attack | C15: sprites/bosses/ | D15: Prototype No. 7: Main attack pose for basic boss action. Arena/character direction: malfunctioning workshop arena with safe-looking machines and bomb props. | E15: P1
... A58: ☐ | B58: ico_boss_rule_boss_king_bloxley | C58: icons/boss-rules/ | D58: King Bloxley rule-card icon representing the boss gimmick clearly. | E58: P1

Sheet 17 - NPCs
A1: 17. Sprite Assets — NPCs
A2: Tracking sheet generated from the uploaded markdown. Done? is unchecked by default.
A4: Done? | B4: Asset Key | C4: Suggested Folder | D4: Designer Description | E4: Priority
A5: ☐ | B5: spr_npc_professor_poplin_idle | C5: sprites/npcs/ | D5: Professor Poplin small idle sprite. Direction: inventor/tutorial wizard; excited, absent-minded, harmless. | E5: P1
A6: ☐ | B6: spr_npc_professor_poplin_portrait | C6: sprites/npcs/ | D6: Professor Poplin dialogue portrait with strong expression and readable face. | E6: P1
A7: ☐ | B7: ico_npc_professor_poplin | C7: icons/npcs/ | D7: Professor Poplin compact icon for dialogue headers, map/shop/event labels. | E7: P2
A8: ☐ | B8: spr_npc_marnie_merchant_idle | C8: sprites/npcs/ | D8: Marnie the Merchant small idle sprite. Direction: general shop NPC; warm, practical, festival-stall energy. | E8: P1
A9: ☐ | B9: spr_npc_marnie_merchant_portrait | C9: sprites/npcs/ | D9: Marnie the Merchant dialogue portrait with strong expression and readable face. | E9: P1
A10: ☐ | B10: ico_npc_marnie_merchant | C10: icons/npcs/ | D10: Marnie the Merchant compact icon for dialogue headers, map/shop/event labels. | E10: P2
A11: ☐ | B11: spr_npc_ticket_imp_idle | C11: sprites/npcs/ | D11: Ticket Imp small idle sprite. Direction: arcade/event NPC; mischievous but friendly. | E11: P1
A12: ☐ | B12: spr_npc_ticket_imp_portrait | C12: sprites/npcs/ | D12: Ticket Imp dialogue portrait with strong expression and readable face. | E12: P1
A13: ☐ | B13: ico_npc_ticket_imp | C13: icons/npcs/ | D13: Ticket Imp compact icon for dialogue headers, map/shop/event labels. | E13: P2
A14: ☐ | B14: spr_npc_bloop_idle | C14: sprites/npcs/ | D14: Bloop small idle sprite. Direction: friendly slime NPC; simple expressive blob. | E14: P1
A15: ☐ | B15: spr_npc_bloop_portrait | C15: sprites/npcs/ | D15: Bloop dialogue portrait with strong expression and readable face. | E15: P1
... A28: ☐ | B28: ico_npc_repair_sprite | C28: icons/npcs/ | D28: Repair Sprite compact icon for dialogue headers, map/shop/event labels. | E28: P2

Sheet 18 - Board Blocks
A1: 18. Sprite Assets — Board Blocks and Board UI
A2: Tracking sheet generated from the uploaded markdown. Done? is unchecked by default.
A4: Done? | B4: Asset Key | C4: Suggested Folder | D4: Designer Description | E4: Priority
A5: ☐ | B5: spr_block_red_rune | C5: sprites/board-blocks/ | D5: Red Rune: Base board tile/sprite. Direction: basic red magical rune block; clean readable color/symbol. | E5: P0
A6: ☐ | B6: spr_block_red_rune_glow | C6: sprites/board-blocks/ | D6: Red Rune: Glow/highlight version for selection, warning, or active effect. Direction: basic red magical rune block; clean readable color/symbol. | E6: P0
A7: ☐ | B7: spr_block_red_rune_clear | C7: sprites/board-blocks/ | D7: Red Rune: Clear/burst frame used when block is removed. Direction: basic red magical rune block; clean readable color/symbol. | E7: P0
A8: ☐ | B8: ico_block_red_rune | C8: icons/board-blocks/ | D8: Red Rune icon for tutorial, tooltips, boss rule cards, and content UI. | E8: P1
A9: ☐ | B9: spr_block_blue_rune | C9: sprites/board-blocks/ | D9: Blue Rune: Base board tile/sprite. Direction: basic blue magical rune block; clean readable color/symbol. | E9: P0
A10: ☐ | B10: spr_block_blue_rune_glow | C10: sprites/board-blocks/ | D10: Blue Rune: Glow/highlight version for selection, warning, or active effect. Direction: basic blue magical rune block; clean readable color/symbol. | E10: P0
A11: ☐ | B11: spr_block_blue_rune_clear | C11: sprites/board-blocks/ | D11: Blue Rune: Clear/burst frame used when block is removed. Direction: basic blue magical rune block; clean readable color/symbol. | E11: P0
A12: ☐ | B12: ico_block_blue_rune | C12: icons/board-blocks/ | D12: Blue Rune icon for tutorial, tooltips, boss rule cards, and content UI. | E12: P1
A13: ☐ | B13: spr_block_green_rune | C13: sprites/board-blocks/ | D13: Green Rune: Base board tile/sprite. Direction: basic green magical rune block; clean readable color/symbol. | E13: P0
A14: ☐ | B14: spr_block_green_rune_glow | C14: sprites/board-blocks/ | D14: Green Rune: Glow/highlight version for selection, warning, or active effect. Direction: basic green magical rune block; clean readable color/symbol. | E14: P0
A15: ☐ | B15: spr_block_green_rune_clear | C15: sprites/board-blocks/ | D15: Green Rune: Clear/burst frame used when block is removed. Direction: basic green magical rune block; clean readable color/symbol. | E15: P0
... A90: ☐ | B90: spr_board_warning_floaty_block | C90: sprites/board-blocks/ | D90: Warning marker for floating block countdown/hover danger. | E90: P1

Sheet 19 and VFX - Spells
A1: 19. Icon and VFX Assets — Spells
A2: Tracking sheet generated from the uploaded markdown. Done? is unchecked by default.
A4: Done? | B4: Asset Key | C4: Suggested Folder | D4: Designer Description | E4: Priority
A5: ☐ | B5: ico_spl_fireball | C5: icons/spells/ | D5: Fireball spell icon. Must clearly communicate: Fire damage; should feel like Pippa preheating the enemy. | E5: P0
A6: ☐ | B6: vfx_spl_fireball_cast | C6: sprites/effects/ | D6: Cast VFX: short readable effect around hero/spell button for Fireball. | E6: P1
A7: ☐ | B7: vfx_spl_fireball_impact | C7: sprites/effects/ | D7: Impact VFX: board/enemy effect showing result of Fireball. | E7: P1
A8: ☐ | B8: ico_spl_frost_lock | C8: icons/spells/ | D8: Frost Lock spell icon. Must clearly communicate: Control spell; chills fall speed or freezes enemy timing. | E8: P0
A9: ☐ | B9: vfx_spl_frost_lock_cast | C9: sprites/effects/ | D9: Cast VFX: short readable effect around hero/spell button for Frost Lock. | E9: P1
A10: ☐ | B10: vfx_spl_frost_lock_impact | C10: sprites/effects/ | D10: Impact VFX: board/enemy effect showing result of Frost Lock. | E10: P1
A11: ☐ | B11: ico_spl_bomb_rune | C11: icons/spells/ | D11: Bomb Rune spell icon. Must clearly communicate: Board-clear spell; creates a toy bomb area clear. | E11: P0
A12: ☐ | B12: vfx_spl_bomb_rune_cast | C12: sprites/effects/ | D12: Cast VFX: short readable effect around hero/spell button for Bomb Rune. | E12: P1
A13: ☐ | B13: vfx_spl_bomb_rune_impact | C13: sprites/effects/ | D13: Impact VFX: board/enemy effect showing result of Bomb Rune. | E13: P1
A14: ☐ | B14: ico_spl_clean_cut | C14: icons/spells/ | D14: Clean Cut spell icon. Must clearly communicate: Precise cleanup spell that clears a row or messy pattern. | E14: P0
A15: ☐ | B15: vfx_spl_clean_cut_cast | C15: sprites/effects/ | D15: Cast VFX: short readable effect around hero/spell button for Clean Cut. | E15: P1
... A49: ☐ | B49: vfx_spl_cascade_cheer_impact | C49: sprites/effects/ | D49: Impact VFX: board/enemy effect showing result of Cascade Cheer. | E49: P1

Sheet 20 - Items
A1: 20. Icon Assets — Items and Reactive Counter Items
A2: Tracking sheet generated from the uploaded markdown. Done? is unchecked by default.
A4: Done? | B4: Asset Key | C4: Suggested Folder | D4: Designer Description | E4: Priority
A5: ☐ | B5: ico_item_mini_cupcake | C5: icons/items/ | D5: Mini Cupcake icon: small healing snack; icon should look instantly edible and friendly. | E5: P0
A6: ☐ | B6: ico_item_mana_lemonade | C6: icons/items/ | D6: Mana Lemonade icon: blue/yellow lemonade bottle for mana refill. | E6: P0
A7: ☐ | B7: ico_item_rainbow_soda | C7: icons/items/ | D7: Rainbow Soda icon: rainbow drink that fills Fever meter. | E7: P0
A8: ☐ | B8: ico_item_toolbox | C8: icons/items/ | D8: Toolbox icon: small red/yellow toolbox for removing junk blocks. | E8: P0
A9: ☐ | B9: ico_item_snowcone | C9: icons/items/ | D9: Snowcone icon: icy treat for slowing fall speed temporarily. | E9: P0
A10: ☐ | B10: ico_item_party_popper | C10: icons/items/ | D10: Party Popper icon: party popper that clears random cells. | E10: P1
A11: ☐ | B11: ico_item_bubble_gum | C11: icons/items/ | D11: Bubble Gum icon: pink bubble gum that grants shield. | E11: P1
A12: ☐ | B12: ico_item_lucky_ticket | C12: icons/items/ | D12: Lucky Ticket icon: festival ticket for rerolling rewards. | E12: P1
A13: ☐ | B13: ico_item_hold_coupon | C13: icons/items/ | D13: Hold Coupon icon: coupon/ticket for refreshing Hold block. | E13: P1
A14: ☐ | B14: ico_item_block_polish | C14: icons/items/ | D14: Block Polish icon: sparkly polish bottle that converts junk to normal block. | E14: P1
A15: ☐ | B15: ico_item_snack_vacuum | C15: icons/items/ | D15: Snack Vacuum icon: cute vacuum that removes junk blocks from chosen area. | E15: P1
... A56: ☐ | B56: ico_item_mana_straw | C56: icons/items/ | D56: Mana Straw icon: utility catalyst that converts sprinkle blocks into mana. | E56: P1

Sheet 21 - Relics
A1: 21. Icon Assets — Relics
A2: Tracking sheet generated from the uploaded markdown. Done? is unchecked by default.
A4: Done? | B4: Asset Key | C4: Suggested Folder | D4: Designer Description | E4: Priority
A5: ☐ | B5: ico_rel_goblin_coin | C5: icons/relics/ | D5: Goblin Coin relic icon: lucky goblin coin that increases gold gain. Should look like a collectible souvenir. | E5: P1
A6: ☐ | B6: ico_rel_lucky_cupcake | C6: icons/relics/ | D6: Lucky Cupcake relic icon: cute cupcake charm that heals after boss. Should look like a collectible souvenir. | E6: P1
A7: ☐ | B7: ico_rel_sparkly_spoon | C7: icons/relics/ | D7: Sparkly Spoon relic icon: shiny spoon relic that boosts line damage. Should look like a collectible souvenir. | E7: P1
A8: ☐ | B8: ico_rel_sticky_sticker | C8: icons/relics/ | D8: Sticky Sticker relic icon: sticker relic that turns sticky clears into mana value. Should look like a collectible souvenir. | E8: P1
A9: ☐ | B9: ico_rel_confetti_popper | C9: icons/relics/ | D9: Confetti Popper relic icon: party relic that may clear a random cell. Should look like a collectible souvenir. | E9: P1
A10: ☐ | B10: ico_rel_rainbow_ticket | C10: icons/relics/ | D10: Rainbow Ticket relic icon: rare ticket granting extra reward choice. Should look like a collectible souvenir. | E10: P1
A11: ☐ | B11: ico_rel_tiny_toolbox | C11: icons/relics/ | D11: Tiny Toolbox relic icon: small toolbox reducing bomb/gadget cost. Should look like a collectible souvenir. | E11: P1
A12: ☐ | B12: ico_rel_plush_helmet | C12: icons/relics/ | D12: Plush Helmet relic icon: soft helmet that prevents lethal damage once. Should look like a collectible souvenir. | E12: P1
A13: ☐ | B13: ico_rel_snowflake_charm | C13: icons/relics/ | D13: Snowflake Charm relic icon: icy charm strengthening frost spells. Should look like a collectible souvenir. | E13: P1
A14: ☐ | B14: ico_rel_star_cookie | C14: icons/relics/ | D14: Star Cookie relic icon: star-shaped cookie increasing cascade damage. Should look like a collectible souvenir. | E14: P1
A15: ☐ | B15: ico_rel_bouncy_boots | C15: icons/relics/ | D15: Bouncy Boots relic icon: boots that reward hard drops with mana. Should look like a collectible souvenir. | E15: P1
... A19: ☐ | B19: ico_rel_block_o_manual | C19: icons/relics/ | D19: Block-O Manual relic icon: legendary manual that fixes or highlights a messy row once per battle. Should look like a collectible souvenir. | E19: P1

Sheet 22 - Upgrades
A1: 22. Icon Assets — Upgrades
A2: Tracking sheet generated from the uploaded markdown. Done? is unchecked by default.
A4: Done? | B4: Asset Key | C4: Suggested Folder | D4: Designer Description | E4: Priority
A5: ☐ | B5: ico_upg_clean_stack | C5: icons/upgrades/ | D5: Clean Stack upgrade icon: board upgrade that slightly lowers fall speed. Use clear category visual language. | E5: P1
A6: ☐ | B6: ico_upg_sharp_sprinkles | C6: icons/upgrades/ | D6: Sharp Sprinkles upgrade icon: damage upgrade for line clears. Use clear category visual language. | E6: P1
A7: ☐ | B7: ico_upg_extra_frosting | C7: icons/upgrades/ | D7: Extra Frosting upgrade icon: defense upgrade that increases max HP. Use clear category visual language. | E7: P1
A8: ☐ | B8: ico_upg_mana_lemonade | C8: icons/upgrades/ | D8: Mana Lemonade upgrade icon: mana upgrade that increases mana gain. Use clear category visual language. | E8: P1
A9: ☐ | B9: ico_upg_combo_cheer | C9: icons/upgrades/ | D9: Combo Cheer upgrade icon: combo upgrade for cascade damage. Use clear category visual language. | E9: P1
A10: ☐ | B10: ico_upg_bigger_booms | C10: icons/upgrades/ | D10: Bigger Booms upgrade icon: spell upgrade increasing Bomb Rune radius. Use clear category visual language. | E10: P1
A11: ☐ | B11: ico_upg_hotter_oven | C11: icons/upgrades/ | D11: Hotter Oven upgrade icon: fire upgrade improving Fireball damage. Use clear category visual language. | E11: P1
A12: ☐ | B12: ico_upg_chill_zone | C12: icons/upgrades/ | D12: Chill Zone upgrade icon: frost upgrade improving Frost Lock. Use clear category visual language. | E12: P1
A13: ☐ | B13: ico_upg_pocket_snack | C13: icons/upgrades/ | D13: Pocket Snack upgrade icon: healing upgrade after each room. Use clear category visual language. | E13: P1
A14: ☐ | B14: ico_upg_bonus_preview | C14: icons/upgrades/ | D14: Bonus Preview upgrade icon: board upgrade showing extra next block. Use clear category visual language. | E14: P1
A15: ☐ | B15: ico_upg_quick_hold | C15: icons/upgrades/ | D15: Quick Hold upgrade icon: board upgrade reducing hold restrictions/cooldown. Use clear category visual language. | E15: P1
... A19: ☐ | B19: ico_upg_smooth_cascade | C19: icons/upgrades/ | D19: Smooth Cascade upgrade icon: cascade upgrade increasing mana from cascades. Use clear category visual language. | E19: P1

Sheet 23 and - Weapons
A1: 23. Icon and Sprite Assets — Weapons
A2: Tracking sheet generated from the uploaded markdown. Done? is unchecked by default.
A4: Done? | B4: Asset Key | C4: Suggested Folder | D4: Designer Description | E4: Priority
A5: ☐ | B5: ico_wpn_basic_wand | C5: icons/weapons/ | D5: Basic Wand weapon icon: starter wand with simple wooden/magic rune design. | E5: P1
A6: ☐ | B6: spr_wpn_basic_wand_small | C6: sprites/weapons/ | D6: Basic Wand small in-battle weapon sprite or hero overlay: starter wand with simple wooden/magic rune design. | E6: P2
A7: ☐ | B7: ico_wpn_lemonade_wand | C7: icons/weapons/ | D7: Lemonade Wand weapon icon: wand with lemonade cup/bottle motif for mana gain. | E7: P1
A8: ☐ | B8: spr_wpn_lemonade_wand_small | C8: sprites/weapons/ | D8: Lemonade Wand small in-battle weapon sprite or hero overlay: wand with lemonade cup/bottle motif for mana gain. | E8: P2
A9: ☐ | B9: ico_wpn_cookie_spatula | C9: icons/weapons/ | D9: Cookie Spatula weapon icon: baker spatula weapon for fire/cookie theme. | E9: P1
A10: ☐ | B10: spr_wpn_cookie_spatula_small | C10: sprites/weapons/ | D10: Cookie Spatula small in-battle weapon sprite or hero overlay: baker spatula weapon for fire/cookie theme. | E10: P2
A11: ☐ | B11: ico_wpn_snowcone_staff | C11: icons/weapons/ | D11: Snowcone Staff weapon icon: icy staff with snowcone top for frost effects. | E11: P1
A12: ☐ | B12: spr_wpn_snowcone_staff_small | C12: sprites/weapons/ | D12: Snowcone Staff small in-battle weapon sprite or hero overlay: icy staff with snowcone top for frost effects. | E12: P2
A13: ☐ | B13: ico_wpn_spring_hammer | C13: icons/weapons/ | D13: Spring Hammer weapon icon: goblin spring hammer for hard-drop damage. | E13: P1
A14: ☐ | B14: spr_wpn_spring_hammer_small | C14: sprites/weapons/ | D14: Spring Hammer small in-battle weapon sprite or hero overlay: goblin spring hammer for hard-drop damage. | E14: P2
A15: ☐ | B15: ico_wpn_confetti_cannon | C15: icons/weapons/ | D15: Confetti Cannon weapon icon: party cannon gadget that suggests bomb/confetti chance. | E15: P1
... A24: ☐ | B24: spr_wpn_arcade_blaster_small | C24: sprites/weapons/ | D24: Arcade Blaster small in-battle weapon sprite or hero overlay: neon arcade blaster for Fever gain. | E24: P2

Sheet 24 - Status Effects
A1: 24. Icon Assets — Status Effects
A2: Tracking sheet generated from the uploaded markdown. Done? is unchecked by default.
A4: Done? | B4: Asset Key | C4: Suggested Folder | D4: Designer Description | E4: Priority
A5: ☐ | B5: ico_status_sugar_rush | C5: icons/statuses/ | D5: Sugar Rush status icon: speed/action boost icon, candy lightning style. Keep readable at small HUD size. | E5: P1
A6: ☐ | B6: ico_status_sticky | C6: icons/statuses/ | D6: Sticky status icon: goo/sticky status icon. Keep readable at small HUD size. | E6: P1
A7: ☐ | B7: ico_status_chilled | C7: icons/statuses/ | D7: Chilled status icon: snowflake/cold status icon. Keep readable at small HUD size. | E7: P1
A8: ☐ | B8: ico_status_sleepy | C8: icons/statuses/ | D8: Sleepy status icon: sleep bubble/z icon. Keep readable at small HUD size. | E8: P1
A9: ☐ | B9: ico_status_dizzy | C9: icons/statuses/ | D9: Dizzy status icon: spiral stars icon. Keep readable at small HUD size. | E9: P1
A10: ☐ | B10: ico_status_sparkly | C10: icons/statuses/ | D10: Sparkly status icon: extra mana sparkle icon. Keep readable at small HUD size. | E10: P1
A11: ☐ | B11: ico_status_bubbled | C11: icons/statuses/ | D11: Bubbled status icon: shield bubble icon. Keep readable at small HUD size. | E11: P1
A12: ☐ | B12: ico_status_confetti | C12: icons/statuses/ | D12: Confetti status icon: random party bonus icon. Keep readable at small HUD size. | E12: P1
A13: ☐ | B13: ico_status_snack_boost | C13: icons/statuses/ | D13: Snack Boost status icon: snack/heal-over-time icon. Keep readable at small HUD size. | E13: P1
A14: ☐ | B14: ico_status_overclocked | C14: icons/statuses/ | D14: Overclocked status icon: machine speed/junk reward icon. Keep readable at small HUD size. | E14: P1

Sheet 25 - Oopsies
A1: 25. Icon Assets — Oopsies / Silly Drawbacks
A2: Tracking sheet generated from the uploaded markdown. Done? is unchecked by default.
A4: Done? | B4: Asset Key | C4: Suggested Folder | D4: Designer Description | E4: Priority
A5: ☐ | B5: ico_oops_heavy_blocks | C5: icons/oopsies/ | D5: Heavy Blocks Oopsie icon: fall speed drawback; heavy block/weight icon. Must feel silly, not cursed/dark. | E5: P1
A6: ☐ | B6: ico_oops_slippery_buttons | C6: icons/oopsies/ | D6: Slippery Buttons Oopsie icon: input delay drawback; slippery button icon. Must feel silly, not cursed/dark. | E6: P1
A7: ☐ | B7: ico_oops_too_much_confetti | C7: icons/oopsies/ | D7: Too Much Confetti Oopsie icon: preview flashing drawback; confetti cloud icon. Must feel silly, not cursed/dark. | E7: P1
A8: ☐ | B8: ico_oops_snack_tax | C8: icons/oopsies/ | D8: Snack Tax Oopsie icon: shop price drawback; snack coin/tax icon. Must feel silly, not cursed/dark. | E8: P1
A9: ☐ | B9: ico_oops_sticky_floor | C9: icons/oopsies/ | D9: Sticky Floor Oopsie icon: more sticky blocks drawback; syrup floor icon. Must feel silly, not cursed/dark. | E9: P1
A10: ☐ | B10: ico_oops_overexcited_machine | C10: icons/oopsies/ | D10: Overexcited Machine Oopsie icon: more junk/better rewards drawback; excited machine icon. Must feel silly, not cursed/dark. | E10: P1
A11: ☐ | B11: ico_oops_square_only | C11: icons/oopsies/ | D11: Square Only Oopsie icon: pattern challenge drawback; square-only icon. Must feel silly, not cursed/dark. | E11: P1
A12: ☐ | B12: ico_oops_sugar_crash | C12: icons/oopsies/ | D12: Sugar Crash Oopsie icon: mana gain drawback after spell spam; broken candy icon. Must feel silly, not cursed/dark. | E12: P1

Sheet 26 - Festival Chaos Rules
A1: 26. Icon Assets — Festival Chaos Rules
A2: Tracking sheet generated from the uploaded markdown. Done? is unchecked by default.
A4: Done? | B4: Asset Key | C4: Suggested Folder | D4: Designer Description | E4: Priority
A5: ☐ | B5: ico_chaos_sprinkle_storm | C5: icons/events/ | D5: Sprinkle Storm chaos-rule icon: chaos rule with sprinkle rain. | E5: P1
A6: ☐ | B6: ico_chaos_wobbly_floor | C6: icons/events/ | D6: Wobbly Floor chaos-rule icon: chaos rule with shaky floor. | E6: P1
A7: ☐ | B7: ico_chaos_snack_tax | C7: icons/events/ | D7: Snack Tax chaos-rule icon: chaos rule with temporary shop/economy pressure. | E7: P1
A8: ☐ | B8: ico_chaos_confetti_fever | C8: icons/events/ | D8: Confetti Fever chaos-rule icon: chaos rule with party randomness/fever. | E8: P1
A9: ☐ | B9: ico_chaos_goblin_safety_test | C9: icons/events/ | D9: Goblin Safety Test chaos-rule icon: chaos rule with questionable workshop hazard. | E9: P1
A10: ☐ | B10: ico_chaos_freezer_draft | C10: icons/events/ | D10: Freezer Draft chaos-rule icon: chaos rule with cold/freeze pressure. | E10: P1
A11: ☐ | B11: ico_chaos_royal_inspection | C11: icons/events/ | D11: Royal Inspection chaos-rule icon: chaos rule with Bloxley pattern/symmetry pressure. | E11: P1
A12: ☐ | B12: ico_chaos_jelly_bounce | C12: icons/events/ | D12: Jelly Bounce chaos-rule icon: chaos rule with wobbly/jelly block movement. | E12: P1

Sheet 27 - Battle Objectives
A1: 27. Icon Assets — Battle Objectives
A2: Tracking sheet generated from the uploaded markdown. Done? is unchecked by default.
A4: Done? | B4: Asset Key | C4: Suggested Folder | D4: Designer Description | E4: Priority
A5: ☐ | B5: ico_obj_trigger_cascade | C5: icons/objectives/ | D5: Trigger Cascade: mini-objective icon for making at least one cascade. | E5: P1
A6: ☐ | B6: ico_obj_clear_two_lines | C6: icons/objectives/ | D6: Clear Two Lines: mini-objective icon for clearing two lines at once. | E6: P1
A7: ☐ | B7: ico_obj_clear_sprinkles | C7: icons/objectives/ | D7: Clear Sprinkles: mini-objective icon for clearing sprinkle blocks. | E7: P1
A8: ☐ | B8: ico_obj_destroy_junk | C8: icons/objectives/ | D8: Destroy Junk: mini-objective icon for cleaning all junk. | E8: P1
A9: ☐ | B9: ico_obj_no_spell_win | C9: icons/objectives/ | D9: No Spell Win: mini-objective icon for winning without spells. | E9: P1
A10: ☐ | B10: ico_obj_fast_win | C10: icons/objectives/ | D10: Fast Win: mini-objective icon for winning before enemy acts several times. | E10: P1
A11: ☐ | B11: ico_obj_use_hold | C11: icons/objectives/ | D11: Use Hold: mini-objective icon for using hold piece. | E11: P1
A12: ☐ | B12: ico_obj_cast_two_spells | C12: icons/objectives/ | D12: Cast Two Spells: mini-objective icon for casting two spells. | E12: P1
A13: ☐ | B13: ico_obj_low_board | C13: icons/objectives/ | D13: Low Board: mini-objective icon for keeping board height low. | E13: P1
A14: ☐ | B14: ico_obj_trigger_fever | C14: icons/objectives/ | D14: Trigger Fever: mini-objective icon for activating fever. | E14: P1

Sheet 28 - Events
A1: 28. Icon Assets — Room Events and Random Gameplay Events
A2: Tracking sheet generated from the uploaded markdown. Done? is unchecked by default.
A4: Done? | B4: Asset Key | C4: Suggested Folder | D4: Designer Description | E4: Priority
A5: ☐ | B5: ico_evt_suspicious_button | C5: icons/events/ | D5: Suspicious Button: event icon: big red button with warning label. | E5: P1
A6: ☐ | B6: ico_evt_lost_cake_cart | C6: icons/events/ | D6: Lost Cake Cart: event icon: cake cart with missing snacks. | E6: P1
A7: ☐ | B7: ico_evt_goblin_quality_test | C7: icons/events/ | D7: Goblin Quality Test: event icon: goblin gadget test clipboard. | E7: P1
A8: ☐ | B8: ico_evt_rainbow_fountain | C8: icons/events/ | D8: Rainbow Fountain: event icon: rainbow fountain with magic water. | E8: P1
A9: ☐ | B9: ico_evt_sleepy_guard | C9: icons/events/ | D9: Sleepy Guard: event icon: guard sleeping by key. | E9: P1
A10: ☐ | B10: ico_evt_arcade_challenge | C10: icons/events/ | D10: Arcade Challenge: event icon: arcade cabinet/ticket. | E10: P1
A11: ☐ | B11: ico_evt_block_o_manual_page | C11: icons/events/ | D11: Manual Page: event icon: Block-O-Matic manual page. | E11: P1
A12: ☐ | B12: ico_evt_friendship_slime | C12: icons/events/ | D12: Friendship Slime: event icon: friendly slime with snack. | E12: P1
A13: ☐ | B13: ico_r_evt_jelly_surge | C13: icons/events/ | D13: Jelly Surge: random battle event icon: wobbly jelly burst. | E13: P1
A14: ☐ | B14: ico_r_evt_sprinkle_rain | C14: icons/events/ | D14: Sprinkle Rain: random battle event icon: sprinkles falling. | E14: P1
A15: ☐ | B15: ico_r_evt_sticky_spill | C15: icons/events/ | D15: Sticky Spill: random battle event icon: syrup spill. | E15: P1
... A32: ☐ | B32: ico_r_evt_machine_hiccup | C32: icons/events/ | D32: Machine Hiccup: random battle event icon: hiccuping machine. | E32: P1

Sheet 29 - Boss Rule Cards
A1: 29. Icon Assets — Boss Rule Cards
A2: Tracking sheet generated from the uploaded markdown. Done? is unchecked by default.
A4: Done? | B4: Asset Key | C4: Suggested Folder | D4: Designer Description | E4: Priority
A5: ☐ | B5: ico_boss_rule_boss_cupcake_slime_king | C5: icons/boss-rules/ | D5: Rule-card icon for Cupcake Slime King; represent the boss mechanic in one clear symbol. | E5: P1
A6: ☐ | B6: ico_boss_rule_boss_prototype_no_7 | C6: icons/boss-rules/ | D6: Rule-card icon for Prototype No. 7; represent the boss mechanic in one clear symbol. | E6: P1
A7: ☐ | B7: ico_boss_rule_boss_gelato_golem | C7: icons/boss-rules/ | D7: Rule-card icon for Gelato Golem; represent the boss mechanic in one clear symbol. | E7: P1
A8: ☐ | B8: ico_boss_rule_boss_sir_snore_a_lot | C8: icons/boss-rules/ | D8: Rule-card icon for Sir Snore-a-Lot; represent the boss mechanic in one clear symbol. | E8: P1
A9: ☐ | B9: ico_boss_rule_boss_high_score_hydra | C9: icons/boss-rules/ | D9: Rule-card icon for High Score Hydra; represent the boss mechanic in one clear symbol. | E9: P1
A10: ☐ | B10: ico_boss_rule_boss_king_bloxley | C10: icons/boss-rules/ | D10: Rule-card icon for King Bloxley; represent the boss mechanic in one clear symbol. | E10: P1

Sheet 30 - Currency Collect
A1: 30. Icon Assets — Currencies and Collectibles
A2: Tracking sheet generated from the uploaded markdown. Done? is unchecked by default.
A4: Done? | B4: Asset Key | C4: Suggested Folder | D4: Designer Description | E4: Priority
A5: ☐ | B5: ico_currency_gold | C5: icons/currencies/ | D5: Gold currency icon: main shop currency; coin icon with cheerful shine. | E5: P0
A6: ☐ | B6: ico_currency_sprinkles | C6: icons/currencies/ | D6: Sprinkles currency icon: upgrade/cosmetic currency; candy sprinkles icon. | E6: P1
A7: ☐ | B7: ico_currency_tickets | C7: icons/currencies/ | D7: Festival Tickets currency icon: meta unlock/arcade currency; ticket icon. | E7: P1
A8: ☐ | B8: ico_currency_stars | C8: icons/currencies/ | D8: Star Tokens currency icon: rare unlock currency; star token icon. | E8: P1
A9: ☐ | B9: ico_collectible_lost_cake | C9: icons/collectibles/ | D9: Lost Cake collectible icon: true-ending cake collectible; small rescued cake icon. | E9: P1
A10: ☐ | B10: ico_collectible_manual_page | C10: icons/collectibles/ | D10: Manual Page collectible icon: tutorial/lore collectible; paper page icon. | E10: P1
A11: ☐ | B11: ico_collectible_friendship_badge | C11: icons/collectibles/ | D11: Friendship Badge collectible icon: monster friendship collectible; badge/heart icon. | E11: P1
A12: ☐ | B12: ico_collectible_arcade_token | C12: icons/collectibles/ | D12: Arcade Token collectible icon: arcade collectible; neon token icon. | E12: P1

Sheet 31 and - Hub Buildings
A1: 31. Sprite and Icon Assets — Festival Hub Buildings
A2: Tracking sheet generated from the uploaded markdown. Done? is unchecked by default.
A4: Done? | B4: Asset Key | C4: Suggested Folder | D4: Designer Description | E4: Priority
A5: ☐ | B5: spr_hub_cake_stall_level_0 | C5: sprites/hub/ | D5: Cake Stall building level 0; show visible upgrade progression. Direction: festival booth for cake restoration/progression. | E5: P2
A6: ☐ | B6: spr_hub_cake_stall_level_1 | C6: sprites/hub/ | D6: Cake Stall building level 1; show visible upgrade progression. Direction: festival booth for cake restoration/progression. | E6: P2
A7: ☐ | B7: spr_hub_cake_stall_level_2 | C7: sprites/hub/ | D7: Cake Stall building level 2; show visible upgrade progression. Direction: festival booth for cake restoration/progression. | E7: P2
A8: ☐ | B8: spr_hub_cake_stall_level_3 | C8: sprites/hub/ | D8: Cake Stall building level 3; show visible upgrade progression. Direction: festival booth for cake restoration/progression. | E8: P2
A9: ☐ | B9: ico_hub_cake_stall | C9: icons/hub/ | D9: Cake Stall hub icon for menu/building upgrade UI. | E9: P2
A10: ☐ | B10: spr_hub_ice_cream_cart_level_0 | C10: sprites/hub/ | D10: Ice Cream Cart building level 0; show visible upgrade progression. Direction: Nixie-style cart for frost/heal upgrades. | E10: P2
A11: ☐ | B11: spr_hub_ice_cream_cart_level_1 | C11: sprites/hub/ | D11: Ice Cream Cart building level 1; show visible upgrade progression. Direction: Nixie-style cart for frost/heal upgrades. | E11: P2
A12: ☐ | B12: spr_hub_ice_cream_cart_level_2 | C12: sprites/hub/ | D12: Ice Cream Cart building level 2; show visible upgrade progression. Direction: Nixie-style cart for frost/heal upgrades. | E12: P2
A13: ☐ | B13: spr_hub_ice_cream_cart_level_3 | C13: sprites/hub/ | D13: Ice Cream Cart building level 3; show visible upgrade progression. Direction: Nixie-style cart for frost/heal upgrades. | E13: P2
A14: ☐ | B14: ico_hub_ice_cream_cart | C14: icons/hub/ | D14: Ice Cream Cart hub icon for menu/building upgrade UI. | E14: P2
A15: ☐ | B15: spr_hub_goblin_workshop_level_0 | C15: sprites/hub/ | D15: Goblin Workshop building level 0; show visible upgrade progression. Direction: gadget booth with tools and machines. | E15: P2
... A44: ☐ | B44: ico_hub_bloxley_statue | C44: icons/hub/ | D44: Bloxley Statue hub icon for menu/building upgrade UI. | E44: P2

Sheet 32 UI - Panels Frames
A1: 32. UI Assets — Panels and Frames
A2: Tracking sheet generated from the uploaded markdown. Done? is unchecked by default.
A4: Done? | B4: Asset Key | C4: Suggested Folder | D4: Designer Description | E4: Priority
A5: ☐ | B5: ui_panel_default | C5: ui/panels/ | D5: Default chunky pixel panel for common UI. | E5: P0
A6: ☐ | B6: ui_panel_battle | C6: ui/panels/ | D6: Battle HUD panel frame, compact and mobile-readable. | E6: P0
A7: ☐ | B7: ui_panel_reward | C7: ui/panels/ | D7: Reward screen panel with card slots and sparkle trim. | E7: P0
A8: ☐ | B8: ui_panel_shop | C8: ui/panels/ | D8: Shop panel with merchant-friendly trim and price readability. | E8: P1
A9: ☐ | B9: ui_panel_event | C9: ui/panels/ | D9: Event choice panel with flexible text area. | E9: P1
A10: ☐ | B10: ui_panel_dialogue | C10: ui/panels/ | D10: Dialogue box panel with portrait slot and skip affordance. | E10: P1
A11: ☐ | B11: ui_panel_settings | C11: ui/panels/ | D11: Settings panel with simple rows/toggles. | E11: P1
A12: ☐ | B12: ui_panel_inventory_compact | C12: ui/panels/ | D12: Small inventory overlay panel for portrait battle board. | E12: P0
A13: ☐ | B13: ui_panel_inventory_expanded | C13: ui/panels/ | D13: Expanded inventory panel for item descriptions and use. | E13: P0
A14: ☐ | B14: ui_panel_boss_rule | C14: ui/panels/ | D14: Boss rule card panel with warning/title/tip areas. | E14: P1
A15: ☐ | B15: ui_panel_tutorial_tip | C15: ui/panels/ | D15: Tutorial tip bubble/panel for first-run guidance. | E15: P1
... A20: ☐ | B20: ui_frame_card_legendary | C20: ui/frames/ | D20: Legendary reward card frame with clear premium feel. | E20: P1

Sheet 33 UI - Buttons
A1: 33. UI Assets — Buttons
A2: Tracking sheet generated from the uploaded markdown. Done? is unchecked by default.
A4: Done? | B4: Asset Key | C4: Suggested Folder | D4: Designer Description | E4: Priority
A5: ☐ | B5: ui_button_primary_idle | C5: ui/buttons/ | D5: Primary button idle state; bright and readable. | E5: P0
A6: ☐ | B6: ui_button_primary_pressed | C6: ui/buttons/ | D6: Primary button pressed state; clear tactile feedback. | E6: P0
A7: ☐ | B7: ui_button_primary_disabled | C7: ui/buttons/ | D7: Primary disabled state; muted but still legible. | E7: P0
A8: ☐ | B8: ui_button_secondary_idle | C8: ui/buttons/ | D8: Secondary button idle state. | E8: P0
A9: ☐ | B9: ui_button_secondary_pressed | C9: ui/buttons/ | D9: Secondary button pressed state. | E9: P0
A10: ☐ | B10: ui_button_secondary_disabled | C10: ui/buttons/ | D10: Secondary disabled state. | E10: P0
A11: ☐ | B11: ui_button_danger_idle | C11: ui/buttons/ | D11: Danger/risky action button idle state, still playful. | E11: P1
A12: ☐ | B12: ui_button_danger_pressed | C12: ui/buttons/ | D12: Danger/risky action button pressed state. | E12: P1
A13: ☐ | B13: ui_button_icon_idle | C13: ui/buttons/ | D13: Small icon-only button idle state. | E13: P0
A14: ☐ | B14: ui_button_icon_pressed | C14: ui/buttons/ | D14: Small icon-only button pressed state. | E14: P0
A15: ☐ | B15: ui_button_close | C15: ui/buttons/ | D15: Close/X button for panels. | E15: P0
... A18: ☐ | B18: ui_button_skip | C18: ui/buttons/ | D18: Skip button for tutorial/dialogue. | E18: P1

Sheet 34 UI - Controls
A1: 34. UI Assets — Mobile Controls
A2: Tracking sheet generated from the uploaded markdown. Done? is unchecked by default.
A4: Done? | B4: Asset Key | C4: Suggested Folder | D4: Designer Description | E4: Priority
A5: ☐ | B5: ui_control_left_idle | C5: ui/controls/ | D5: Mobile left control idle state. | E5: P0
A6: ☐ | B6: ui_control_left_pressed | C6: ui/controls/ | D6: Mobile left control pressed state. | E6: P0
A7: ☐ | B7: ui_control_right_idle | C7: ui/controls/ | D7: Mobile right control idle state. | E7: P0
A8: ☐ | B8: ui_control_right_pressed | C8: ui/controls/ | D8: Mobile right control pressed state. | E8: P0
A9: ☐ | B9: ui_control_rotate_idle | C9: ui/controls/ | D9: Mobile rotate control idle state. | E9: P0
A10: ☐ | B10: ui_control_rotate_pressed | C10: ui/controls/ | D10: Mobile rotate control pressed state. | E10: P0
A11: ☐ | B11: ui_control_soft_drop_idle | C11: ui/controls/ | D11: Mobile soft-drop control idle state. | E11: P0
A12: ☐ | B12: ui_control_soft_drop_pressed | C12: ui/controls/ | D12: Mobile soft-drop control pressed state. | E12: P0
A13: ☐ | B13: ui_control_hard_drop_idle | C13: ui/controls/ | D13: Mobile hard-drop control idle state. | E13: P0
A14: ☐ | B14: ui_control_hard_drop_pressed | C14: ui/controls/ | D14: Mobile hard-drop control pressed state. | E14: P0
A15: ☐ | B15: ui_control_hold_idle | C15: ui/controls/ | D15: Mobile hold control idle state. | E15: P0
... A18: ☐ | B18: ui_control_inventory_pressed | C18: ui/controls/ | D18: Mobile inventory control pressed state. | E18: P0

Sheet 35 UI - HUD
A1: 35. UI Assets — HUD and Meters
A2: Tracking sheet generated from the uploaded markdown. Done? is unchecked by default.
A4: Done? | B4: Asset Key | C4: Suggested Folder | D4: Designer Description | E4: Priority
A5: ☐ | B5: ui_hud_hp_bar_bg | C5: ui/hud/ | D5: HP bar background track. | E5: P0
A6: ☐ | B6: ui_hud_hp_bar_fill | C6: ui/hud/ | D6: HP bar fill with readable health color/symbol support. | E6: P0
A7: ☐ | B7: ui_hud_mana_bar_bg | C7: ui/hud/ | D7: Mana bar background track. | E7: P0
A8: ☐ | B8: ui_hud_mana_bar_fill | C8: ui/hud/ | D8: Mana bar fill with magical readable style. | E8: P0
A9: ☐ | B9: ui_hud_shield_bar_bg | C9: ui/hud/ | D9: Shield bar background track. | E9: P1
A10: ☐ | B10: ui_hud_shield_bar_fill | C10: ui/hud/ | D10: Shield bar fill, bubble-like but readable. | E10: P1
A11: ☐ | B11: ui_hud_fever_bar_bg | C11: ui/hud/ | D11: Fever meter background track. | E11: P1
A12: ☐ | B12: ui_hud_fever_bar_fill | C12: ui/hud/ | D12: Fever meter fill with arcade/combo energy. | E12: P1
A13: ☐ | B13: ui_hud_enemy_intent_frame | C13: ui/hud/ | D13: Frame for enemy intent icon/countdown. | E13: P0
A14: ☐ | B14: ui_hud_stage_label | C14: ui/hud/ | D14: Small stage label plaque for battle top panel. | E14: P0
A15: ☐ | B15: ui_hud_cascade_badge | C15: ui/hud/ | D15: Badge showing current cascade count. | E15: P1
... A19: ☐ | B19: ui_hud_hazard_warning_tray | C19: ui/hud/ | D19: Compact tray for hazard warnings and available counters. | E19: P1

Sheet 36 VFX - VFX
A1: 36. VFX Assets — Board, Combat, and Status
A2: Tracking sheet generated from the uploaded markdown. Done? is unchecked by default.
A4: Done? | B4: Asset Key | C4: Suggested Folder | D4: Designer Description | E4: Priority
A5: ☐ | B5: vfx_line_clear_sparkle | C5: sprites/effects/ | D5: Sparkle sweep across cleared line. | E5: P1
A6: ☐ | B6: vfx_cascade_pop_1 | C6: sprites/effects/ | D6: Small cascade pop effect. | E6: P1
A7: ☐ | B7: vfx_cascade_pop_2 | C7: sprites/effects/ | D7: Medium cascade pop effect. | E7: P1
A8: ☐ | B8: vfx_cascade_pop_3 | C8: sprites/effects/ | D8: Large cascade pop effect. | E8: P1
A9: ☐ | B9: vfx_cascade_pop_mega | C9: sprites/effects/ | D9: Mega cascade celebration burst. | E9: P1
A10: ☐ | B10: vfx_block_drop_dust | C10: sprites/effects/ | D10: Tiny dust/puff when blocks land. | E10: P1
A11: ☐ | B11: vfx_block_lock_puff | C11: sprites/effects/ | D11: Small puff when active piece locks. | E11: P1
A12: ☐ | B12: vfx_junk_warning | C12: sprites/effects/ | D12: Warning effect for incoming junk tray/board. | E12: P1
A13: ☐ | B13: vfx_low_ceiling_warning | C13: sprites/effects/ | D13: Overlay/alert showing ceiling is dropping. | E13: P1
A14: ☐ | B14: vfx_floaty_block_warning | C14: sprites/effects/ | D14: Hover/countdown effect around floating block. | E14: P1
A15: ☐ | B15: vfx_enemy_hit_spark | C15: sprites/effects/ | D15: Small spark on enemy hit. | E15: P1
... A33: ☐ | B33: vfx_status_overclocked | C33: sprites/effects/ | D33: Loop or burst VFX for Overclocked status: machine speed/junk reward icon. | E33: P1

Sheet 37 Font
A1: 37. Font Assets
A2: Tracking sheet generated from the uploaded markdown. Done? is unchecked by default.
A4: Done? | B4: Asset Key | C4: Suggested Folder | D4: Designer Description | E4: Priority
A5: ☐ | B5: font_pixel_header | C5: fonts/ | D5: Pixel display font for titles, boss intros, stage names. | E5: P0
A6: ☐ | B6: font_pixel_body | C6: fonts/ | D6: Readable pixel body font for descriptions, dialogue, buttons. | E6: P0
A7: ☐ | B7: font_pixel_number | C7: fonts/ | D7: Readable numeric font for damage, HP, mana, gold, score. | E7: P0
A8: ☐ | B8: font_pixel_small | C8: fonts/ | D8: Small UI font for tooltips, labels, compact HUD text. | E8: P1

Sheet 38 Store
A1: 38. Store and Platform Assets
A2: Tracking sheet generated from the uploaded markdown. Done? is unchecked by default.
A4: Done? | B4: Asset Key | C4: Suggested Folder | D4: Designer Description | E4: Priority
A5: ☐ | B5: store_app_icon_512 | C5: store/ | D5: 512x512 app icon: Milo, rune block, festival sparkle, readable at small size. | E5: P0
A6: ☐ | B6: store_app_icon_1024 | C6: store/ | D6: 1024x1024 high-resolution store icon with same composition as app icon. | E6: P0
A7: ☐ | B7: store_feature_graphic | C7: store/ | D7: Wide promotional graphic showing board, hero, monsters, and festival chaos. | E7: P1
A8: ☐ | B8: store_splash_portrait | C8: store/ | D8: Portrait splash/loading image with Blockmancer logo and cheerful festival mood. | E8: P0
A9: ☐ | B9: store_screenshot_01_battle | C9: store/ | D9: Store screenshot showing core battle board with hero/enemy panel. | E9: P0
A10: ☐ | B10: store_screenshot_02_cascade | C10: store/ | D10: Store screenshot showing Cascade Gravity/combo moment. | E10: P0
A11: ☐ | B11: store_screenshot_03_map | C11: store/ | D11: Store screenshot showing roguelike map progression. | E11: P1
A12: ☐ | B12: store_screenshot_04_boss | C12: store/ | D12: Store screenshot showing boss rule or boss battle. | E12: P1
A13: ☐ | B13: store_screenshot_05_heroes | C13: store/ | D13: Store screenshot showing hero select/unlocks. | E13: P1
A14: ☐ | B14: store_screenshot_06_rewards | C14: store/ | D14: Store screenshot showing reward cards/items/relics. | E14: P1
A15: ☐ | B15: store_trailer_thumbnail | C15: store/ | D15: Trailer thumbnail with strong character + falling block hook. | E15: P2
