Workbook

Sheet Summary
A1: Blockmancer Release 1.0 Visual Asset Checklist — 627 Source Update
A2: Separated from audio/SFX. Visual source contract: board blocks remain 24x24 / board icons 48x48; all non-board visual assets may use 627x627 source or 1254x1254 2x2 sheets with category-constrained runtime display.
A4: Category Sheet | B4: Original Category | C4: Total Assets | D4: Done | E4: Remaining | F4: Progress
A5: 00 Global Placeholder | B5: 0. Global Placeholder Assets — Visual | C5: =COUNTA('00 Global Placeholder'!$B$5:$B$10000) | D5: =COUNTIF('00 Global Placeholder'!$A$5:$A$10000,"☑") | E5: =C5-D5 | F5: =IFERROR(D5/C5,0)
A6: 08 BG - Scenes | B6: 8. Background Assets — Scenes | C6: =COUNTA('08 BG - Scenes'!$B$5:$B$10000) | D6: =COUNTIF('08 BG - Scenes'!$A$5:$A$10000,"☑") | E6: =C6-D6 | F6: =IFERROR(D6/C6,0)
A7: 09 BG - Stage Battle Parallax | B7: 9. Background Assets — Stage Battle Parallax | C7: =COUNTA('09 BG - Stage Battle Parallax'!$B$5:$B$10000) | D7: =COUNTIF('09 BG - Stage Battle Parallax'!$A$5:$A$10000,"☑") | E7: =C7-D7 | F7: =IFERROR(D7/C7,0)
A8: 10 BG - Boss Arenas | B8: 10. Background Assets — Boss Arenas | C8: =COUNTA('10 BG - Boss Arenas'!$B$5:$B$10000) | D8: =COUNTIF('10 BG - Boss Arenas'!$A$5:$A$10000,"☑") | E8: =C8-D8 | F8: =IFERROR(D8/C8,0)
A9: 11 Map - Map BGs | B9: 11. Map Assets — Map Backgrounds | C9: =COUNTA('11 Map - Map BGs'!$B$5:$B$10000) | D9: =COUNTIF('11 Map - Map BGs'!$A$5:$A$10000,"☑") | E9: =C9-D9 | F9: =IFERROR(D9/C9,0)
A10: 12 Map - Node States | B10: 12. Map Assets — Node States | C10: =COUNTA('12 Map - Node States'!$B$5:$B$10000) | D10: =COUNTIF('12 Map - Node States'!$A$5:$A$10000,"☑") | E10: =C10-D10 | F10: =IFERROR(D10/C10,0)
A11: 13 Map - Paths and Decorations | B11: 13. Map Assets — Paths and Decorations | C11: =COUNTA('13 Map - Paths and Decorations'!$B$5:$B$10000) | D11: =COUNTIF('13 Map - Paths and Decorations'!$A$5:$A$10000,"☑") | E11: =C11-D11 | F11: =IFERROR(D11/C11,0)
A12: 14 - Heroes | B12: 14. Sprite Assets — Playable Heroes | C12: =COUNTA('14 - Heroes'!$B$5:$B$10000) | D12: =COUNTIF('14 - Heroes'!$A$5:$A$10000,"☑") | E12: =C12-D12 | F12: =IFERROR(D12/C12,0)
A13: 15 - Monsters | B13: 15. Sprite Assets — Regular Monsters | C13: =COUNTA('15 - Monsters'!$B$5:$B$10000) | D13: =COUNTIF('15 - Monsters'!$A$5:$A$10000,"☑") | E13: =C13-D13 | F13: =IFERROR(D13/C13,0)
A14: 16 - Bosses | B14: 16. Sprite Assets — Bosses | C14: =COUNTA('16 - Bosses'!$B$5:$B$10000) | D14: =COUNTIF('16 - Bosses'!$A$5:$A$10000,"☑") | E14: =C14-D14 | F14: =IFERROR(D14/C14,0)
A15: 17 - NPCs | B15: 17. Sprite Assets — NPCs | C15: =COUNTA('17 - NPCs'!$B$5:$B$10000) | D15: =COUNTIF('17 - NPCs'!$A$5:$A$10000,"☑") | E15: =C15-D15 | F15: =IFERROR(D15/C15,0)
A16: 18 - Board Blocks | B16: 18. Runtime Sprite Assets — Board Blocks and Board UI | C16: =COUNTA('18 - Board Blocks'!$B$5:$B$10000) | D16: =COUNTIF('18 - Board Blocks'!$A$5:$A$10000,"☑") | E16: =C16-D16 | F16: =IFERROR(D16/C16,0)
A17: 19 and VFX - Spells | B17: 19. Icon and VFX Assets — Spells | C17: =COUNTA('19 and VFX - Spells'!$B$5:$B$10000) | D17: =COUNTIF('19 and VFX - Spells'!$A$5:$A$10000,"☑") | E17: =C17-D17 | F17: =IFERROR(D17/C17,0)
A18: 20 - Items | B18: 20. Icon Assets — Items and Reactive Counter Items | C18: =COUNTA('20 - Items'!$B$5:$B$10000) | D18: =COUNTIF('20 - Items'!$A$5:$A$10000,"☑") | E18: =C18-D18 | F18: =IFERROR(D18/C18,0)
A19: 21 - Relics | B19: 21. Icon Assets — Relics | C19: =COUNTA('21 - Relics'!$B$5:$B$10000) | D19: =COUNTIF('21 - Relics'!$A$5:$A$10000,"☑") | E19: =C19-D19 | F19: =IFERROR(D19/C19,0)
A20: 22 - Upgrades | B20: 22. Icon Assets — Upgrades | C20: =COUNTA('22 - Upgrades'!$B$5:$B$10000) | D20: =COUNTIF('22 - Upgrades'!$A$5:$A$10000,"☑") | E20: =C20-D20 | F20: =IFERROR(D20/C20,0)
A21: 23 and - Weapons | B21: 23. Icon and Sprite Assets — Weapons | C21: =COUNTA('23 and - Weapons'!$B$5:$B$10000) | D21: =COUNTIF('23 and - Weapons'!$A$5:$A$10000,"☑") | E21: =C21-D21 | F21: =IFERROR(D21/C21,0)
A22: 24 - Status Effects | B22: 24. Icon Assets — Status Effects | C22: =COUNTA('24 - Status Effects'!$B$5:$B$10000) | D22: =COUNTIF('24 - Status Effects'!$A$5:$A$10000,"☑") | E22: =C22-D22 | F22: =IFERROR(D22/C22,0)
A23: 25 - Oopsies | B23: 25. Icon Assets — Oopsies / Silly Drawbacks | C23: =COUNTA('25 - Oopsies'!$B$5:$B$10000) | D23: =COUNTIF('25 - Oopsies'!$A$5:$A$10000,"☑") | E23: =C23-D23 | F23: =IFERROR(D23/C23,0)
A24: 26 - Festival Chaos Rules | B24: 26. Icon Assets — Festival Chaos Rules | C24: =COUNTA('26 - Festival Chaos Rules'!$B$5:$B$10000) | D24: =COUNTIF('26 - Festival Chaos Rules'!$A$5:$A$10000,"☑") | E24: =C24-D24 | F24: =IFERROR(D24/C24,0)
A25: 27 - Battle Objectives | B25: 27. Icon Assets — Battle Objectives | C25: =COUNTA('27 - Battle Objectives'!$B$5:$B$10000) | D25: =COUNTIF('27 - Battle Objectives'!$A$5:$A$10000,"☑") | E25: =C25-D25 | F25: =IFERROR(D25/C25,0)
A26: 28 - Events | B26: 28. Icon Assets — Room Events and Random Gameplay Events | C26: =COUNTA('28 - Events'!$B$5:$B$10000) | D26: =COUNTIF('28 - Events'!$A$5:$A$10000,"☑") | E26: =C26-D26 | F26: =IFERROR(D26/C26,0)
A27: 29 - Boss Rule Cards | B27: 29. Icon Assets — Boss Rule Cards | C27: =COUNTA('29 - Boss Rule Cards'!$B$5:$B$10000) | D27: =COUNTIF('29 - Boss Rule Cards'!$A$5:$A$10000,"☑") | E27: =C27-D27 | F27: =IFERROR(D27/C27,0)
A28: 30 - Currency Collect | B28: 30. Icon Assets — Currencies and Collectibles | C28: =COUNTA('30 - Currency Collect'!$B$5:$B$10000) | D28: =COUNTIF('30 - Currency Collect'!$A$5:$A$10000,"☑") | E28: =C28-D28 | F28: =IFERROR(D28/C28,0)
A29: 31 and - Hub Buildings | B29: 31. Sprite and Icon Assets — Festival Hub Buildings | C29: =COUNTA('31 and - Hub Buildings'!$B$5:$B$10000) | D29: =COUNTIF('31 and - Hub Buildings'!$A$5:$A$10000,"☑") | E29: =C29-D29 | F29: =IFERROR(D29/C29,0)
A30: 32 UI - Panels Frames | B30: 32. UI Assets — Panels and Frames | C30: =COUNTA('32 UI - Panels Frames'!$B$5:$B$10000) | D30: =COUNTIF('32 UI - Panels Frames'!$A$5:$A$10000,"☑") | E30: =C30-D30 | F30: =IFERROR(D30/C30,0)
A31: 33 UI - Buttons | B31: 33. UI Assets — Buttons | C31: =COUNTA('33 UI - Buttons'!$B$5:$B$10000) | D31: =COUNTIF('33 UI - Buttons'!$A$5:$A$10000,"☑") | E31: =C31-D31 | F31: =IFERROR(D31/C31,0)
A32: 34 UI - Controls | B32: 34. UI Assets — Mobile Controls | C32: =COUNTA('34 UI - Controls'!$B$5:$B$10000) | D32: =COUNTIF('34 UI - Controls'!$A$5:$A$10000,"☑") | E32: =C32-D32 | F32: =IFERROR(D32/C32,0)
A33: 35 UI - HUD | B33: 35. UI Assets — HUD and Meters | C33: =COUNTA('35 UI - HUD'!$B$5:$B$10000) | D33: =COUNTIF('35 UI - HUD'!$A$5:$A$10000,"☑") | E33: =C33-D33 | F33: =IFERROR(D33/C33,0)
A34: 36 VFX - VFX | B34: 36. VFX Assets — Board, Combat, and Status | C34: =COUNTA('36 VFX - VFX'!$B$5:$B$10000) | D34: =COUNTIF('36 VFX - VFX'!$A$5:$A$10000,"☑") | E34: =C34-D34 | F34: =IFERROR(D34/C34,0)
A35: 37 Font | B35: 37. Font Assets | C35: =COUNTA('37 Font'!$B$5:$B$10000) | D35: =COUNTIF('37 Font'!$A$5:$A$10000,"☑") | E35: =C35-D35 | F35: =IFERROR(D35/C35,0)
A36: 38 Store | B36: 38. Store and Platform Assets | C36: =COUNTA('38 Store'!$B$5:$B$10000) | D36: =COUNTIF('38 Store'!$A$5:$A$10000,"☑") | E36: =C36-D36 | F36: =IFERROR(D36/C36,0)
A37: Update Status | B37: Latest Workbook Update — Exact Runtime IDs + Folder Contract | C37: =COUNTA('Update Status'!$B$5:$B$10000) | D37: =COUNTIF('Update Status'!$A$5:$A$10000,"☑") | E37: =C37-D37 | F37: =IFERROR(D37/C37,0)
A38: Done vs Gaps | B38: Area | C38: =COUNTA('Done vs Gaps'!$B$5:$B$10000) | D38: =COUNTIF('Done vs Gaps'!$A$5:$A$10000,"☑") | E38: =C38-D38 | F38: =IFERROR(D38/C38,0)
A39: Asset Backlog | B39: Priority | C39: =COUNTA('Asset Backlog'!$B$5:$B$10000) | D39: =COUNTIF('Asset Backlog'!$A$5:$A$10000,"☑") | E39: =C39-D39 | F39: =IFERROR(D39/C39,0)
A40: Runtime Coverage | B40: Metric / Category | C40: =COUNTA('Runtime Coverage'!$B$5:$B$10000) | D40: =COUNTIF('Runtime Coverage'!$A$5:$A$10000,"☑") | E40: =C40-D40 | F40: =IFERROR(D40/C40,0)
A41: Animation Coverage | B41: Category | C41: =COUNTA('Animation Coverage'!$B$5:$B$10000) | D41: =COUNTIF('Animation Coverage'!$A$5:$A$10000,"☑") | E41: =C41-D41 | F41: =IFERROR(D41/C41,0)
A42: 39 Story Routes | B42: 39. Story Route Assets — Character Routes, Dialogue UI, Endings | C42: =COUNTA('39 Story Routes'!$B$5:$B$10000) | D42: =COUNTIF('39 Story Routes'!$A$5:$A$10000,"☑") | E42: =C42-D42 | F42: =IFERROR(D42/C42,0)
A43: 40 Size Rules | B43: Blockmancer Asset Size + Folder Rules — 627 Source Update | C43: =COUNTA('40 Size Rules'!$B$5:$B$10000) | D43: =COUNTIF('40 Size Rules'!$A$5:$A$10000,"☑") | E43: =C43-D43 | F43: =IFERROR(D43/C43,0)
A44: 41 Audit Notes | B44: Release Audit Information Applied to Asset Checklist | C44: =COUNTA('41 Audit Notes'!$B$5:$B$10000) | D44: =COUNTIF('41 Audit Notes'!$A$5:$A$10000,"☑") | E44: =C44-D44 | F44: =IFERROR(D44/C44,0)
A45: 42 Folder Verification | B45: Folder Structure Re-Verification — Latest Runtime Audit | C45: =COUNTA('42 Folder Verification'!$B$5:$B$10000) | D45: =COUNTIF('42 Folder Verification'!$A$5:$A$10000,"☑") | E45: =C45-D45 | F45: =IFERROR(D45/C45,0)
A46: 43 Runtime Contract | B46: Runtime Asset Folder Contract — 627 Source Update | C46: =COUNTA('43 Runtime Contract'!$B$5:$B$10000) | D46: =COUNTIF('43 Runtime Contract'!$A$5:$A$10000,"☑") | E46: =C46-D46 | F46: =IFERROR(D46/C46,0)
A47: 44 Exact Runtime IDs | B47: Exact Runtime IDs from Latest Audit | C47: =COUNTA('44 Exact Runtime IDs'!$B$5:$B$10000) | D47: =COUNTIF('44 Exact Runtime IDs'!$A$5:$A$10000,"☑") | E47: =C47-D47 | F47: =IFERROR(D47/C47,0)
A48: 45 Character Paths | B48: Character Runtime Folder Contract — 627 Source Update | C48: =COUNTA('45 Character Paths'!$B$5:$B$10000) | D48: =COUNTIF('45 Character Paths'!$A$5:$A$10000,"☑") | E48: =C48-D48 | F48: =IFERROR(D48/C48,0)
A49: 46 VFX Exact Paths | B49: VFX Runtime Folder Contract — 627 Source Update | C49: =COUNTA('46 VFX Exact Paths'!$B$5:$B$10000) | D49: =COUNTIF('46 VFX Exact Paths'!$A$5:$A$10000,"☑") | E49: =C49-D49 | F49: =IFERROR(D49/C49,0)
A50: 47 Artist ZIP Layout | B50: Artist ZIP Layout — 627 Source Contract | C50: =COUNTA('47 Artist ZIP Layout'!$B$5:$B$10000) | D50: =COUNTIF('47 Artist ZIP Layout'!$A$5:$A$10000,"☑") | E50: =C50-D50 | F50: =IFERROR(D50/C50,0)
A51: 48 Legacy Compatibility | B51: Legacy Compatibility / Folder Mismatch Report | C51: =COUNTA('48 Legacy Compatibility'!$B$5:$B$10000) | D51: =COUNTIF('48 Legacy Compatibility'!$A$5:$A$10000,"☑") | E51: =C51-D51 | F51: =IFERROR(D51/C51,0)
A54: Workbook Notes
A55: Board gameplay blocks are intentionally unchanged at 24x24 and should not be upscaled.
A56: Heroes, monsters, and bosses now prefer 1254x1254 2x2 pose sheets with 627x627 cells.
A57: Items, spells, relics, upgrades, weapons, status, hazards, UI icons, thumbnails, portraits, and VFX now support 627x627 source art while rendering smaller in-game.
A58: Stage/fullscreen backgrounds keep portrait cover/contain sizing and are not forced into 627x627.
A59: Missing visual assets must use category fallbacks instead of crashing.

Sheet 00 Global Placeholder
A1: 0. Global Placeholder Assets — Visual
A2: Visual fallbacks only. Audio fallback lives in the separate SFX workbook.
A4: Done? | B4: Asset Key | C4: Suggested Path | D4: Designer Description | E4: Priority | F4: Source / Export Size | G4: Runtime Render Size | H4: Exact Frames / Count | I4: Final Folder Structure (relative to public/assets) | J4: Audit / Release Note | K4: GDD Theme / Prompt Note
A5: ☐ | B5: missing_texture | C5: placeholders/missing_texture.png | D5: Generic fallback texture for missing non-board image assets. | E5: P0 fallback | F5: 627x627 PNG source | G5: HUD/button 24-48px; inventory 32-64px; reward/shop card 64-96px; modal 96-128px | H5: Static fallback | I5: placeholders/ | J5: Updated: missing assets must not crash runtime. | Updated 2026-05-19: non-board visual source supports 627x627 PNG or 1254x1254 2x2 sheets; runtime display is category-constrained. | K5: Friendly temporary art, not dark/debug-looking.
A6: ☐ | B6: missing_hero | C6: placeholders/missing_hero.png | D6: Simple friendly character silhouette for missing hero sheets. | E6: P0 fallback | F6: 627x627 PNG source | G6: HUD/button 24-48px; inventory 32-64px; reward/shop card 64-96px; modal 96-128px | H6: Static fallback | I6: placeholders/ | J6: Fallback for heroPoseSheet. | Updated 2026-05-19: non-board visual source supports 627x627 PNG or 1254x1254 2x2 sheets; runtime display is category-constrained. | K6: Cheerful placeholder silhouette.
A7: ☐ | B7: missing_monster | C7: placeholders/missing_monster.png | D7: Cute monster silhouette for missing monster sheets. | E7: P0 fallback | F7: 627x627 PNG source | G7: HUD/button 24-48px; inventory 32-64px; reward/shop card 64-96px; modal 96-128px | H7: Static fallback | I7: placeholders/ | J7: Fallback for monsterPoseSheet. | Updated 2026-05-19: non-board visual source supports 627x627 PNG or 1254x1254 2x2 sheets; runtime display is category-constrained. | K7: Cute-chaotic placeholder.
A8: ☐ | B8: missing_boss | C8: placeholders/missing_boss.png | D8: Readable large boss silhouette for missing boss sheets. | E8: P0 fallback | F8: 627x627 PNG source | G8: HUD/button 24-48px; inventory 32-64px; reward/shop card 64-96px; modal 96-128px | H8: Static fallback | I8: placeholders/ | J8: Fallback for bossPoseSheet. | Updated 2026-05-19: non-board visual source supports 627x627 PNG or 1254x1254 2x2 sheets; runtime display is category-constrained. | K8: Funny boss placeholder, not scary.
A9: ☐ | B9: missing_portrait | C9: placeholders/missing_portrait.png | D9: Portrait fallback for hero/NPC/boss dialogue. | E9: P0 fallback | F9: 627x627 PNG portrait source | G9: Dialogue 96-128px; story/unlock modal 128-220px; preserve aspect ratio | H9: Static fallback | I9: placeholders/ | J9: Fallback for portraitKey. | Updated 2026-05-19: non-board visual source supports 627x627 PNG or 1254x1254 2x2 sheets; runtime display is category-constrained. | K9: Friendly portrait placeholder.
A10: ☐ | B10: missing_icon | C10: placeholders/missing_icon.png | D10: Readable missing icon tile for items, spells, relics, upgrades, weapons, status, hazards. | E10: P0 fallback | F10: 627x627 PNG source | G10: HUD/button 24-48px; inventory 32-64px; reward/shop card 64-96px; modal 96-128px | H10: Static fallback | I10: placeholders/ | J10: Fallback for iconKey. | Updated 2026-05-19: non-board visual source supports 627x627 PNG or 1254x1254 2x2 sheets; runtime display is category-constrained. | K10: Cute question-rune icon.
A11: ☐ | B11: missing_vfx | C11: placeholders/missing_vfx.png | D11: Generic sparkle burst for missing VFX hooks. | E11: P0 fallback | F11: 627x627 PNG source | G11: HUD/button 24-48px; inventory 32-64px; reward/shop card 64-96px; modal 96-128px | H11: Static or 4-frame fallback | I11: placeholders/ | J11: Fallback for vfxKey. | Updated 2026-05-19: non-board visual source supports 627x627 PNG or 1254x1254 2x2 sheets; runtime display is category-constrained. | K11: Sparkly magical cleanup feedback.
A12: ☐ | B12: missing_map_icon | C12: placeholders/missing_map_icon.png | D12: Fallback icon for map/room nodes. | E12: P0 fallback | F12: 627x627 PNG source | G12: HUD/button 24-48px; inventory 32-64px; reward/shop card 64-96px; modal 96-128px | H12: Static fallback | I12: placeholders/ | J12: Fallback for map icons. | Updated 2026-05-19: non-board visual source supports 627x627 PNG or 1254x1254 2x2 sheets; runtime display is category-constrained. | K12: Readable map marker.
A13: ☐ | B13: missing_bg | C13: placeholders/missing_bg.png | D13: Simple colorful fallback scene background. | E13: P0 fallback | F13: 627x627 PNG source | G13: HUD/button 24-48px; inventory 32-64px; reward/shop card 64-96px; modal 96-128px | H13: Static fallback | I13: placeholders/ | J13: Fullscreen fallback not 627-only. | Updated 2026-05-19: non-board visual source supports 627x627 PNG or 1254x1254 2x2 sheets; runtime display is category-constrained. | K13: Colorful non-distracting backdrop.

Sheet 08 BG - Scenes
A1: 8. Background Assets — Scenes
A2: Tracking sheet generated from the uploaded markdown. Done? is unchecked by default.
A4: Done? | B4: Asset Key | C4: Suggested Folder | D4: Designer Description | E4: Priority | F4: Source / Export Size | G4: Runtime Render Size | H4: Exact Frames / Count | I4: Final Folder Structure (relative to public/assets) | J4: Audit / Release Note | K4: GDD Theme / Prompt Note
A5: ☐ | B5: bg_scene_title_festival | C5: backgrounds/scenes/ | D5: Title screen image showing Brixonia festival, falling stars, and playful blocks. | E5: P0 | F5: Portrait background 720x1280 or 1080x1920 PNG; 627x627 only for thumbnails | G5: cover/contain portrait frame; do not force into icon rules | H5: Static/layered; parallax variants as needed | I5: backgrounds/ | J5: Audit: replace placeholder backgrounds on critical path. | Updated 2026-05-19: non-board visual source supports 627x627 PNG or 1254x1254 2x2 sheets; runtime display is category-constrained. | K5: Stage-themed cheerful festival dungeon backdrop.
A6: ☐ | B6: bg_scene_main_menu | C6: backgrounds/scenes/ | D6: Main menu scene with cozy arcade-festival framing. | E6: P0 | F6: Portrait background 720x1280 or 1080x1920 PNG; 627x627 only for thumbnails | G6: cover/contain portrait frame; do not force into icon rules | H6: Static/layered; parallax variants as needed | I6: backgrounds/ | J6: Audit: replace placeholder backgrounds on critical path. | Updated 2026-05-19: non-board visual source supports 627x627 PNG or 1254x1254 2x2 sheets; runtime display is category-constrained. | K6: Stage-themed cheerful festival dungeon backdrop.
A7: ☐ | B7: bg_scene_hub_brixonia | C7: backgrounds/scenes/ | D7: Festival hub overview with booths, lanterns, and colorful magical mess. | E7: P1 | F7: Portrait background 720x1280 or 1080x1920 PNG; 627x627 only for thumbnails | G7: cover/contain portrait frame; do not force into icon rules | H7: Static/layered; parallax variants as needed | I7: backgrounds/ | J7: Audit: replace placeholder backgrounds on critical path. | Updated 2026-05-19: non-board visual source supports 627x627 PNG or 1254x1254 2x2 sheets; runtime display is category-constrained. | K7: Stage-themed cheerful festival dungeon backdrop.
A8: ☐ | B8: bg_scene_hero_select | C8: backgrounds/scenes/ | D8: Hero select backdrop with stage or festival booth silhouettes. | E8: P1 | F8: Portrait background 720x1280 or 1080x1920 PNG; 627x627 only for thumbnails | G8: cover/contain portrait frame; do not force into icon rules | H8: Static/layered; parallax variants as needed | I8: backgrounds/ | J8: Audit: replace placeholder backgrounds on critical path. | Updated 2026-05-19: non-board visual source supports 627x627 PNG or 1254x1254 2x2 sheets; runtime display is category-constrained. | K8: Stage-themed cheerful festival dungeon backdrop.
A9: ☐ | B9: bg_scene_tutorial | C9: backgrounds/scenes/ | D9: Simple classroom/festival demo area for learning controls. | E9: P1 | F9: Portrait background 720x1280 or 1080x1920 PNG; 627x627 only for thumbnails | G9: cover/contain portrait frame; do not force into icon rules | H9: Static/layered; parallax variants as needed | I9: backgrounds/ | J9: Audit: replace placeholder backgrounds on critical path. | Updated 2026-05-19: non-board visual source supports 627x627 PNG or 1254x1254 2x2 sheets; runtime display is category-constrained. | K9: Stage-themed cheerful festival dungeon backdrop.
A10: ☐ | B10: bg_scene_reward | C10: backgrounds/scenes/ | D10: Reward backdrop with sparkles, cards, and treasure glow. | E10: P0 | F10: Portrait background 720x1280 or 1080x1920 PNG; 627x627 only for thumbnails | G10: cover/contain portrait frame; do not force into icon rules | H10: Static/layered; parallax variants as needed | I10: backgrounds/ | J10: Audit: replace placeholder backgrounds on critical path. | Updated 2026-05-19: non-board visual source supports 627x627 PNG or 1254x1254 2x2 sheets; runtime display is category-constrained. | K10: Stage-themed cheerful festival dungeon backdrop.
A11: ☐ | B11: bg_scene_shop | C11: backgrounds/scenes/ | D11: Marnie’s cozy merchant stall filled with snacks and items. | E11: P0 | F11: Portrait background 720x1280 or 1080x1920 PNG; 627x627 only for thumbnails | G11: cover/contain portrait frame; do not force into icon rules | H11: Static/layered; parallax variants as needed | I11: backgrounds/ | J11: Audit: replace placeholder backgrounds on critical path. | Updated 2026-05-19: non-board visual source supports 627x627 PNG or 1254x1254 2x2 sheets; runtime display is category-constrained. | K11: Stage-themed cheerful festival dungeon backdrop.
A12: ☐ | B12: bg_scene_event | C12: backgrounds/scenes/ | D12: Generic event backdrop with flexible festival/dungeon props. | E12: P1 | F12: Portrait background 720x1280 or 1080x1920 PNG; 627x627 only for thumbnails | G12: cover/contain portrait frame; do not force into icon rules | H12: Static/layered; parallax variants as needed | I12: backgrounds/ | J12: Audit: replace placeholder backgrounds on critical path. | Updated 2026-05-19: non-board visual source supports 627x627 PNG or 1254x1254 2x2 sheets; runtime display is category-constrained. | K12: Stage-themed cheerful festival dungeon backdrop.
A13: ☐ | B13: bg_scene_rest | C13: backgrounds/scenes/ | D13: Safe rest spot with pillows, snacks, and warm lanterns. | E13: P1 | F13: Portrait background 720x1280 or 1080x1920 PNG; 627x627 only for thumbnails | G13: cover/contain portrait frame; do not force into icon rules | H13: Static/layered; parallax variants as needed | I13: backgrounds/ | J13: Audit: replace placeholder backgrounds on critical path. | Updated 2026-05-19: non-board visual source supports 627x627 PNG or 1254x1254 2x2 sheets; runtime display is category-constrained. | K13: Stage-themed cheerful festival dungeon backdrop.
A14: ☐ | B14: bg_scene_treasure | C14: backgrounds/scenes/ | D14: Treasure room with glowing chest and playful sparkles. | E14: P1 | F14: Portrait background 720x1280 or 1080x1920 PNG; 627x627 only for thumbnails | G14: cover/contain portrait frame; do not force into icon rules | H14: Static/layered; parallax variants as needed | I14: backgrounds/ | J14: Audit: replace placeholder backgrounds on critical path. | Updated 2026-05-19: non-board visual source supports 627x627 PNG or 1254x1254 2x2 sheets; runtime display is category-constrained. | K14: Stage-themed cheerful festival dungeon backdrop.
A15: ☐ | B15: bg_scene_game_over | C15: backgrounds/scenes/ | D15: Soft defeat backdrop with block pile and encouraging restart tone. | E15: P0 | F15: Portrait background 720x1280 or 1080x1920 PNG; 627x627 only for thumbnails | G15: cover/contain portrait frame; do not force into icon rules | H15: Static/layered; parallax variants as needed | I15: backgrounds/ | J15: Audit: replace placeholder backgrounds on critical path. | Updated 2026-05-19: non-board visual source supports 627x627 PNG or 1254x1254 2x2 sheets; runtime display is category-constrained. | K15: Stage-themed cheerful festival dungeon backdrop.
... A19: ☐ | B19: bg_scene_settings | C19: backgrounds/scenes/ | D19: Simple readable settings backdrop with cozy UI frame. | E19: P1 | F19: Portrait background 720x1280 or 1080x1920 PNG; 627x627 only for thumbnails | G19: cover/contain portrait frame; do not force into icon rules | H19: Static/layered; parallax variants as needed | I19: backgrounds/ | J19: Audit: replace placeholder backgrounds on critical path. | Updated 2026-05-19: non-board visual source supports 627x627 PNG or 1254x1254 2x2 sheets; runtime display is category-constrained. | K19: Stage-themed cheerful festival dungeon backdrop.

Sheet 09 BG - Stage Battle Parallax
A1: 9. Background Assets — Stage Battle Parallax
A2: Tracking sheet generated from the uploaded markdown. Done? is unchecked by default.
A4: Done? | B4: Asset Key | C4: Suggested Folder | D4: Designer Description | E4: Priority | F4: Source / Export Size | G4: Runtime Render Size | H4: Exact Frames / Count | I4: Final Folder Structure (relative to public/assets) | J4: Audit / Release Note | K4: GDD Theme / Prompt Note
A5: ☐ | B5: bg_stage_sprinkle_sewers_battle_far | C5: backgrounds/stages/ | D5: Sprinkle Sewers battle background distant parallax layer; show candy sewer with rainbow water, frosting pipes, and cupcake slime colors. | E5: P0 | F5: Portrait background 720x1280 or 1080x1920 PNG; 627x627 only for thumbnails | G5: cover/contain portrait frame; do not force into icon rules | H5: Static/layered; parallax variants as needed | I5: backgrounds/ | J5: Audit: replace placeholder backgrounds on critical path. | Updated 2026-05-19: non-board visual source supports 627x627 PNG or 1254x1254 2x2 sheets; runtime display is category-constrained. | K5: Stage-themed cheerful festival dungeon backdrop.
A6: ☐ | B6: bg_stage_sprinkle_sewers_battle_mid | C6: backgrounds/stages/ | D6: Sprinkle Sewers battle background main scenic layer; show candy sewer with rainbow water, frosting pipes, and cupcake slime colors. | E6: P0 | F6: Portrait background 720x1280 or 1080x1920 PNG; 627x627 only for thumbnails | G6: cover/contain portrait frame; do not force into icon rules | H6: Static/layered; parallax variants as needed | I6: backgrounds/ | J6: Audit: replace placeholder backgrounds on critical path. | Updated 2026-05-19: non-board visual source supports 627x627 PNG or 1254x1254 2x2 sheets; runtime display is category-constrained. | K6: Stage-themed cheerful festival dungeon backdrop.
A7: ☐ | B7: bg_stage_sprinkle_sewers_battle_near | C7: backgrounds/stages/ | D7: Sprinkle Sewers battle background foreground framing layer; show candy sewer with rainbow water, frosting pipes, and cupcake slime colors. | E7: P0 | F7: Portrait background 720x1280 or 1080x1920 PNG; 627x627 only for thumbnails | G7: cover/contain portrait frame; do not force into icon rules | H7: Static/layered; parallax variants as needed | I7: backgrounds/ | J7: Audit: replace placeholder backgrounds on critical path. | Updated 2026-05-19: non-board visual source supports 627x627 PNG or 1254x1254 2x2 sheets; runtime display is category-constrained. | K7: Stage-themed cheerful festival dungeon backdrop.
A8: ☐ | B8: bg_stage_goblin_workshop_battle_far | C8: backgrounds/stages/ | D8: Goblin Workshop battle background distant parallax layer; show goblin machinery, toy bombs, springs, gears, and warning signs. | E8: P0 | F8: Portrait background 720x1280 or 1080x1920 PNG; 627x627 only for thumbnails | G8: cover/contain portrait frame; do not force into icon rules | H8: Static/layered; parallax variants as needed | I8: backgrounds/ | J8: Audit: replace placeholder backgrounds on critical path. | Updated 2026-05-19: non-board visual source supports 627x627 PNG or 1254x1254 2x2 sheets; runtime display is category-constrained. | K8: Stage-themed cheerful festival dungeon backdrop.
A9: ☐ | B9: bg_stage_goblin_workshop_battle_mid | C9: backgrounds/stages/ | D9: Goblin Workshop battle background main scenic layer; show goblin machinery, toy bombs, springs, gears, and warning signs. | E9: P0 | F9: Portrait background 720x1280 or 1080x1920 PNG; 627x627 only for thumbnails | G9: cover/contain portrait frame; do not force into icon rules | H9: Static/layered; parallax variants as needed | I9: backgrounds/ | J9: Audit: replace placeholder backgrounds on critical path. | Updated 2026-05-19: non-board visual source supports 627x627 PNG or 1254x1254 2x2 sheets; runtime display is category-constrained. | K9: Stage-themed cheerful festival dungeon backdrop.
A10: ☐ | B10: bg_stage_goblin_workshop_battle_near | C10: backgrounds/stages/ | D10: Goblin Workshop battle background foreground framing layer; show goblin machinery, toy bombs, springs, gears, and warning signs. | E10: P0 | F10: Portrait background 720x1280 or 1080x1920 PNG; 627x627 only for thumbnails | G10: cover/contain portrait frame; do not force into icon rules | H10: Static/layered; parallax variants as needed | I10: backgrounds/ | J10: Audit: replace placeholder backgrounds on critical path. | Updated 2026-05-19: non-board visual source supports 627x627 PNG or 1254x1254 2x2 sheets; runtime display is category-constrained. | K10: Stage-themed cheerful festival dungeon backdrop.
A11: ☐ | B11: bg_stage_frosty_pantry_battle_far | C11: backgrounds/stages/ | D11: Frosty Pantry battle background distant parallax layer; show magical freezer with ice cream crates, cold mist, and slippery tiles. | E11: P1 | F11: Portrait background 720x1280 or 1080x1920 PNG; 627x627 only for thumbnails | G11: cover/contain portrait frame; do not force into icon rules | H11: Static/layered; parallax variants as needed | I11: backgrounds/ | J11: Audit: replace placeholder backgrounds on critical path. | Updated 2026-05-19: non-board visual source supports 627x627 PNG or 1254x1254 2x2 sheets; runtime display is category-constrained. | K11: Stage-themed cheerful festival dungeon backdrop.
A12: ☐ | B12: bg_stage_frosty_pantry_battle_mid | C12: backgrounds/stages/ | D12: Frosty Pantry battle background main scenic layer; show magical freezer with ice cream crates, cold mist, and slippery tiles. | E12: P1 | F12: Portrait background 720x1280 or 1080x1920 PNG; 627x627 only for thumbnails | G12: cover/contain portrait frame; do not force into icon rules | H12: Static/layered; parallax variants as needed | I12: backgrounds/ | J12: Audit: replace placeholder backgrounds on critical path. | Updated 2026-05-19: non-board visual source supports 627x627 PNG or 1254x1254 2x2 sheets; runtime display is category-constrained. | K12: Stage-themed cheerful festival dungeon backdrop.
A13: ☐ | B13: bg_stage_frosty_pantry_battle_near | C13: backgrounds/stages/ | D13: Frosty Pantry battle background foreground framing layer; show magical freezer with ice cream crates, cold mist, and slippery tiles. | E13: P1 | F13: Portrait background 720x1280 or 1080x1920 PNG; 627x627 only for thumbnails | G13: cover/contain portrait frame; do not force into icon rules | H13: Static/layered; parallax variants as needed | I13: backgrounds/ | J13: Audit: replace placeholder backgrounds on critical path. | Updated 2026-05-19: non-board visual source supports 627x627 PNG or 1254x1254 2x2 sheets; runtime display is category-constrained. | K13: Stage-themed cheerful festival dungeon backdrop.
A14: ☐ | B14: bg_stage_pillow_castle_battle_far | C14: backgrounds/stages/ | D14: Pillow Castle battle background distant parallax layer; show soft pillow fortress with plush toys, blankets, and sleepy fabric shapes. | E14: P1 | F14: Portrait background 720x1280 or 1080x1920 PNG; 627x627 only for thumbnails | G14: cover/contain portrait frame; do not force into icon rules | H14: Static/layered; parallax variants as needed | I14: backgrounds/ | J14: Audit: replace placeholder backgrounds on critical path. | Updated 2026-05-19: non-board visual source supports 627x627 PNG or 1254x1254 2x2 sheets; runtime display is category-constrained. | K14: Stage-themed cheerful festival dungeon backdrop.
A15: ☐ | B15: bg_stage_pillow_castle_battle_mid | C15: backgrounds/stages/ | D15: Pillow Castle battle background main scenic layer; show soft pillow fortress with plush toys, blankets, and sleepy fabric shapes. | E15: P1 | F15: Portrait background 720x1280 or 1080x1920 PNG; 627x627 only for thumbnails | G15: cover/contain portrait frame; do not force into icon rules | H15: Static/layered; parallax variants as needed | I15: backgrounds/ | J15: Audit: replace placeholder backgrounds on critical path. | Updated 2026-05-19: non-board visual source supports 627x627 PNG or 1254x1254 2x2 sheets; runtime display is category-constrained. | K15: Stage-themed cheerful festival dungeon backdrop.
... A22: ☐ | B22: bg_stage_bloxley_block_palace_battle_near | C22: backgrounds/stages/ | D22: Bloxley’s Block Palace battle background foreground framing layer; show royal block palace with square banners, confetti cannons, and toy flags. | E22: P1 | F22: Portrait background 720x1280 or 1080x1920 PNG; 627x627 only for thumbnails | G22: cover/contain portrait frame; do not force into icon rules | H22: Static/layered; parallax variants as needed | I22: backgrounds/ | J22: Audit: replace placeholder backgrounds on critical path. | Updated 2026-05-19: non-board visual source supports 627x627 PNG or 1254x1254 2x2 sheets; runtime display is category-constrained. | K22: Stage-themed cheerful festival dungeon backdrop.

Sheet 10 BG - Boss Arenas
A1: 10. Background Assets — Boss Arenas
A2: Tracking sheet generated from the uploaded markdown. Done? is unchecked by default.
A4: Done? | B4: Asset Key | C4: Suggested Folder | D4: Designer Description | E4: Priority | F4: Source / Export Size | G4: Runtime Render Size | H4: Exact Frames / Count | I4: Final Folder Structure (relative to public/assets) | J4: Audit / Release Note | K4: GDD Theme / Prompt Note
A5: ☐ | B5: bg_boss_cupcake_slime_king_arena | C5: backgrounds/stages/ | D5: Boss-specific arena for Cupcake Slime King: sticky candy sewer boss arena with frosting puddles and giant cupcake slime throne. | E5: P1 | F5: Portrait background 720x1280 or 1080x1920 PNG; 627x627 only for thumbnails | G5: cover/contain portrait frame; do not force into icon rules | H5: Static/layered; parallax variants as needed | I5: backgrounds/ | J5: Audit: replace placeholder backgrounds on critical path. | Updated 2026-05-19: non-board visual source supports 627x627 PNG or 1254x1254 2x2 sheets; runtime display is category-constrained. | K5: Stage-themed cheerful festival dungeon backdrop.
A6: ☐ | B6: bg_boss_prototype_no_7_arena | C6: backgrounds/stages/ | D6: Boss-specific arena for Prototype No. 7: malfunctioning workshop arena with safe-looking machines and bomb props. | E6: P1 | F6: Portrait background 720x1280 or 1080x1920 PNG; 627x627 only for thumbnails | G6: cover/contain portrait frame; do not force into icon rules | H6: Static/layered; parallax variants as needed | I6: backgrounds/ | J6: Audit: replace placeholder backgrounds on critical path. | Updated 2026-05-19: non-board visual source supports 627x627 PNG or 1254x1254 2x2 sheets; runtime display is category-constrained. | K6: Stage-themed cheerful festival dungeon backdrop.
A7: ☐ | B7: bg_boss_gelato_golem_arena | C7: backgrounds/stages/ | D7: Boss-specific arena for Gelato Golem: freezer boss arena with melting rainbow gelato and ice platforms. | E7: P1 | F7: Portrait background 720x1280 or 1080x1920 PNG; 627x627 only for thumbnails | G7: cover/contain portrait frame; do not force into icon rules | H7: Static/layered; parallax variants as needed | I7: backgrounds/ | J7: Audit: replace placeholder backgrounds on critical path. | Updated 2026-05-19: non-board visual source supports 627x627 PNG or 1254x1254 2x2 sheets; runtime display is category-constrained. | K7: Stage-themed cheerful festival dungeon backdrop.
A8: ☐ | B8: bg_boss_sir_snore_a_lot_arena | C8: backgrounds/stages/ | D8: Boss-specific arena for Sir Snore-a-Lot: pillow castle boss arena with blanket banners and sleepy toy shields. | E8: P1 | F8: Portrait background 720x1280 or 1080x1920 PNG; 627x627 only for thumbnails | G8: cover/contain portrait frame; do not force into icon rules | H8: Static/layered; parallax variants as needed | I8: backgrounds/ | J8: Audit: replace placeholder backgrounds on critical path. | Updated 2026-05-19: non-board visual source supports 627x627 PNG or 1254x1254 2x2 sheets; runtime display is category-constrained. | K8: Stage-themed cheerful festival dungeon backdrop.
A9: ☐ | B9: bg_boss_high_score_hydra_arena | C9: backgrounds/stages/ | D9: Boss-specific arena for High Score Hydra: arcade boss arena with scoreboard, neon combo lights, and hydra cabinet energy. | E9: P1 | F9: Portrait background 720x1280 or 1080x1920 PNG; 627x627 only for thumbnails | G9: cover/contain portrait frame; do not force into icon rules | H9: Static/layered; parallax variants as needed | I9: backgrounds/ | J9: Audit: replace placeholder backgrounds on critical path. | Updated 2026-05-19: non-board visual source supports 627x627 PNG or 1254x1254 2x2 sheets; runtime display is category-constrained. | K9: Stage-themed cheerful festival dungeon backdrop.
A10: ☐ | B10: bg_boss_king_bloxley_arena | C10: backgrounds/stages/ | D10: Boss-specific arena for King Bloxley: final royal block throne room with symmetry marks and confetti cannons. | E10: P1 | F10: Portrait background 720x1280 or 1080x1920 PNG; 627x627 only for thumbnails | G10: cover/contain portrait frame; do not force into icon rules | H10: Static/layered; parallax variants as needed | I10: backgrounds/ | J10: Audit: replace placeholder backgrounds on critical path. | Updated 2026-05-19: non-board visual source supports 627x627 PNG or 1254x1254 2x2 sheets; runtime display is category-constrained. | K10: Stage-themed cheerful festival dungeon backdrop.

Sheet 11 Map - Map BGs
A1: 11. Map Assets — Map Backgrounds
A2: Tracking sheet generated from the uploaded markdown. Done? is unchecked by default.
A4: Done? | B4: Asset Key | C4: Suggested Folder | D4: Designer Description | E4: Priority | F4: Source / Export Size | G4: Runtime Render Size | H4: Exact Frames / Count | I4: Final Folder Structure (relative to public/assets) | J4: Audit / Release Note | K4: GDD Theme / Prompt Note
A5: ☐ | B5: bg_map_sprinkle_sewers | C5: backgrounds/maps/ | D5: Roguelike map background for Sprinkle Sewers; use icons/paths over this readable stage map. | E5: P0 | F5: 627x627 PNG source for nodes/icons/routes; backgrounds use portrait size | G5: Map node 32-56px; selected node/detail 64-96px; route card 96-180px | H5: State variants as needed | I5: icons/map-nodes/ | J5: Audit: Stage 6 route node/smoke testing pending. | Updated 2026-05-19: non-board visual source supports 627x627 PNG or 1254x1254 2x2 sheets; runtime display is category-constrained. | K5: Cheerful stage-map icon; readable normal/event/shop/rest/treasure/elite/boss state.
A6: ☐ | B6: bg_map_goblin_workshop | C6: backgrounds/maps/ | D6: Roguelike map background for Goblin Workshop; use icons/paths over this readable stage map. | E6: P1 | F6: 627x627 PNG source for nodes/icons/routes; backgrounds use portrait size | G6: Map node 32-56px; selected node/detail 64-96px; route card 96-180px | H6: State variants as needed | I6: icons/map-nodes/ | J6: Audit: Stage 6 route node/smoke testing pending. | Updated 2026-05-19: non-board visual source supports 627x627 PNG or 1254x1254 2x2 sheets; runtime display is category-constrained. | K6: Cheerful stage-map icon; readable normal/event/shop/rest/treasure/elite/boss state.
A7: ☐ | B7: bg_map_frosty_pantry | C7: backgrounds/maps/ | D7: Roguelike map background for Frosty Pantry; use icons/paths over this readable stage map. | E7: P1 | F7: 627x627 PNG source for nodes/icons/routes; backgrounds use portrait size | G7: Map node 32-56px; selected node/detail 64-96px; route card 96-180px | H7: State variants as needed | I7: icons/map-nodes/ | J7: Audit: Stage 6 route node/smoke testing pending. | Updated 2026-05-19: non-board visual source supports 627x627 PNG or 1254x1254 2x2 sheets; runtime display is category-constrained. | K7: Cheerful stage-map icon; readable normal/event/shop/rest/treasure/elite/boss state.
A8: ☐ | B8: bg_map_pillow_castle | C8: backgrounds/maps/ | D8: Roguelike map background for Pillow Castle; use icons/paths over this readable stage map. | E8: P1 | F8: 627x627 PNG source for nodes/icons/routes; backgrounds use portrait size | G8: Map node 32-56px; selected node/detail 64-96px; route card 96-180px | H8: State variants as needed | I8: icons/map-nodes/ | J8: Audit: Stage 6 route node/smoke testing pending. | Updated 2026-05-19: non-board visual source supports 627x627 PNG or 1254x1254 2x2 sheets; runtime display is category-constrained. | K8: Cheerful stage-map icon; readable normal/event/shop/rest/treasure/elite/boss state.
A9: ☐ | B9: bg_map_starfall_arcade | C9: backgrounds/maps/ | D9: Roguelike map background for Starfall Arcade; use icons/paths over this readable stage map. | E9: P1 | F9: 627x627 PNG source for nodes/icons/routes; backgrounds use portrait size | G9: Map node 32-56px; selected node/detail 64-96px; route card 96-180px | H9: State variants as needed | I9: icons/map-nodes/ | J9: Audit: Stage 6 route node/smoke testing pending. | Updated 2026-05-19: non-board visual source supports 627x627 PNG or 1254x1254 2x2 sheets; runtime display is category-constrained. | K9: Cheerful stage-map icon; readable normal/event/shop/rest/treasure/elite/boss state.
A10: ☐ | B10: bg_map_bloxley_block_palace | C10: backgrounds/maps/ | D10: Roguelike map background for Bloxley’s Block Palace; use icons/paths over this readable stage map. | E10: P1 | F10: 627x627 PNG source for nodes/icons/routes; backgrounds use portrait size | G10: Map node 32-56px; selected node/detail 64-96px; route card 96-180px | H10: State variants as needed | I10: icons/map-nodes/ | J10: Audit: Stage 6 route node/smoke testing pending. | Updated 2026-05-19: non-board visual source supports 627x627 PNG or 1254x1254 2x2 sheets; runtime display is category-constrained. | K10: Cheerful stage-map icon; readable normal/event/shop/rest/treasure/elite/boss state.

Sheet 12 Map - Node States
A1: 12. Map Assets — Node States
A2: Tracking sheet generated from the uploaded markdown. Done? is unchecked by default.
A4: Done? | B4: Asset Key | C4: Suggested Folder | D4: Designer Description | E4: Priority | F4: Source / Export Size | G4: Runtime Render Size | H4: Exact Frames / Count | I4: Final Folder Structure (relative to public/assets) | J4: Audit / Release Note | K4: GDD Theme / Prompt Note
A5: ☐ | B5: map_node_start_locked | C5: map/nodes/ | D5: Start node, safe and friendly entry point. Unavailable gray/low-saturation state. Must be readable at mobile size. | E5: P0 | F5: 627x627 PNG source for nodes/icons/routes; backgrounds use portrait size | G5: Map node 32-56px; selected node/detail 64-96px; route card 96-180px | H5: State variants as needed | I5: icons/map-nodes/ | J5: Audit: Stage 6 route node/smoke testing pending. | Updated 2026-05-19: non-board visual source supports 627x627 PNG or 1254x1254 2x2 sheets; runtime display is category-constrained. | K5: Cheerful stage-map icon; readable normal/event/shop/rest/treasure/elite/boss state.
A6: ☐ | B6: map_node_start_available | C6: map/nodes/ | D6: Start node, safe and friendly entry point. Selectable glowing state. Must be readable at mobile size. | E6: P0 | F6: 627x627 PNG source for nodes/icons/routes; backgrounds use portrait size | G6: Map node 32-56px; selected node/detail 64-96px; route card 96-180px | H6: State variants as needed | I6: icons/map-nodes/ | J6: Audit: Stage 6 route node/smoke testing pending. | Updated 2026-05-19: non-board visual source supports 627x627 PNG or 1254x1254 2x2 sheets; runtime display is category-constrained. | K6: Cheerful stage-map icon; readable normal/event/shop/rest/treasure/elite/boss state.
A7: ☐ | B7: map_node_start_current | C7: map/nodes/ | D7: Start node, safe and friendly entry point. Current player position state. Must be readable at mobile size. | E7: P0 | F7: 627x627 PNG source for nodes/icons/routes; backgrounds use portrait size | G7: Map node 32-56px; selected node/detail 64-96px; route card 96-180px | H7: State variants as needed | I7: icons/map-nodes/ | J7: Audit: Stage 6 route node/smoke testing pending. | Updated 2026-05-19: non-board visual source supports 627x627 PNG or 1254x1254 2x2 sheets; runtime display is category-constrained. | K7: Cheerful stage-map icon; readable normal/event/shop/rest/treasure/elite/boss state.
A8: ☐ | B8: map_node_start_completed | C8: map/nodes/ | D8: Start node, safe and friendly entry point. Completed checked/cleared state. Must be readable at mobile size. | E8: P0 | F8: 627x627 PNG source for nodes/icons/routes; backgrounds use portrait size | G8: Map node 32-56px; selected node/detail 64-96px; route card 96-180px | H8: State variants as needed | I8: icons/map-nodes/ | J8: Audit: Stage 6 route node/smoke testing pending. | Updated 2026-05-19: non-board visual source supports 627x627 PNG or 1254x1254 2x2 sheets; runtime display is category-constrained. | K8: Cheerful stage-map icon; readable normal/event/shop/rest/treasure/elite/boss state.
A9: ☐ | B9: map_node_normal_locked | C9: map/nodes/ | D9: Normal battle node with small monster symbol. Unavailable gray/low-saturation state. Must be readable at mobile size. | E9: P0 | F9: 627x627 PNG source for nodes/icons/routes; backgrounds use portrait size | G9: Map node 32-56px; selected node/detail 64-96px; route card 96-180px | H9: State variants as needed | I9: icons/map-nodes/ | J9: Audit: Stage 6 route node/smoke testing pending. | Updated 2026-05-19: non-board visual source supports 627x627 PNG or 1254x1254 2x2 sheets; runtime display is category-constrained. | K9: Cheerful stage-map icon; readable normal/event/shop/rest/treasure/elite/boss state.
A10: ☐ | B10: map_node_normal_available | C10: map/nodes/ | D10: Normal battle node with small monster symbol. Selectable glowing state. Must be readable at mobile size. | E10: P0 | F10: 627x627 PNG source for nodes/icons/routes; backgrounds use portrait size | G10: Map node 32-56px; selected node/detail 64-96px; route card 96-180px | H10: State variants as needed | I10: icons/map-nodes/ | J10: Audit: Stage 6 route node/smoke testing pending. | Updated 2026-05-19: non-board visual source supports 627x627 PNG or 1254x1254 2x2 sheets; runtime display is category-constrained. | K10: Cheerful stage-map icon; readable normal/event/shop/rest/treasure/elite/boss state.
A11: ☐ | B11: map_node_normal_current | C11: map/nodes/ | D11: Normal battle node with small monster symbol. Current player position state. Must be readable at mobile size. | E11: P0 | F11: 627x627 PNG source for nodes/icons/routes; backgrounds use portrait size | G11: Map node 32-56px; selected node/detail 64-96px; route card 96-180px | H11: State variants as needed | I11: icons/map-nodes/ | J11: Audit: Stage 6 route node/smoke testing pending. | Updated 2026-05-19: non-board visual source supports 627x627 PNG or 1254x1254 2x2 sheets; runtime display is category-constrained. | K11: Cheerful stage-map icon; readable normal/event/shop/rest/treasure/elite/boss state.
A12: ☐ | B12: map_node_normal_completed | C12: map/nodes/ | D12: Normal battle node with small monster symbol. Completed checked/cleared state. Must be readable at mobile size. | E12: P0 | F12: 627x627 PNG source for nodes/icons/routes; backgrounds use portrait size | G12: Map node 32-56px; selected node/detail 64-96px; route card 96-180px | H12: State variants as needed | I12: icons/map-nodes/ | J12: Audit: Stage 6 route node/smoke testing pending. | Updated 2026-05-19: non-board visual source supports 627x627 PNG or 1254x1254 2x2 sheets; runtime display is category-constrained. | K12: Cheerful stage-map icon; readable normal/event/shop/rest/treasure/elite/boss state.
A13: ☐ | B13: map_node_elite_locked | C13: map/nodes/ | D13: Elite battle node with stronger warning frame. Unavailable gray/low-saturation state. Must be readable at mobile size. | E13: P1 | F13: 627x627 PNG source for nodes/icons/routes; backgrounds use portrait size | G13: Map node 32-56px; selected node/detail 64-96px; route card 96-180px | H13: State variants as needed | I13: icons/map-nodes/ | J13: Audit: Stage 6 route node/smoke testing pending. | Updated 2026-05-19: non-board visual source supports 627x627 PNG or 1254x1254 2x2 sheets; runtime display is category-constrained. | K13: Cheerful stage-map icon; readable normal/event/shop/rest/treasure/elite/boss state.
A14: ☐ | B14: map_node_elite_available | C14: map/nodes/ | D14: Elite battle node with stronger warning frame. Selectable glowing state. Must be readable at mobile size. | E14: P1 | F14: 627x627 PNG source for nodes/icons/routes; backgrounds use portrait size | G14: Map node 32-56px; selected node/detail 64-96px; route card 96-180px | H14: State variants as needed | I14: icons/map-nodes/ | J14: Audit: Stage 6 route node/smoke testing pending. | Updated 2026-05-19: non-board visual source supports 627x627 PNG or 1254x1254 2x2 sheets; runtime display is category-constrained. | K14: Cheerful stage-map icon; readable normal/event/shop/rest/treasure/elite/boss state.
A15: ☐ | B15: map_node_elite_current | C15: map/nodes/ | D15: Elite battle node with stronger warning frame. Current player position state. Must be readable at mobile size. | E15: P1 | F15: 627x627 PNG source for nodes/icons/routes; backgrounds use portrait size | G15: Map node 32-56px; selected node/detail 64-96px; route card 96-180px | H15: State variants as needed | I15: icons/map-nodes/ | J15: Audit: Stage 6 route node/smoke testing pending. | Updated 2026-05-19: non-board visual source supports 627x627 PNG or 1254x1254 2x2 sheets; runtime display is category-constrained. | K15: Cheerful stage-map icon; readable normal/event/shop/rest/treasure/elite/boss state.
... A44: ☐ | B44: map_node_mini_boss_completed | C44: map/nodes/ | D44: Mini-boss or royal guard node before final boss. Completed checked/cleared state. Must be readable at mobile size. | E44: P1 | F44: 627x627 PNG source for nodes/icons/routes; backgrounds use portrait size | G44: Map node 32-56px; selected node/detail 64-96px; route card 96-180px | H44: State variants as needed | I44: icons/map-nodes/ | J44: Audit: Stage 6 route node/smoke testing pending. | Updated 2026-05-19: non-board visual source supports 627x627 PNG or 1254x1254 2x2 sheets; runtime display is category-constrained. | K44: Cheerful stage-map icon; readable normal/event/shop/rest/treasure/elite/boss state.

Sheet 13 Map - Paths and Decorations
A1: 13. Map Assets — Paths and Decorations
A2: Tracking sheet generated from the uploaded markdown. Done? is unchecked by default.
A4: Done? | B4: Asset Key | C4: Suggested Folder | D4: Designer Description | E4: Priority | F4: Source / Export Size | G4: Runtime Render Size | H4: Exact Frames / Count | I4: Final Folder Structure (relative to public/assets) | J4: Audit / Release Note | K4: GDD Theme / Prompt Note
A5: ☐ | B5: map_path_line_locked | C5: map/paths/ | D5: Thin muted line showing locked route connection. | E5: P0 | F5: 627x627 PNG source for nodes/icons/routes; backgrounds use portrait size | G5: Map node 32-56px; selected node/detail 64-96px; route card 96-180px | H5: State variants as needed | I5: icons/map-nodes/ | J5: Audit: Stage 6 route node/smoke testing pending. | Updated 2026-05-19: non-board visual source supports 627x627 PNG or 1254x1254 2x2 sheets; runtime display is category-constrained. | K5: Cheerful stage-map icon; readable normal/event/shop/rest/treasure/elite/boss state.
A6: ☐ | B6: map_path_line_available | C6: map/paths/ | D6: Clear readable line showing selectable route connection. | E6: P0 | F6: 627x627 PNG source for nodes/icons/routes; backgrounds use portrait size | G6: Map node 32-56px; selected node/detail 64-96px; route card 96-180px | H6: State variants as needed | I6: icons/map-nodes/ | J6: Audit: Stage 6 route node/smoke testing pending. | Updated 2026-05-19: non-board visual source supports 627x627 PNG or 1254x1254 2x2 sheets; runtime display is category-constrained. | K6: Cheerful stage-map icon; readable normal/event/shop/rest/treasure/elite/boss state.
A7: ☐ | B7: map_path_line_completed | C7: map/paths/ | D7: Route line showing already traveled path. | E7: P0 | F7: 627x627 PNG source for nodes/icons/routes; backgrounds use portrait size | G7: Map node 32-56px; selected node/detail 64-96px; route card 96-180px | H7: State variants as needed | I7: icons/map-nodes/ | J7: Audit: Stage 6 route node/smoke testing pending. | Updated 2026-05-19: non-board visual source supports 627x627 PNG or 1254x1254 2x2 sheets; runtime display is category-constrained. | K7: Cheerful stage-map icon; readable normal/event/shop/rest/treasure/elite/boss state.
A8: ☐ | B8: map_path_dotted_locked | C8: map/paths/ | D8: Optional dotted locked route style for alternate branches. | E8: P1 | F8: 627x627 PNG source for nodes/icons/routes; backgrounds use portrait size | G8: Map node 32-56px; selected node/detail 64-96px; route card 96-180px | H8: State variants as needed | I8: icons/map-nodes/ | J8: Audit: Stage 6 route node/smoke testing pending. | Updated 2026-05-19: non-board visual source supports 627x627 PNG or 1254x1254 2x2 sheets; runtime display is category-constrained. | K8: Cheerful stage-map icon; readable normal/event/shop/rest/treasure/elite/boss state.
A9: ☐ | B9: map_path_glow_available | C9: map/paths/ | D9: Glowing route overlay for newly opened path. | E9: P1 | F9: 627x627 PNG source for nodes/icons/routes; backgrounds use portrait size | G9: Map node 32-56px; selected node/detail 64-96px; route card 96-180px | H9: State variants as needed | I9: icons/map-nodes/ | J9: Audit: Stage 6 route node/smoke testing pending. | Updated 2026-05-19: non-board visual source supports 627x627 PNG or 1254x1254 2x2 sheets; runtime display is category-constrained. | K9: Cheerful stage-map icon; readable normal/event/shop/rest/treasure/elite/boss state.
A10: ☐ | B10: map_deco_sprinkle_sewers_cupcake_pipe | C10: map/decorations/ | D10: Small cupcake/frosting pipe decoration for Stage 1 map. | E10: P2 | F10: 627x627 PNG source for nodes/icons/routes; backgrounds use portrait size | G10: Map node 32-56px; selected node/detail 64-96px; route card 96-180px | H10: State variants as needed | I10: icons/map-nodes/ | J10: Audit: Stage 6 route node/smoke testing pending. | Updated 2026-05-19: non-board visual source supports 627x627 PNG or 1254x1254 2x2 sheets; runtime display is category-constrained. | K10: Cheerful stage-map icon; readable normal/event/shop/rest/treasure/elite/boss state.
A11: ☐ | B11: map_deco_goblin_workshop_gear | C11: map/decorations/ | D11: Small gear/spring decoration for Stage 2 map. | E11: P2 | F11: 627x627 PNG source for nodes/icons/routes; backgrounds use portrait size | G11: Map node 32-56px; selected node/detail 64-96px; route card 96-180px | H11: State variants as needed | I11: icons/map-nodes/ | J11: Audit: Stage 6 route node/smoke testing pending. | Updated 2026-05-19: non-board visual source supports 627x627 PNG or 1254x1254 2x2 sheets; runtime display is category-constrained. | K11: Cheerful stage-map icon; readable normal/event/shop/rest/treasure/elite/boss state.
A12: ☐ | B12: map_deco_frosty_pantry_ice_crate | C12: map/decorations/ | D12: Ice cream crate decoration for Stage 3 map. | E12: P2 | F12: 627x627 PNG source for nodes/icons/routes; backgrounds use portrait size | G12: Map node 32-56px; selected node/detail 64-96px; route card 96-180px | H12: State variants as needed | I12: icons/map-nodes/ | J12: Audit: Stage 6 route node/smoke testing pending. | Updated 2026-05-19: non-board visual source supports 627x627 PNG or 1254x1254 2x2 sheets; runtime display is category-constrained. | K12: Cheerful stage-map icon; readable normal/event/shop/rest/treasure/elite/boss state.
A13: ☐ | B13: map_deco_pillow_castle_blanket_flag | C13: map/decorations/ | D13: Blanket flag decoration for Stage 4 map. | E13: P2 | F13: 627x627 PNG source for nodes/icons/routes; backgrounds use portrait size | G13: Map node 32-56px; selected node/detail 64-96px; route card 96-180px | H13: State variants as needed | I13: icons/map-nodes/ | J13: Audit: Stage 6 route node/smoke testing pending. | Updated 2026-05-19: non-board visual source supports 627x627 PNG or 1254x1254 2x2 sheets; runtime display is category-constrained. | K13: Cheerful stage-map icon; readable normal/event/shop/rest/treasure/elite/boss state.
A14: ☐ | B14: map_deco_starfall_arcade_neon_sign | C14: map/decorations/ | D14: Neon sign decoration for Stage 5 map. | E14: P2 | F14: 627x627 PNG source for nodes/icons/routes; backgrounds use portrait size | G14: Map node 32-56px; selected node/detail 64-96px; route card 96-180px | H14: State variants as needed | I14: icons/map-nodes/ | J14: Audit: Stage 6 route node/smoke testing pending. | Updated 2026-05-19: non-board visual source supports 627x627 PNG or 1254x1254 2x2 sheets; runtime display is category-constrained. | K14: Cheerful stage-map icon; readable normal/event/shop/rest/treasure/elite/boss state.
A15: ☐ | B15: map_deco_bloxley_block_palace_royal_seal | C15: map/decorations/ | D15: Royal seal decoration for Stage 6 map. | E15: P2 | F15: 627x627 PNG source for nodes/icons/routes; backgrounds use portrait size | G15: Map node 32-56px; selected node/detail 64-96px; route card 96-180px | H15: State variants as needed | I15: icons/map-nodes/ | J15: Audit: Stage 6 route node/smoke testing pending. | Updated 2026-05-19: non-board visual source supports 627x627 PNG or 1254x1254 2x2 sheets; runtime display is category-constrained. | K15: Cheerful stage-map icon; readable normal/event/shop/rest/treasure/elite/boss state.

Sheet 14 - Heroes
A1: 14. Sprite Assets — Playable Heroes
A2: Tracking sheet generated from the uploaded markdown. Done? is unchecked by default.
A4: Done? | B4: Asset Key | C4: Suggested Folder | D4: Designer Description | E4: Priority | F4: Source / Export Size | G4: Runtime Render Size | H4: Exact Frames / Count | I4: Final Folder Structure (relative to public/assets) | J4: Audit / Release Note | K4: GDD Theme / Prompt Note
A5: ☐ | B5: spr_hero_milo_blockmancer_idle | C5: sprites/heroes/ | D5: Milo: Neutral battle idle; loopable and readable in top battle panel. Character direction: balanced starter Blockmancer, optimistic apprentice with lemonade-assistant charm. | E5: P0 | F5: 1254x1254 2x2 pose sheet (627x627 per frame); optional exact frames 627x627 | G5: Battle max 72-96px; hero select 128-180px; modal/unlock 160-220px; preserve aspect ratio | H5: Hero standard: idle 4, cast_spell 6, hit 3, victory 5, defeat_tired 4, portrait_icon 1 | I5: sprites/heroes/hero_milo_blockmancer/idle/ | J5: Audit: 8 heroes exist; Release 1 route coverage is 6 heroes. Critical heroes need final sprites. | Updated 2026-05-19: non-board visual source supports 627x627 PNG or 1254x1254 2x2 sheets; runtime display is category-constrained. | K5: Cute chibi festival adventurer, bright 32-bit style, clear top battle panel silhouette.
A6: ☐ | B6: spr_hero_milo_blockmancer_cast | C6: sprites/heroes/ | D6: Milo: Spell-casting pose with clear silhouette and hand/wand motion. Character direction: balanced starter Blockmancer, optimistic apprentice with lemonade-assistant charm. | E6: P0 | F6: 1254x1254 2x2 pose sheet (627x627 per frame); optional exact frames 627x627 | G6: Battle max 72-96px; hero select 128-180px; modal/unlock 160-220px; preserve aspect ratio | H6: Hero standard: idle 4, cast_spell 6, hit 3, victory 5, defeat_tired 4, portrait_icon 1 | I6: sprites/heroes/hero_milo_blockmancer/cast_spell/ | J6: Audit: 8 heroes exist; Release 1 route coverage is 6 heroes. Critical heroes need final sprites. | Updated 2026-05-19: non-board visual source supports 627x627 PNG or 1254x1254 2x2 sheets; runtime display is category-constrained. | K6: Cute chibi festival adventurer, bright 32-bit style, clear top battle panel silhouette.
A7: ☐ | B7: spr_hero_milo_blockmancer_attack | C7: sprites/heroes/ | D7: Milo: Quick attack pose for line-clear damage feedback. Character direction: balanced starter Blockmancer, optimistic apprentice with lemonade-assistant charm. | E7: P0 | F7: 1254x1254 2x2 pose sheet (627x627 per frame); optional exact frames 627x627 | G7: Battle max 72-96px; hero select 128-180px; modal/unlock 160-220px; preserve aspect ratio | H7: Hero standard: idle 4, cast_spell 6, hit 3, victory 5, defeat_tired 4, portrait_icon 1 | I7: sprites/heroes/hero_milo_blockmancer/attack_or_cast_spell/ | J7: Audit: 8 heroes exist; Release 1 route coverage is 6 heroes. Critical heroes need final sprites. | Updated 2026-05-19: non-board visual source supports 627x627 PNG or 1254x1254 2x2 sheets; runtime display is category-constrained. | K7: Cute chibi festival adventurer, bright 32-bit style, clear top battle panel silhouette.
A8: ☐ | B8: spr_hero_milo_blockmancer_hit | C8: sprites/heroes/ | D8: Milo: Short hurt/flinch pose, cute but readable. Character direction: balanced starter Blockmancer, optimistic apprentice with lemonade-assistant charm. | E8: P0 | F8: 1254x1254 2x2 pose sheet (627x627 per frame); optional exact frames 627x627 | G8: Battle max 72-96px; hero select 128-180px; modal/unlock 160-220px; preserve aspect ratio | H8: Hero standard: idle 4, cast_spell 6, hit 3, victory 5, defeat_tired 4, portrait_icon 1 | I8: sprites/heroes/hero_milo_blockmancer/hit/ | J8: Audit: 8 heroes exist; Release 1 route coverage is 6 heroes. Critical heroes need final sprites. | Updated 2026-05-19: non-board visual source supports 627x627 PNG or 1254x1254 2x2 sheets; runtime display is category-constrained. | K8: Cute chibi festival adventurer, bright 32-bit style, clear top battle panel silhouette.
A9: ☐ | B9: spr_hero_milo_blockmancer_victory | C9: sprites/heroes/ | D9: Milo: Celebration pose for room clear and hero select preview. Character direction: balanced starter Blockmancer, optimistic apprentice with lemonade-assistant charm. | E9: P0 | F9: 1254x1254 2x2 pose sheet (627x627 per frame); optional exact frames 627x627 | G9: Battle max 72-96px; hero select 128-180px; modal/unlock 160-220px; preserve aspect ratio | H9: Hero standard: idle 4, cast_spell 6, hit 3, victory 5, defeat_tired 4, portrait_icon 1 | I9: sprites/heroes/hero_milo_blockmancer/victory/ | J9: Audit: 8 heroes exist; Release 1 route coverage is 6 heroes. Critical heroes need final sprites. | Updated 2026-05-19: non-board visual source supports 627x627 PNG or 1254x1254 2x2 sheets; runtime display is category-constrained. | K9: Cute chibi festival adventurer, bright 32-bit style, clear top battle panel silhouette.
A10: ☐ | B10: spr_hero_milo_blockmancer_defeat | C10: sprites/heroes/ | D10: Milo: Soft defeat/tired pose without grim tone. Character direction: balanced starter Blockmancer, optimistic apprentice with lemonade-assistant charm. | E10: P0 | F10: 1254x1254 2x2 pose sheet (627x627 per frame); optional exact frames 627x627 | G10: Battle max 72-96px; hero select 128-180px; modal/unlock 160-220px; preserve aspect ratio | H10: Hero standard: idle 4, cast_spell 6, hit 3, victory 5, defeat_tired 4, portrait_icon 1 | I10: sprites/heroes/hero_milo_blockmancer/defeat_tired/ | J10: Audit: 8 heroes exist; Release 1 route coverage is 6 heroes. Critical heroes need final sprites. | Updated 2026-05-19: non-board visual source supports 627x627 PNG or 1254x1254 2x2 sheets; runtime display is category-constrained. | K10: Cute chibi festival adventurer, bright 32-bit style, clear top battle panel silhouette.
A11: ☐ | B11: spr_hero_milo_blockmancer_portrait | C11: sprites/heroes/ | D11: Milo: Large dialogue/hero-select portrait with expressive face. Character direction: balanced starter Blockmancer, optimistic apprentice with lemonade-assistant charm. | E11: P0 | F11: 1254x1254 2x2 pose sheet (627x627 per frame); optional exact frames 627x627 | G11: Battle max 72-96px; hero select 128-180px; modal/unlock 160-220px; preserve aspect ratio | H11: Hero standard: idle 4, cast_spell 6, hit 3, victory 5, defeat_tired 4, portrait_icon 1 | I11: sprites/heroes/hero_milo_blockmancer/idle/ | J11: Audit: 8 heroes exist; Release 1 route coverage is 6 heroes. Critical heroes need final sprites. | Updated 2026-05-19: non-board visual source supports 627x627 PNG or 1254x1254 2x2 sheets; runtime display is category-constrained. | K11: Cute chibi festival adventurer, bright 32-bit style, clear top battle panel silhouette.
A12: ☐ | B12: spr_hero_milo_blockmancer_silhouette_locked | C12: sprites/heroes/ | D12: Milo: Locked hero silhouette; recognizable but not fully revealed. Character direction: balanced starter Blockmancer, optimistic apprentice with lemonade-assistant charm. | E12: P0 | F12: 1254x1254 2x2 pose sheet (627x627 per frame); optional exact frames 627x627 | G12: Battle max 72-96px; hero select 128-180px; modal/unlock 160-220px; preserve aspect ratio | H12: Hero standard: idle 4, cast_spell 6, hit 3, victory 5, defeat_tired 4, portrait_icon 1 | I12: sprites/heroes/hero_milo_blockmancer_silhouette_locked/idle/ | J12: Audit: 8 heroes exist; Release 1 route coverage is 6 heroes. Critical heroes need final sprites. | Updated 2026-05-19: non-board visual source supports 627x627 PNG or 1254x1254 2x2 sheets; runtime display is category-constrained. | K12: Cute chibi festival adventurer, bright 32-bit style, clear top battle panel silhouette.
A13: ☐ | B13: ico_hero_milo_blockmancer | C13: icons/heroes/ | D13: Milo small icon for hero select, save slot, HUD, and unlock UI. | E13: P0 | F13: 1254x1254 2x2 pose sheet (627x627 per frame); optional exact frames 627x627 | G13: Battle max 72-96px; hero select 128-180px; modal/unlock 160-220px; preserve aspect ratio | H13: Static 1 PNG unless animation standard says otherwise | I13: icons/heroes/ | J13: Audit: use manifest key and placeholder-safe fallback; verify final art before release. | Updated 2026-05-19: non-board visual source supports 627x627 PNG or 1254x1254 2x2 sheets; runtime display is category-constrained. | K13: Cheerful festival / cute chaos tone; transparent pixel art; no text or watermark.
A14: ☐ | B14: spr_hero_pippa_pyromancer_idle | C14: sprites/heroes/ | D14: Pippa: Neutral battle idle; loopable and readable in top battle panel. Character direction: festival baker pyromancer, energetic and cupcake-protective. | E14: P1 | F14: 1254x1254 2x2 pose sheet (627x627 per frame); optional exact frames 627x627 | G14: Battle max 72-96px; hero select 128-180px; modal/unlock 160-220px; preserve aspect ratio | H14: Hero standard: idle 4, cast_spell 6, hit 3, victory 5, defeat_tired 4, portrait_icon 1 | I14: sprites/heroes/hero_pippa_pyromancer/idle/ | J14: Audit: 8 heroes exist; Release 1 route coverage is 6 heroes. Critical heroes need final sprites. | Updated 2026-05-19: non-board visual source supports 627x627 PNG or 1254x1254 2x2 sheets; runtime display is category-constrained. | K14: Cute chibi festival adventurer, bright 32-bit style, clear top battle panel silhouette.
A15: ☐ | B15: spr_hero_pippa_pyromancer_cast | C15: sprites/heroes/ | D15: Pippa: Spell-casting pose with clear silhouette and hand/wand motion. Character direction: festival baker pyromancer, energetic and cupcake-protective. | E15: P1 | F15: 1254x1254 2x2 pose sheet (627x627 per frame); optional exact frames 627x627 | G15: Battle max 72-96px; hero select 128-180px; modal/unlock 160-220px; preserve aspect ratio | H15: Hero standard: idle 4, cast_spell 6, hit 3, victory 5, defeat_tired 4, portrait_icon 1 | I15: sprites/heroes/hero_pippa_pyromancer/cast_spell/ | J15: Audit: 8 heroes exist; Release 1 route coverage is 6 heroes. Critical heroes need final sprites. | Updated 2026-05-19: non-board visual source supports 627x627 PNG or 1254x1254 2x2 sheets; runtime display is category-constrained. | K15: Cute chibi festival adventurer, bright 32-bit style, clear top battle panel silhouette.
... A58: ☐ | B58: ico_hero_lumi_star_witch | C58: icons/heroes/ | D58: Lumi small icon for hero select, save slot, HUD, and unlock UI. | E58: P1 | F58: 1254x1254 2x2 pose sheet (627x627 per frame); optional exact frames 627x627 | G58: Battle max 72-96px; hero select 128-180px; modal/unlock 160-220px; preserve aspect ratio | H58: Static 1 PNG unless animation standard says otherwise | I58: icons/heroes/ | J58: Audit: use manifest key and placeholder-safe fallback; verify final art before release. | Updated 2026-05-19: non-board visual source supports 627x627 PNG or 1254x1254 2x2 sheets; runtime display is category-constrained. | K58: Cheerful festival / cute chaos tone; transparent pixel art; no text or watermark.

Sheet 15 - Monsters
A1: 15. Sprite Assets — Regular Monsters
A2: Tracking sheet generated from the uploaded markdown. Done? is unchecked by default.
A4: Done? | B4: Asset Key | C4: Suggested Folder | D4: Designer Description | E4: Priority | F4: Source / Export Size | G4: Runtime Render Size | H4: Exact Frames / Count | I4: Final Folder Structure (relative to public/assets) | J4: Audit / Release Note | K4: GDD Theme / Prompt Note
A5: ☐ | B5: spr_mon_cupcake_slime_idle | C5: sprites/monsters/ | D5: Cupcake Slime: Loopable battle idle, cute and readable in small top battle panel. Direction: slime wearing whipped cream; basic enemy that drops sprinkles. | E5: P0 | F5: 1254x1254 2x2 pose sheet (627x627 per frame); optional exact frames 627x627 | G5: Regular max 96px; elite/large max 112px; bottom-center origin; preserve aspect ratio | H5: idle: 4 exact PNG frames; monster total standard 20 PNGs | I5: sprites/monsters/mon_cupcake_slime/idle/ | J5: Audit: monster content exists, but critical Release 1 monsters need final sprites and smoke verification. | Updated 2026-05-19: non-board visual source supports 627x627 PNG or 1254x1254 2x2 sheets; runtime display is category-constrained. | K5: Cute-chaotic festival monster; readable in top battle panel; no gore/horror.
A6: ☐ | B6: spr_mon_cupcake_slime_attack | C6: sprites/monsters/ | D6: Cupcake Slime: Attack animation pose matching its behavior. Direction: slime wearing whipped cream; basic enemy that drops sprinkles. | E6: P0 | F6: 1254x1254 2x2 pose sheet (627x627 per frame); optional exact frames 627x627 | G6: Regular max 96px; elite/large max 112px; bottom-center origin; preserve aspect ratio | H6: attack: 6 exact PNG frames; monster total standard 20 PNGs | I6: sprites/monsters/mon_cupcake_slime/attack/ | J6: Audit: monster content exists, but critical Release 1 monsters need final sprites and smoke verification. | Updated 2026-05-19: non-board visual source supports 627x627 PNG or 1254x1254 2x2 sheets; runtime display is category-constrained. | K6: Cute-chaotic festival monster; readable in top battle panel; no gore/horror.
A7: ☐ | B7: spr_mon_cupcake_slime_hit | C7: sprites/monsters/ | D7: Cupcake Slime: Short squash/flinch response when damaged. Direction: slime wearing whipped cream; basic enemy that drops sprinkles. | E7: P0 | F7: 1254x1254 2x2 pose sheet (627x627 per frame); optional exact frames 627x627 | G7: Regular max 96px; elite/large max 112px; bottom-center origin; preserve aspect ratio | H7: hit: 3 exact PNG frames; monster total standard 20 PNGs | I7: sprites/monsters/mon_cupcake_slime/hit/ | J7: Audit: monster content exists, but critical Release 1 monsters need final sprites and smoke verification. | Updated 2026-05-19: non-board visual source supports 627x627 PNG or 1254x1254 2x2 sheets; runtime display is category-constrained. | K7: Cute-chaotic festival monster; readable in top battle panel; no gore/horror.
A8: ☐ | B8: spr_mon_cupcake_slime_defeat | C8: sprites/monsters/ | D8: Cupcake Slime: Playful poof or calm-down defeat, no gore. Direction: slime wearing whipped cream; basic enemy that drops sprinkles. | E8: P0 | F8: 1254x1254 2x2 pose sheet (627x627 per frame); optional exact frames 627x627 | G8: Regular max 96px; elite/large max 112px; bottom-center origin; preserve aspect ratio | H8: defeat: 6 exact PNG frames; monster total standard 20 PNGs | I8: sprites/monsters/mon_cupcake_slime/defeat/ | J8: Audit: monster content exists, but critical Release 1 monsters need final sprites and smoke verification. | Updated 2026-05-19: non-board visual source supports 627x627 PNG or 1254x1254 2x2 sheets; runtime display is category-constrained. | K8: Cute-chaotic festival monster; readable in top battle panel; no gore/horror.
A9: ☐ | B9: ico_mon_cupcake_slime | C9: icons/monsters/ | D9: Cupcake Slime compact icon for bestiary, intent UI, debug spawn, or friendship screen. | E9: P1 | F9: 1254x1254 2x2 pose sheet (627x627 per frame); optional exact frames 627x627 | G9: Regular max 96px; elite/large max 112px; bottom-center origin; preserve aspect ratio | H9: icon: 1 PNG; monster total standard 20 PNGs | I9: icons/monsters/ | J9: Audit: monster content exists, but critical Release 1 monsters need final sprites and smoke verification. | Updated 2026-05-19: non-board visual source supports 627x627 PNG or 1254x1254 2x2 sheets; runtime display is category-constrained. | K9: Cute-chaotic festival monster; readable in top battle panel; no gore/horror.
A10: ☐ | B10: spr_mon_sugar_bat_idle | C10: sprites/monsters/ | D10: Sugar Bat: Loopable battle idle, cute and readable in small top battle panel. Direction: small candy-rushed bat; disrupts next preview. | E10: P0 | F10: 1254x1254 2x2 pose sheet (627x627 per frame); optional exact frames 627x627 | G10: Regular max 96px; elite/large max 112px; bottom-center origin; preserve aspect ratio | H10: idle: 4 exact PNG frames; monster total standard 20 PNGs | I10: sprites/monsters/mon_sugar_bat/idle/ | J10: Audit: monster content exists, but critical Release 1 monsters need final sprites and smoke verification. | Updated 2026-05-19: non-board visual source supports 627x627 PNG or 1254x1254 2x2 sheets; runtime display is category-constrained. | K10: Cute-chaotic festival monster; readable in top battle panel; no gore/horror.
A11: ☐ | B11: spr_mon_sugar_bat_attack | C11: sprites/monsters/ | D11: Sugar Bat: Attack animation pose matching its behavior. Direction: small candy-rushed bat; disrupts next preview. | E11: P0 | F11: 1254x1254 2x2 pose sheet (627x627 per frame); optional exact frames 627x627 | G11: Regular max 96px; elite/large max 112px; bottom-center origin; preserve aspect ratio | H11: attack: 6 exact PNG frames; monster total standard 20 PNGs | I11: sprites/monsters/mon_sugar_bat/attack/ | J11: Audit: monster content exists, but critical Release 1 monsters need final sprites and smoke verification. | Updated 2026-05-19: non-board visual source supports 627x627 PNG or 1254x1254 2x2 sheets; runtime display is category-constrained. | K11: Cute-chaotic festival monster; readable in top battle panel; no gore/horror.
A12: ☐ | B12: spr_mon_sugar_bat_hit | C12: sprites/monsters/ | D12: Sugar Bat: Short squash/flinch response when damaged. Direction: small candy-rushed bat; disrupts next preview. | E12: P0 | F12: 1254x1254 2x2 pose sheet (627x627 per frame); optional exact frames 627x627 | G12: Regular max 96px; elite/large max 112px; bottom-center origin; preserve aspect ratio | H12: hit: 3 exact PNG frames; monster total standard 20 PNGs | I12: sprites/monsters/mon_sugar_bat/hit/ | J12: Audit: monster content exists, but critical Release 1 monsters need final sprites and smoke verification. | Updated 2026-05-19: non-board visual source supports 627x627 PNG or 1254x1254 2x2 sheets; runtime display is category-constrained. | K12: Cute-chaotic festival monster; readable in top battle panel; no gore/horror.
A13: ☐ | B13: spr_mon_sugar_bat_defeat | C13: sprites/monsters/ | D13: Sugar Bat: Playful poof or calm-down defeat, no gore. Direction: small candy-rushed bat; disrupts next preview. | E13: P0 | F13: 1254x1254 2x2 pose sheet (627x627 per frame); optional exact frames 627x627 | G13: Regular max 96px; elite/large max 112px; bottom-center origin; preserve aspect ratio | H13: defeat: 6 exact PNG frames; monster total standard 20 PNGs | I13: sprites/monsters/mon_sugar_bat/defeat/ | J13: Audit: monster content exists, but critical Release 1 monsters need final sprites and smoke verification. | Updated 2026-05-19: non-board visual source supports 627x627 PNG or 1254x1254 2x2 sheets; runtime display is category-constrained. | K13: Cute-chaotic festival monster; readable in top battle panel; no gore/horror.
A14: ☐ | B14: ico_mon_sugar_bat | C14: icons/monsters/ | D14: Sugar Bat compact icon for bestiary, intent UI, debug spawn, or friendship screen. | E14: P1 | F14: 1254x1254 2x2 pose sheet (627x627 per frame); optional exact frames 627x627 | G14: Regular max 96px; elite/large max 112px; bottom-center origin; preserve aspect ratio | H14: icon: 1 PNG; monster total standard 20 PNGs | I14: icons/monsters/ | J14: Audit: monster content exists, but critical Release 1 monsters need final sprites and smoke verification. | Updated 2026-05-19: non-board visual source supports 627x627 PNG or 1254x1254 2x2 sheets; runtime display is category-constrained. | K14: Cute-chaotic festival monster; readable in top battle panel; no gore/horror.
A15: ☐ | B15: spr_mon_crumb_goblin_idle | C15: sprites/monsters/ | D15: Crumb Goblin: Loopable battle idle, cute and readable in small top battle panel. Direction: tiny cookie crumb goblin; throws crumb junk. | E15: P0 | F15: 1254x1254 2x2 pose sheet (627x627 per frame); optional exact frames 627x627 | G15: Regular max 96px; elite/large max 112px; bottom-center origin; preserve aspect ratio | H15: idle: 4 exact PNG frames; monster total standard 20 PNGs | I15: sprites/monsters/mon_crumb_goblin/idle/ | J15: Audit: monster content exists, but critical Release 1 monsters need final sprites and smoke verification. | Updated 2026-05-19: non-board visual source supports 627x627 PNG or 1254x1254 2x2 sheets; runtime display is category-constrained. | K15: Cute-chaotic festival monster; readable in top battle panel; no gore/horror.
... A184: ☐ | B184: ico_mon_banner_bug | C184: icons/monsters/ | D184: Banner Bug compact icon for bestiary, intent UI, debug spawn, or friendship screen. | E184: P1 | F184: 1254x1254 2x2 pose sheet (627x627 per frame); optional exact frames 627x627 | G184: Regular max 96px; elite/large max 112px; bottom-center origin; preserve aspect ratio | H184: icon: 1 PNG; monster total standard 20 PNGs | I184: icons/monsters/ | J184: Audit: monster content exists, but critical Release 1 monsters need final sprites and smoke verification. | Updated 2026-05-19: non-board visual source supports 627x627 PNG or 1254x1254 2x2 sheets; runtime display is category-constrained. | K184: Cute-chaotic festival monster; readable in top battle panel; no gore/horror.

Sheet 16 - Bosses
A1: 16. Sprite Assets — Bosses
A2: Tracking sheet generated from the uploaded markdown. Done? is unchecked by default.
A4: Done? | B4: Asset Key | C4: Suggested Folder | D4: Designer Description | E4: Priority | F4: Source / Export Size | G4: Runtime Render Size | H4: Exact Frames / Count | I4: Final Folder Structure (relative to public/assets) | J4: Audit / Release Note | K4: GDD Theme / Prompt Note
A5: ☐ | B5: spr_boss_cupcake_slime_king_idle | C5: sprites/bosses/ | D5: Cupcake Slime King: Large boss idle loop with strong silhouette and stage personality. Arena/character direction: sticky candy sewer boss arena with frosting puddles and giant cupcake slime throne. | E5: P0 | F5: 1254x1254 2x2 pose sheet (627x627 per frame); optional extended sheet | G5: Battle max 144px; intro/rule card 180-220px; bottom-center origin; preserve aspect ratio | H5: Boss standard: idle 6, attack 8, hit 4, phase_change 8, special_attack 8, defeat 10, portrait_icon 1 | I5: sprites/bosses/boss_cupcake_slime_king/idle/ | J5: Audit: boss mechanics and boss rule visuals need visible verification; import final frames. | Updated 2026-05-19: non-board visual source supports 627x627 PNG or 1254x1254 2x2 sheets; runtime display is category-constrained. | K5: Readable funny boss identity with stage mechanics: sticky, gadget, frost, sleepy, arcade, or royal.
A6: ☐ | B6: spr_boss_cupcake_slime_king_attack | C6: sprites/bosses/ | D6: Cupcake Slime King: Main attack pose for basic boss action. Arena/character direction: sticky candy sewer boss arena with frosting puddles and giant cupcake slime throne. | E6: P0 | F6: 1254x1254 2x2 pose sheet (627x627 per frame); optional extended sheet | G6: Battle max 144px; intro/rule card 180-220px; bottom-center origin; preserve aspect ratio | H6: Boss standard: idle 6, attack 8, hit 4, phase_change 8, special_attack 8, defeat 10, portrait_icon 1 | I6: sprites/bosses/boss_cupcake_slime_king/attack/ | J6: Audit: boss mechanics and boss rule visuals need visible verification; import final frames. | Updated 2026-05-19: non-board visual source supports 627x627 PNG or 1254x1254 2x2 sheets; runtime display is category-constrained. | K6: Readable funny boss identity with stage mechanics: sticky, gadget, frost, sleepy, arcade, or royal.
A7: ☐ | B7: spr_boss_cupcake_slime_king_special | C7: sprites/bosses/ | D7: Cupcake Slime King: Unique mechanic pose for boss gimmick. Arena/character direction: sticky candy sewer boss arena with frosting puddles and giant cupcake slime throne. | E7: P0 | F7: 1254x1254 2x2 pose sheet (627x627 per frame); optional extended sheet | G7: Battle max 144px; intro/rule card 180-220px; bottom-center origin; preserve aspect ratio | H7: Boss standard: idle 6, attack 8, hit 4, phase_change 8, special_attack 8, defeat 10, portrait_icon 1 | I7: sprites/bosses/boss_cupcake_slime_king/special_attack/ | J7: Audit: boss mechanics and boss rule visuals need visible verification; import final frames. | Updated 2026-05-19: non-board visual source supports 627x627 PNG or 1254x1254 2x2 sheets; runtime display is category-constrained. | K7: Readable funny boss identity with stage mechanics: sticky, gadget, frost, sleepy, arcade, or royal.
A8: ☐ | B8: spr_boss_cupcake_slime_king_phase_2 | C8: sprites/bosses/ | D8: Cupcake Slime King: Altered phase-two visual state, readable but not completely new boss. Arena/character direction: sticky candy sewer boss arena with frosting puddles and giant cupcake slime throne. | E8: P0 | F8: 1254x1254 2x2 pose sheet (627x627 per frame); optional extended sheet | G8: Battle max 144px; intro/rule card 180-220px; bottom-center origin; preserve aspect ratio | H8: Boss standard: idle 6, attack 8, hit 4, phase_change 8, special_attack 8, defeat 10, portrait_icon 1 | I8: sprites/bosses/boss_cupcake_slime_king/phase_change/ | J8: Audit: boss mechanics and boss rule visuals need visible verification; import final frames. | Updated 2026-05-19: non-board visual source supports 627x627 PNG or 1254x1254 2x2 sheets; runtime display is category-constrained. | K8: Readable funny boss identity with stage mechanics: sticky, gadget, frost, sleepy, arcade, or royal.
A9: ☐ | B9: spr_boss_cupcake_slime_king_hit | C9: sprites/bosses/ | D9: Cupcake Slime King: Heavy hit reaction without scary violence. Arena/character direction: sticky candy sewer boss arena with frosting puddles and giant cupcake slime throne. | E9: P0 | F9: 1254x1254 2x2 pose sheet (627x627 per frame); optional extended sheet | G9: Battle max 144px; intro/rule card 180-220px; bottom-center origin; preserve aspect ratio | H9: Boss standard: idle 6, attack 8, hit 4, phase_change 8, special_attack 8, defeat 10, portrait_icon 1 | I9: sprites/bosses/boss_cupcake_slime_king/hit/ | J9: Audit: boss mechanics and boss rule visuals need visible verification; import final frames. | Updated 2026-05-19: non-board visual source supports 627x627 PNG or 1254x1254 2x2 sheets; runtime display is category-constrained. | K9: Readable funny boss identity with stage mechanics: sticky, gadget, frost, sleepy, arcade, or royal.
A10: ☐ | B10: spr_boss_cupcake_slime_king_defeat | C10: sprites/bosses/ | D10: Cupcake Slime King: Big playful defeat/calm-down animation. Arena/character direction: sticky candy sewer boss arena with frosting puddles and giant cupcake slime throne. | E10: P0 | F10: 1254x1254 2x2 pose sheet (627x627 per frame); optional extended sheet | G10: Battle max 144px; intro/rule card 180-220px; bottom-center origin; preserve aspect ratio | H10: Boss standard: idle 6, attack 8, hit 4, phase_change 8, special_attack 8, defeat 10, portrait_icon 1 | I10: sprites/bosses/boss_cupcake_slime_king/defeat/ | J10: Audit: boss mechanics and boss rule visuals need visible verification; import final frames. | Updated 2026-05-19: non-board visual source supports 627x627 PNG or 1254x1254 2x2 sheets; runtime display is category-constrained. | K10: Readable funny boss identity with stage mechanics: sticky, gadget, frost, sleepy, arcade, or royal.
A11: ☐ | B11: spr_boss_cupcake_slime_king_intro_portrait | C11: sprites/bosses/ | D11: Cupcake Slime King: Large intro/rule-card portrait with expressive personality. Arena/character direction: sticky candy sewer boss arena with frosting puddles and giant cupcake slime throne. | E11: P0 | F11: 1254x1254 2x2 pose sheet (627x627 per frame); optional extended sheet | G11: Battle max 144px; intro/rule card 180-220px; bottom-center origin; preserve aspect ratio | H11: Boss standard: idle 6, attack 8, hit 4, phase_change 8, special_attack 8, defeat 10, portrait_icon 1 | I11: sprites/bosses/boss_cupcake_slime_king_intro/idle/ | J11: Audit: boss mechanics and boss rule visuals need visible verification; import final frames. | Updated 2026-05-19: non-board visual source supports 627x627 PNG or 1254x1254 2x2 sheets; runtime display is category-constrained. | K11: Readable funny boss identity with stage mechanics: sticky, gadget, frost, sleepy, arcade, or royal.
A12: ☐ | B12: ico_boss_cupcake_slime_king | C12: icons/bosses/ | D12: Cupcake Slime King compact icon for map boss node, boss rule card, and debug tools. | E12: P1 | F12: 1254x1254 2x2 pose sheet (627x627 per frame); optional extended sheet | G12: Battle max 144px; intro/rule card 180-220px; bottom-center origin; preserve aspect ratio | H12: Boss standard: idle 6, attack 8, hit 4, phase_change 8, special_attack 8, defeat 10, portrait_icon 1 | I12: icons/bosses/ | J12: Audit: boss mechanics and boss rule visuals need visible verification; import final frames. | Updated 2026-05-19: non-board visual source supports 627x627 PNG or 1254x1254 2x2 sheets; runtime display is category-constrained. | K12: Readable funny boss identity with stage mechanics: sticky, gadget, frost, sleepy, arcade, or royal.
A13: ☐ | B13: ico_boss_rule_boss_cupcake_slime_king | C13: icons/boss-rules/ | D13: Cupcake Slime King rule-card icon representing the boss gimmick clearly. | E13: P1 | F13: 1254x1254 2x2 pose sheet (627x627 per frame); optional extended sheet | G13: Battle max 144px; intro/rule card 180-220px; bottom-center origin; preserve aspect ratio | H13: Boss standard: idle 6, attack 8, hit 4, phase_change 8, special_attack 8, defeat 10, portrait_icon 1 | I13: icons/bosses/ | J13: Audit: boss mechanics and boss rule visuals need visible verification; import final frames. | Updated 2026-05-19: non-board visual source supports 627x627 PNG or 1254x1254 2x2 sheets; runtime display is category-constrained. | K13: Readable funny boss identity with stage mechanics: sticky, gadget, frost, sleepy, arcade, or royal.
A14: ☐ | B14: spr_boss_prototype_no_7_idle | C14: sprites/bosses/ | D14: Prototype No. 7: Large boss idle loop with strong silhouette and stage personality. Arena/character direction: malfunctioning workshop arena with safe-looking machines and bomb props. | E14: P1 | F14: 1254x1254 2x2 pose sheet (627x627 per frame); optional extended sheet | G14: Battle max 144px; intro/rule card 180-220px; bottom-center origin; preserve aspect ratio | H14: Boss standard: idle 6, attack 8, hit 4, phase_change 8, special_attack 8, defeat 10, portrait_icon 1 | I14: sprites/bosses/boss_prototype_no_7/idle/ | J14: Audit: boss mechanics and boss rule visuals need visible verification; import final frames. | Updated 2026-05-19: non-board visual source supports 627x627 PNG or 1254x1254 2x2 sheets; runtime display is category-constrained. | K14: Readable funny boss identity with stage mechanics: sticky, gadget, frost, sleepy, arcade, or royal.
A15: ☐ | B15: spr_boss_prototype_no_7_attack | C15: sprites/bosses/ | D15: Prototype No. 7: Main attack pose for basic boss action. Arena/character direction: malfunctioning workshop arena with safe-looking machines and bomb props. | E15: P1 | F15: 1254x1254 2x2 pose sheet (627x627 per frame); optional extended sheet | G15: Battle max 144px; intro/rule card 180-220px; bottom-center origin; preserve aspect ratio | H15: Boss standard: idle 6, attack 8, hit 4, phase_change 8, special_attack 8, defeat 10, portrait_icon 1 | I15: sprites/bosses/boss_prototype_no_7/attack/ | J15: Audit: boss mechanics and boss rule visuals need visible verification; import final frames. | Updated 2026-05-19: non-board visual source supports 627x627 PNG or 1254x1254 2x2 sheets; runtime display is category-constrained. | K15: Readable funny boss identity with stage mechanics: sticky, gadget, frost, sleepy, arcade, or royal.
... A58: ☐ | B58: ico_boss_rule_boss_king_bloxley | C58: icons/boss-rules/ | D58: King Bloxley rule-card icon representing the boss gimmick clearly. | E58: P1 | F58: 1254x1254 2x2 pose sheet (627x627 per frame); optional extended sheet | G58: Battle max 144px; intro/rule card 180-220px; bottom-center origin; preserve aspect ratio | H58: Boss standard: idle 6, attack 8, hit 4, phase_change 8, special_attack 8, defeat 10, portrait_icon 1 | I58: icons/bosses/ | J58: Audit: boss mechanics and boss rule visuals need visible verification; import final frames. | Updated 2026-05-19: non-board visual source supports 627x627 PNG or 1254x1254 2x2 sheets; runtime display is category-constrained. | K58: Readable funny boss identity with stage mechanics: sticky, gadget, frost, sleepy, arcade, or royal.

Sheet 17 - NPCs
A1: 17. Sprite Assets — NPCs
A2: Tracking sheet generated from the uploaded markdown. Done? is unchecked by default.
A4: Done? | B4: Asset Key | C4: Suggested Folder | D4: Designer Description | E4: Priority | F4: Source / Export Size | G4: Runtime Render Size | H4: Exact Frames / Count | I4: Final Folder Structure (relative to public/assets) | J4: Audit / Release Note | K4: GDD Theme / Prompt Note
A5: ☐ | B5: spr_npc_professor_poplin_idle | C5: sprites/npcs/ | D5: Professor Poplin small idle sprite. Direction: inventor/tutorial wizard; excited, absent-minded, harmless. | E5: P1 | F5: 627x627 PNG portrait source | G5: Dialogue 96-128px; story/unlock modal 128-220px; preserve aspect ratio | H5: Static portrait/icon unless animation is defined | I5: sprites/npcs/ | J5: Use placeholders only for non-critical NPCs; story route UI needs final portraits. | Updated 2026-05-19: non-board visual source supports 627x627 PNG or 1254x1254 2x2 sheets; runtime display is category-constrained. | K5: Friendly Brixonia festival NPC; expressive, bright, readable.
A6: ☐ | B6: spr_npc_professor_poplin_portrait | C6: sprites/npcs/ | D6: Professor Poplin dialogue portrait with strong expression and readable face. | E6: P1 | F6: 627x627 PNG portrait source | G6: Dialogue 96-128px; story/unlock modal 128-220px; preserve aspect ratio | H6: Static portrait/icon unless animation is defined | I6: sprites/npcs/ | J6: Use placeholders only for non-critical NPCs; story route UI needs final portraits. | Updated 2026-05-19: non-board visual source supports 627x627 PNG or 1254x1254 2x2 sheets; runtime display is category-constrained. | K6: Friendly Brixonia festival NPC; expressive, bright, readable.
A7: ☐ | B7: ico_npc_professor_poplin | C7: icons/npcs/ | D7: Professor Poplin compact icon for dialogue headers, map/shop/event labels. | E7: P2 | F7: 627x627 PNG portrait source | G7: Dialogue 96-128px; story/unlock modal 128-220px; preserve aspect ratio | H7: Static portrait/icon unless animation is defined | I7: sprites/npcs/ | J7: Use placeholders only for non-critical NPCs; story route UI needs final portraits. | Updated 2026-05-19: non-board visual source supports 627x627 PNG or 1254x1254 2x2 sheets; runtime display is category-constrained. | K7: Friendly Brixonia festival NPC; expressive, bright, readable.
A8: ☐ | B8: spr_npc_marnie_merchant_idle | C8: sprites/npcs/ | D8: Marnie the Merchant small idle sprite. Direction: general shop NPC; warm, practical, festival-stall energy. | E8: P1 | F8: 627x627 PNG portrait source | G8: Dialogue 96-128px; story/unlock modal 128-220px; preserve aspect ratio | H8: Static portrait/icon unless animation is defined | I8: sprites/npcs/ | J8: Use placeholders only for non-critical NPCs; story route UI needs final portraits. | Updated 2026-05-19: non-board visual source supports 627x627 PNG or 1254x1254 2x2 sheets; runtime display is category-constrained. | K8: Friendly Brixonia festival NPC; expressive, bright, readable.
A9: ☐ | B9: spr_npc_marnie_merchant_portrait | C9: sprites/npcs/ | D9: Marnie the Merchant dialogue portrait with strong expression and readable face. | E9: P1 | F9: 627x627 PNG portrait source | G9: Dialogue 96-128px; story/unlock modal 128-220px; preserve aspect ratio | H9: Static portrait/icon unless animation is defined | I9: sprites/npcs/ | J9: Use placeholders only for non-critical NPCs; story route UI needs final portraits. | Updated 2026-05-19: non-board visual source supports 627x627 PNG or 1254x1254 2x2 sheets; runtime display is category-constrained. | K9: Friendly Brixonia festival NPC; expressive, bright, readable.
A10: ☐ | B10: ico_npc_marnie_merchant | C10: icons/npcs/ | D10: Marnie the Merchant compact icon for dialogue headers, map/shop/event labels. | E10: P2 | F10: 627x627 PNG portrait source | G10: Dialogue 96-128px; story/unlock modal 128-220px; preserve aspect ratio | H10: Static portrait/icon unless animation is defined | I10: sprites/npcs/ | J10: Use placeholders only for non-critical NPCs; story route UI needs final portraits. | Updated 2026-05-19: non-board visual source supports 627x627 PNG or 1254x1254 2x2 sheets; runtime display is category-constrained. | K10: Friendly Brixonia festival NPC; expressive, bright, readable.
A11: ☐ | B11: spr_npc_ticket_imp_idle | C11: sprites/npcs/ | D11: Ticket Imp small idle sprite. Direction: arcade/event NPC; mischievous but friendly. | E11: P1 | F11: 627x627 PNG portrait source | G11: Dialogue 96-128px; story/unlock modal 128-220px; preserve aspect ratio | H11: Static portrait/icon unless animation is defined | I11: sprites/npcs/ | J11: Use placeholders only for non-critical NPCs; story route UI needs final portraits. | Updated 2026-05-19: non-board visual source supports 627x627 PNG or 1254x1254 2x2 sheets; runtime display is category-constrained. | K11: Friendly Brixonia festival NPC; expressive, bright, readable.
A12: ☐ | B12: spr_npc_ticket_imp_portrait | C12: sprites/npcs/ | D12: Ticket Imp dialogue portrait with strong expression and readable face. | E12: P1 | F12: 627x627 PNG portrait source | G12: Dialogue 96-128px; story/unlock modal 128-220px; preserve aspect ratio | H12: Static portrait/icon unless animation is defined | I12: sprites/npcs/ | J12: Use placeholders only for non-critical NPCs; story route UI needs final portraits. | Updated 2026-05-19: non-board visual source supports 627x627 PNG or 1254x1254 2x2 sheets; runtime display is category-constrained. | K12: Friendly Brixonia festival NPC; expressive, bright, readable.
A13: ☐ | B13: ico_npc_ticket_imp | C13: icons/npcs/ | D13: Ticket Imp compact icon for dialogue headers, map/shop/event labels. | E13: P2 | F13: 627x627 PNG portrait source | G13: Dialogue 96-128px; story/unlock modal 128-220px; preserve aspect ratio | H13: Static portrait/icon unless animation is defined | I13: sprites/npcs/ | J13: Use placeholders only for non-critical NPCs; story route UI needs final portraits. | Updated 2026-05-19: non-board visual source supports 627x627 PNG or 1254x1254 2x2 sheets; runtime display is category-constrained. | K13: Friendly Brixonia festival NPC; expressive, bright, readable.
A14: ☐ | B14: spr_npc_bloop_idle | C14: sprites/npcs/ | D14: Bloop small idle sprite. Direction: friendly slime NPC; simple expressive blob. | E14: P1 | F14: 627x627 PNG portrait source | G14: Dialogue 96-128px; story/unlock modal 128-220px; preserve aspect ratio | H14: Static portrait/icon unless animation is defined | I14: sprites/npcs/ | J14: Use placeholders only for non-critical NPCs; story route UI needs final portraits. | Updated 2026-05-19: non-board visual source supports 627x627 PNG or 1254x1254 2x2 sheets; runtime display is category-constrained. | K14: Friendly Brixonia festival NPC; expressive, bright, readable.
A15: ☐ | B15: spr_npc_bloop_portrait | C15: sprites/npcs/ | D15: Bloop dialogue portrait with strong expression and readable face. | E15: P1 | F15: 627x627 PNG portrait source | G15: Dialogue 96-128px; story/unlock modal 128-220px; preserve aspect ratio | H15: Static portrait/icon unless animation is defined | I15: sprites/npcs/ | J15: Use placeholders only for non-critical NPCs; story route UI needs final portraits. | Updated 2026-05-19: non-board visual source supports 627x627 PNG or 1254x1254 2x2 sheets; runtime display is category-constrained. | K15: Friendly Brixonia festival NPC; expressive, bright, readable.
... A28: ☐ | B28: ico_npc_repair_sprite | C28: icons/npcs/ | D28: Repair Sprite compact icon for dialogue headers, map/shop/event labels. | E28: P2 | F28: 627x627 PNG portrait source | G28: Dialogue 96-128px; story/unlock modal 128-220px; preserve aspect ratio | H28: Static portrait/icon unless animation is defined | I28: sprites/npcs/ | J28: Use placeholders only for non-critical NPCs; story route UI needs final portraits. | Updated 2026-05-19: non-board visual source supports 627x627 PNG or 1254x1254 2x2 sheets; runtime display is category-constrained. | K28: Friendly Brixonia festival NPC; expressive, bright, readable.

Sheet 18 - Board Blocks
A1: 18. Runtime Sprite Assets — Board Blocks and Board UI
A2: Updated from latest exact runtime ID audit. Primary assets use runtime IDs such as block_red, not old spr_block_red_rune names. All folders below are ZIP-ready paths relative to public/assets/.
A4: Done? | B4: Runtime Asset ID | C4: Asset Role / State | D4: Final Folder (relative to public/assets) | E4: Filename Pattern | F4: Source / Export Size | G4: Runtime Render Size | H4: Exact Frames / Count | I4: Legacy/Fallback Key | J4: Designer Description | K4: Priority | L4: Audit / Theme Note
A5: ☑ | B5: block_red | C5: base | D5: sprites/board-blocks/block_red/base/ | E5: block_red__base__f00.png | F5: 24x24 PNG | G5: 24x24 board cell; previews may render 16x16 | H5: base: 1 exact PNG frame(s); 10 total PNGs: base 1, glow 3, clear 5, icon 1 | I5: spr_block_red | J5: Festival-warm rune tile like a tiny Falling Stars lantern; strong red silhouette, snack-fair sparkle, and a simple readable rune for fast cascade play. | K5: P0 | L5: Primary current runtime ID. Board cells must not render native 32/48 sizes.
A6: ☑ | B6: block_red | C6: glow | D6: sprites/board-blocks/block_red/glow/ | E6: block_red__glow__f00..f02.png | F6: 24x24 PNG frames | G6: 24x24 board cell; previews may render 16x16 | H6: glow: 3 exact PNG frame(s); 10 total PNGs: base 1, glow 3, clear 5, icon 1 | I6: spr_block_red | J6: Festival-warm rune tile like a tiny Falling Stars lantern; strong red silhouette, snack-fair sparkle, and a simple readable rune for fast cascade play. | K6: P0 | L6: Primary current runtime ID. Board cells must not render native 32/48 sizes.
A7: ☑ | B7: block_red | C7: clear | D7: sprites/board-blocks/block_red/clear/ | E7: block_red__clear__f00..f04.png | F7: 24x24 PNG frames | G7: 24x24 board cell; previews may render 16x16 | H7: clear: 5 exact PNG frame(s); 10 total PNGs: base 1, glow 3, clear 5, icon 1 | I7: spr_block_red | J7: Festival-warm rune tile like a tiny Falling Stars lantern; strong red silhouette, snack-fair sparkle, and a simple readable rune for fast cascade play. | K7: P0 | L7: Primary current runtime ID. Board cells must not render native 32/48 sizes.
A8: ☑ | B8: block_red | C8: icon | D8: icons/board-blocks/ | E8: ico_block_red.png | F8: 48x48 PNG | G8: 48x48 UI icon | H8: icon: 1 PNG; 10 total PNGs: base 1, glow 3, clear 5, icon 1 | I8: ico_block_red | J8: Festival-warm rune tile like a tiny Falling Stars lantern; strong red silhouette, snack-fair sparkle, and a simple readable rune for fast cascade play. | K8: P0 | L8: Primary current runtime ID. Board cells must not render native 32/48 sizes.
A9: ☑ | B9: block_blue | C9: base | D9: sprites/board-blocks/block_blue/base/ | E9: block_blue__base__f00.png | F9: 24x24 PNG | G9: 24x24 board cell; previews may render 16x16 | H9: base: 1 exact PNG frame(s); 10 total PNGs: base 1, glow 3, clear 5, icon 1 | I9: spr_block_blue | J9: Cool blue festival rune tile with lemonade-glass shine and clean magical symbol; readable as a calm base block at 24x24. | K9: P0 | L9: Primary current runtime ID. Board cells must not render native 32/48 sizes.
A10: ☑ | B10: block_blue | C10: glow | D10: sprites/board-blocks/block_blue/glow/ | E10: block_blue__glow__f00..f02.png | F10: 24x24 PNG frames | G10: 24x24 board cell; previews may render 16x16 | H10: glow: 3 exact PNG frame(s); 10 total PNGs: base 1, glow 3, clear 5, icon 1 | I10: spr_block_blue | J10: Cool blue festival rune tile with lemonade-glass shine and clean magical symbol; readable as a calm base block at 24x24. | K10: P0 | L10: Primary current runtime ID. Board cells must not render native 32/48 sizes.
A11: ☑ | B11: block_blue | C11: clear | D11: sprites/board-blocks/block_blue/clear/ | E11: block_blue__clear__f00..f04.png | F11: 24x24 PNG frames | G11: 24x24 board cell; previews may render 16x16 | H11: clear: 5 exact PNG frame(s); 10 total PNGs: base 1, glow 3, clear 5, icon 1 | I11: spr_block_blue | J11: Cool blue festival rune tile with lemonade-glass shine and clean magical symbol; readable as a calm base block at 24x24. | K11: P0 | L11: Primary current runtime ID. Board cells must not render native 32/48 sizes.
A12: ☑ | B12: block_blue | C12: icon | D12: icons/board-blocks/ | E12: ico_block_blue.png | F12: 48x48 PNG | G12: 48x48 UI icon | H12: icon: 1 PNG; 10 total PNGs: base 1, glow 3, clear 5, icon 1 | I12: ico_block_blue | J12: Cool blue festival rune tile with lemonade-glass shine and clean magical symbol; readable as a calm base block at 24x24. | K12: P0 | L12: Primary current runtime ID. Board cells must not render native 32/48 sizes.
A13: ☑ | B13: block_green | C13: base | D13: sprites/board-blocks/block_green/base/ | E13: block_green__base__f00.png | F13: 24x24 PNG | G13: 24x24 board cell; previews may render 16x16 | H13: base: 1 exact PNG frame(s); 10 total PNGs: base 1, glow 3, clear 5, icon 1 | I13: spr_block_green | J13: Fresh green festival rune tile with garden-stall sparkle, rounded toy-like corners, and clear color identity for board readability. | K13: P0 | L13: Primary current runtime ID. Board cells must not render native 32/48 sizes.
A14: ☑ | B14: block_green | C14: glow | D14: sprites/board-blocks/block_green/glow/ | E14: block_green__glow__f00..f02.png | F14: 24x24 PNG frames | G14: 24x24 board cell; previews may render 16x16 | H14: glow: 3 exact PNG frame(s); 10 total PNGs: base 1, glow 3, clear 5, icon 1 | I14: spr_block_green | J14: Fresh green festival rune tile with garden-stall sparkle, rounded toy-like corners, and clear color identity for board readability. | K14: P0 | L14: Primary current runtime ID. Board cells must not render native 32/48 sizes.
A15: ☑ | B15: block_green | C15: clear | D15: sprites/board-blocks/block_green/clear/ | E15: block_green__clear__f00..f04.png | F15: 24x24 PNG frames | G15: 24x24 board cell; previews may render 16x16 | H15: clear: 5 exact PNG frame(s); 10 total PNGs: base 1, glow 3, clear 5, icon 1 | I15: spr_block_green | J15: Fresh green festival rune tile with garden-stall sparkle, rounded toy-like corners, and clear color identity for board readability. | K15: P0 | L15: Primary current runtime ID. Board cells must not render native 32/48 sizes.
... A109: ☑ | B109: block_void | C109: icon | D109: icons/board-blocks/ | E109: ico_block_void.png | F109: 48x48 PNG | G109: 48x48 UI icon | H109: icon: 1 PNG; Static fallback set: base 1, icon 1 unless animation standard is added | I109: ico_block_void | J109: Generic void runtime block; keep it playful and magical, avoiding dark/horror visuals. | K109: P1 | L109: Runtime ID from audit but not a detailed GDD block; treat as fallback/generic unless confirmed in content. Board cells must not render native 32/48 sizes.

Sheet 19 and VFX - Spells
A1: 19. Icon and VFX Assets — Spells
A2: Tracking sheet generated from the uploaded markdown. Done? is unchecked by default.
A4: Done? | B4: Asset Key | C4: Suggested Folder | D4: Designer Description | E4: Priority | F4: Source / Export Size | G4: Runtime Render Size | H4: Exact Frames / Count | I4: Final Folder Structure (relative to public/assets) | J4: Audit / Release Note | K4: GDD Theme / Prompt Note
A5: ☐ | B5: ico_spl_fireball | C5: icons/spells/ | D5: Fireball spell icon. Must clearly communicate: Fire damage; should feel like Pippa preheating the enemy. | E5: P0 | F5: 627x627 PNG frames | G5: Board-cell 24-48px; combat 64-180px; boss special 180-240px; centered and constrained | H5: icon: 1 PNG | I5: icons/spells/ | J5: Audit: full spell roster behavior partial; final spell icons/VFX should match 15 Release 1 spells. | Updated 2026-05-19: non-board visual source supports 627x627 PNG or 1254x1254 2x2 sheets; runtime display is category-constrained. | K5: Playful magical snack/festival effect: fire, frost, bomb, confetti, star, bubble, or cascade cheer.
A6: ☐ | B6: vfx_spl_fireball_cast | C6: sprites/effects/ | D6: Cast VFX: short readable effect around hero/spell button for Fireball. | E6: P1 | F6: 627x627 PNG frames | G6: Board-cell 24-48px; combat 64-180px; boss special 180-240px; centered and constrained | H6: Spell VFX exact frames: 6-8 depending spell; see ANIMATION_ASSET_REQUIREMENTS | I6: effects/spells/ | J6: Audit: full spell roster behavior partial; final spell icons/VFX should match 15 Release 1 spells. | Updated 2026-05-19: non-board visual source supports 627x627 PNG or 1254x1254 2x2 sheets; runtime display is category-constrained. | K6: Playful magical snack/festival effect: fire, frost, bomb, confetti, star, bubble, or cascade cheer.
A7: ☐ | B7: vfx_spl_fireball_impact | C7: sprites/effects/ | D7: Impact VFX: board/enemy effect showing result of Fireball. | E7: P1 | F7: 627x627 PNG frames | G7: Board-cell 24-48px; combat 64-180px; boss special 180-240px; centered and constrained | H7: Spell VFX exact frames: 6-8 depending spell; see ANIMATION_ASSET_REQUIREMENTS | I7: effects/spells/ | J7: Audit: full spell roster behavior partial; final spell icons/VFX should match 15 Release 1 spells. | Updated 2026-05-19: non-board visual source supports 627x627 PNG or 1254x1254 2x2 sheets; runtime display is category-constrained. | K7: Playful magical snack/festival effect: fire, frost, bomb, confetti, star, bubble, or cascade cheer.
A8: ☐ | B8: ico_spl_frost_lock | C8: icons/spells/ | D8: Frost Lock spell icon. Must clearly communicate: Control spell; chills fall speed or freezes enemy timing. | E8: P0 | F8: 627x627 PNG frames | G8: Board-cell 24-48px; combat 64-180px; boss special 180-240px; centered and constrained | H8: icon: 1 PNG | I8: icons/spells/ | J8: Audit: full spell roster behavior partial; final spell icons/VFX should match 15 Release 1 spells. | Updated 2026-05-19: non-board visual source supports 627x627 PNG or 1254x1254 2x2 sheets; runtime display is category-constrained. | K8: Playful magical snack/festival effect: fire, frost, bomb, confetti, star, bubble, or cascade cheer.
A9: ☐ | B9: vfx_spl_frost_lock_cast | C9: sprites/effects/ | D9: Cast VFX: short readable effect around hero/spell button for Frost Lock. | E9: P1 | F9: 627x627 PNG frames | G9: Board-cell 24-48px; combat 64-180px; boss special 180-240px; centered and constrained | H9: Spell VFX exact frames: 6-8 depending spell; see ANIMATION_ASSET_REQUIREMENTS | I9: effects/spells/ | J9: Audit: full spell roster behavior partial; final spell icons/VFX should match 15 Release 1 spells. | Updated 2026-05-19: non-board visual source supports 627x627 PNG or 1254x1254 2x2 sheets; runtime display is category-constrained. | K9: Playful magical snack/festival effect: fire, frost, bomb, confetti, star, bubble, or cascade cheer.
A10: ☐ | B10: vfx_spl_frost_lock_impact | C10: sprites/effects/ | D10: Impact VFX: board/enemy effect showing result of Frost Lock. | E10: P1 | F10: 627x627 PNG frames | G10: Board-cell 24-48px; combat 64-180px; boss special 180-240px; centered and constrained | H10: Spell VFX exact frames: 6-8 depending spell; see ANIMATION_ASSET_REQUIREMENTS | I10: effects/spells/ | J10: Audit: full spell roster behavior partial; final spell icons/VFX should match 15 Release 1 spells. | Updated 2026-05-19: non-board visual source supports 627x627 PNG or 1254x1254 2x2 sheets; runtime display is category-constrained. | K10: Playful magical snack/festival effect: fire, frost, bomb, confetti, star, bubble, or cascade cheer.
A11: ☐ | B11: ico_spl_bomb_rune | C11: icons/spells/ | D11: Bomb Rune spell icon. Must clearly communicate: Board-clear spell; creates a toy bomb area clear. | E11: P0 | F11: 627x627 PNG frames | G11: Board-cell 24-48px; combat 64-180px; boss special 180-240px; centered and constrained | H11: icon: 1 PNG | I11: icons/spells/ | J11: Audit: full spell roster behavior partial; final spell icons/VFX should match 15 Release 1 spells. | Updated 2026-05-19: non-board visual source supports 627x627 PNG or 1254x1254 2x2 sheets; runtime display is category-constrained. | K11: Playful magical snack/festival effect: fire, frost, bomb, confetti, star, bubble, or cascade cheer.
A12: ☐ | B12: vfx_spl_bomb_rune_cast | C12: sprites/effects/ | D12: Cast VFX: short readable effect around hero/spell button for Bomb Rune. | E12: P1 | F12: 627x627 PNG frames | G12: Board-cell 24-48px; combat 64-180px; boss special 180-240px; centered and constrained | H12: Spell VFX exact frames: 6-8 depending spell; see ANIMATION_ASSET_REQUIREMENTS | I12: effects/spells/ | J12: Audit: full spell roster behavior partial; final spell icons/VFX should match 15 Release 1 spells. | Updated 2026-05-19: non-board visual source supports 627x627 PNG or 1254x1254 2x2 sheets; runtime display is category-constrained. | K12: Playful magical snack/festival effect: fire, frost, bomb, confetti, star, bubble, or cascade cheer.
A13: ☐ | B13: vfx_spl_bomb_rune_impact | C13: sprites/effects/ | D13: Impact VFX: board/enemy effect showing result of Bomb Rune. | E13: P1 | F13: 627x627 PNG frames | G13: Board-cell 24-48px; combat 64-180px; boss special 180-240px; centered and constrained | H13: Spell VFX exact frames: 6-8 depending spell; see ANIMATION_ASSET_REQUIREMENTS | I13: effects/spells/ | J13: Audit: full spell roster behavior partial; final spell icons/VFX should match 15 Release 1 spells. | Updated 2026-05-19: non-board visual source supports 627x627 PNG or 1254x1254 2x2 sheets; runtime display is category-constrained. | K13: Playful magical snack/festival effect: fire, frost, bomb, confetti, star, bubble, or cascade cheer.
A14: ☐ | B14: ico_spl_clean_cut | C14: icons/spells/ | D14: Clean Cut spell icon. Must clearly communicate: Precise cleanup spell that clears a row or messy pattern. | E14: P0 | F14: 627x627 PNG frames | G14: Board-cell 24-48px; combat 64-180px; boss special 180-240px; centered and constrained | H14: icon: 1 PNG | I14: icons/spells/ | J14: Audit: full spell roster behavior partial; final spell icons/VFX should match 15 Release 1 spells. | Updated 2026-05-19: non-board visual source supports 627x627 PNG or 1254x1254 2x2 sheets; runtime display is category-constrained. | K14: Playful magical snack/festival effect: fire, frost, bomb, confetti, star, bubble, or cascade cheer.
A15: ☐ | B15: vfx_spl_clean_cut_cast | C15: sprites/effects/ | D15: Cast VFX: short readable effect around hero/spell button for Clean Cut. | E15: P1 | F15: 627x627 PNG frames | G15: Board-cell 24-48px; combat 64-180px; boss special 180-240px; centered and constrained | H15: Spell VFX exact frames: 6-8 depending spell; see ANIMATION_ASSET_REQUIREMENTS | I15: effects/spells/ | J15: Audit: full spell roster behavior partial; final spell icons/VFX should match 15 Release 1 spells. | Updated 2026-05-19: non-board visual source supports 627x627 PNG or 1254x1254 2x2 sheets; runtime display is category-constrained. | K15: Playful magical snack/festival effect: fire, frost, bomb, confetti, star, bubble, or cascade cheer.
... A49: ☐ | B49: vfx_spl_cascade_cheer_impact | C49: sprites/effects/ | D49: Impact VFX: board/enemy effect showing result of Cascade Cheer. | E49: P1 | F49: 627x627 PNG frames | G49: Board-cell 24-48px; combat 64-180px; boss special 180-240px; centered and constrained | H49: Spell VFX exact frames: 6-8 depending spell; see ANIMATION_ASSET_REQUIREMENTS | I49: effects/spells/ | J49: Audit: full spell roster behavior partial; final spell icons/VFX should match 15 Release 1 spells. | Updated 2026-05-19: non-board visual source supports 627x627 PNG or 1254x1254 2x2 sheets; runtime display is category-constrained. | K49: Playful magical snack/festival effect: fire, frost, bomb, confetti, star, bubble, or cascade cheer.

Sheet 20 - Items
A1: 20. Icon Assets — Items and Reactive Counter Items
A2: Tracking sheet generated from the uploaded markdown. Done? is unchecked by default.
A4: Done? | B4: Asset Key | C4: Suggested Folder | D4: Designer Description | E4: Priority | F4: Source / Export Size | G4: Runtime Render Size | H4: Exact Frames / Count | I4: Final Folder Structure (relative to public/assets) | J4: Audit / Release Note | K4: GDD Theme / Prompt Note
A5: ☐ | B5: ico_item_mini_cupcake | C5: icons/items/ | D5: Mini Cupcake icon: small healing snack; icon should look instantly edible and friendly. | E5: P0 | F5: 627x627 PNG source | G5: HUD/button 24-48px; inventory 32-64px; reward/shop card 64-96px; modal 96-128px | H5: icon: 1 PNG | I5: icons/items/ | J5: Audit: item content coverage exceeds verified runtime behavior; make counters readable. | Updated 2026-05-19: non-board visual source supports 627x627 PNG or 1254x1254 2x2 sheets; runtime display is category-constrained. | K5: Tactical festival tool/snack that clearly suggests heal, mana, cleanup, counter, or gadget use.
A6: ☐ | B6: ico_item_mana_lemonade | C6: icons/items/ | D6: Mana Lemonade icon: blue/yellow lemonade bottle for mana refill. | E6: P0 | F6: 627x627 PNG source | G6: HUD/button 24-48px; inventory 32-64px; reward/shop card 64-96px; modal 96-128px | H6: icon: 1 PNG | I6: icons/items/ | J6: Audit: item content coverage exceeds verified runtime behavior; make counters readable. | Updated 2026-05-19: non-board visual source supports 627x627 PNG or 1254x1254 2x2 sheets; runtime display is category-constrained. | K6: Tactical festival tool/snack that clearly suggests heal, mana, cleanup, counter, or gadget use.
A7: ☐ | B7: ico_item_rainbow_soda | C7: icons/items/ | D7: Rainbow Soda icon: rainbow drink that fills Fever meter. | E7: P0 | F7: 627x627 PNG source | G7: HUD/button 24-48px; inventory 32-64px; reward/shop card 64-96px; modal 96-128px | H7: icon: 1 PNG | I7: icons/items/ | J7: Audit: item content coverage exceeds verified runtime behavior; make counters readable. | Updated 2026-05-19: non-board visual source supports 627x627 PNG or 1254x1254 2x2 sheets; runtime display is category-constrained. | K7: Tactical festival tool/snack that clearly suggests heal, mana, cleanup, counter, or gadget use.
A8: ☐ | B8: ico_item_toolbox | C8: icons/items/ | D8: Toolbox icon: small red/yellow toolbox for removing junk blocks. | E8: P0 | F8: 627x627 PNG source | G8: HUD/button 24-48px; inventory 32-64px; reward/shop card 64-96px; modal 96-128px | H8: icon: 1 PNG | I8: icons/items/ | J8: Audit: item content coverage exceeds verified runtime behavior; make counters readable. | Updated 2026-05-19: non-board visual source supports 627x627 PNG or 1254x1254 2x2 sheets; runtime display is category-constrained. | K8: Tactical festival tool/snack that clearly suggests heal, mana, cleanup, counter, or gadget use.
A9: ☐ | B9: ico_item_snowcone | C9: icons/items/ | D9: Snowcone icon: icy treat for slowing fall speed temporarily. | E9: P0 | F9: 627x627 PNG source | G9: HUD/button 24-48px; inventory 32-64px; reward/shop card 64-96px; modal 96-128px | H9: icon: 1 PNG | I9: icons/items/ | J9: Audit: item content coverage exceeds verified runtime behavior; make counters readable. | Updated 2026-05-19: non-board visual source supports 627x627 PNG or 1254x1254 2x2 sheets; runtime display is category-constrained. | K9: Tactical festival tool/snack that clearly suggests heal, mana, cleanup, counter, or gadget use.
A10: ☐ | B10: ico_item_party_popper | C10: icons/items/ | D10: Party Popper icon: party popper that clears random cells. | E10: P1 | F10: 627x627 PNG source | G10: HUD/button 24-48px; inventory 32-64px; reward/shop card 64-96px; modal 96-128px | H10: icon: 1 PNG | I10: icons/items/ | J10: Audit: item content coverage exceeds verified runtime behavior; make counters readable. | Updated 2026-05-19: non-board visual source supports 627x627 PNG or 1254x1254 2x2 sheets; runtime display is category-constrained. | K10: Tactical festival tool/snack that clearly suggests heal, mana, cleanup, counter, or gadget use.
A11: ☐ | B11: ico_item_bubble_gum | C11: icons/items/ | D11: Bubble Gum icon: pink bubble gum that grants shield. | E11: P1 | F11: 627x627 PNG source | G11: HUD/button 24-48px; inventory 32-64px; reward/shop card 64-96px; modal 96-128px | H11: icon: 1 PNG | I11: icons/items/ | J11: Audit: item content coverage exceeds verified runtime behavior; make counters readable. | Updated 2026-05-19: non-board visual source supports 627x627 PNG or 1254x1254 2x2 sheets; runtime display is category-constrained. | K11: Tactical festival tool/snack that clearly suggests heal, mana, cleanup, counter, or gadget use.
A12: ☐ | B12: ico_item_lucky_ticket | C12: icons/items/ | D12: Lucky Ticket icon: festival ticket for rerolling rewards. | E12: P1 | F12: 627x627 PNG source | G12: HUD/button 24-48px; inventory 32-64px; reward/shop card 64-96px; modal 96-128px | H12: icon: 1 PNG | I12: icons/items/ | J12: Audit: item content coverage exceeds verified runtime behavior; make counters readable. | Updated 2026-05-19: non-board visual source supports 627x627 PNG or 1254x1254 2x2 sheets; runtime display is category-constrained. | K12: Tactical festival tool/snack that clearly suggests heal, mana, cleanup, counter, or gadget use.
A13: ☐ | B13: ico_item_hold_coupon | C13: icons/items/ | D13: Hold Coupon icon: coupon/ticket for refreshing Hold block. | E13: P1 | F13: 627x627 PNG source | G13: HUD/button 24-48px; inventory 32-64px; reward/shop card 64-96px; modal 96-128px | H13: icon: 1 PNG | I13: icons/items/ | J13: Audit: item content coverage exceeds verified runtime behavior; make counters readable. | Updated 2026-05-19: non-board visual source supports 627x627 PNG or 1254x1254 2x2 sheets; runtime display is category-constrained. | K13: Tactical festival tool/snack that clearly suggests heal, mana, cleanup, counter, or gadget use.
A14: ☐ | B14: ico_item_block_polish | C14: icons/items/ | D14: Block Polish icon: sparkly polish bottle that converts junk to normal block. | E14: P1 | F14: 627x627 PNG source | G14: HUD/button 24-48px; inventory 32-64px; reward/shop card 64-96px; modal 96-128px | H14: icon: 1 PNG | I14: icons/items/ | J14: Audit: item content coverage exceeds verified runtime behavior; make counters readable. | Updated 2026-05-19: non-board visual source supports 627x627 PNG or 1254x1254 2x2 sheets; runtime display is category-constrained. | K14: Tactical festival tool/snack that clearly suggests heal, mana, cleanup, counter, or gadget use.
A15: ☐ | B15: ico_item_snack_vacuum | C15: icons/items/ | D15: Snack Vacuum icon: cute vacuum that removes junk blocks from chosen area. | E15: P1 | F15: 627x627 PNG source | G15: HUD/button 24-48px; inventory 32-64px; reward/shop card 64-96px; modal 96-128px | H15: icon: 1 PNG | I15: icons/items/ | J15: Audit: item content coverage exceeds verified runtime behavior; make counters readable. | Updated 2026-05-19: non-board visual source supports 627x627 PNG or 1254x1254 2x2 sheets; runtime display is category-constrained. | K15: Tactical festival tool/snack that clearly suggests heal, mana, cleanup, counter, or gadget use.
... A56: ☐ | B56: ico_item_mana_straw | C56: icons/items/ | D56: Mana Straw icon: utility catalyst that converts sprinkle blocks into mana. | E56: P1 | F56: 627x627 PNG source | G56: HUD/button 24-48px; inventory 32-64px; reward/shop card 64-96px; modal 96-128px | H56: icon: 1 PNG | I56: icons/items/ | J56: Audit: item content coverage exceeds verified runtime behavior; make counters readable. | Updated 2026-05-19: non-board visual source supports 627x627 PNG or 1254x1254 2x2 sheets; runtime display is category-constrained. | K56: Tactical festival tool/snack that clearly suggests heal, mana, cleanup, counter, or gadget use.

Sheet 21 - Relics
A1: 21. Icon Assets — Relics
A2: Tracking sheet generated from the uploaded markdown. Done? is unchecked by default.
A4: Done? | B4: Asset Key | C4: Suggested Folder | D4: Designer Description | E4: Priority | F4: Source / Export Size | G4: Runtime Render Size | H4: Exact Frames / Count | I4: Final Folder Structure (relative to public/assets) | J4: Audit / Release Note | K4: GDD Theme / Prompt Note
A5: ☐ | B5: ico_rel_goblin_coin | C5: icons/relics/ | D5: Goblin Coin relic icon: lucky goblin coin that increases gold gain. Should look like a collectible souvenir. | E5: P1 | F5: 627x627 PNG source | G5: HUD/button 24-48px; inventory 32-64px; reward/shop card 64-96px; modal 96-128px | H5: icon: 1 PNG | I5: icons/relics/ | J5: Audit: some relics use safe placeholders/switch handlers; verify final effect support. | Updated 2026-05-19: non-board visual source supports 627x627 PNG or 1254x1254 2x2 sheets; runtime display is category-constrained. | K5: Collectible festival souvenir, charm, snack, toy, or machine part with clear rarity feel.
A6: ☐ | B6: ico_rel_lucky_cupcake | C6: icons/relics/ | D6: Lucky Cupcake relic icon: cute cupcake charm that heals after boss. Should look like a collectible souvenir. | E6: P1 | F6: 627x627 PNG source | G6: HUD/button 24-48px; inventory 32-64px; reward/shop card 64-96px; modal 96-128px | H6: icon: 1 PNG | I6: icons/relics/ | J6: Audit: some relics use safe placeholders/switch handlers; verify final effect support. | Updated 2026-05-19: non-board visual source supports 627x627 PNG or 1254x1254 2x2 sheets; runtime display is category-constrained. | K6: Collectible festival souvenir, charm, snack, toy, or machine part with clear rarity feel.
A7: ☐ | B7: ico_rel_sparkly_spoon | C7: icons/relics/ | D7: Sparkly Spoon relic icon: shiny spoon relic that boosts line damage. Should look like a collectible souvenir. | E7: P1 | F7: 627x627 PNG source | G7: HUD/button 24-48px; inventory 32-64px; reward/shop card 64-96px; modal 96-128px | H7: icon: 1 PNG | I7: icons/relics/ | J7: Audit: some relics use safe placeholders/switch handlers; verify final effect support. | Updated 2026-05-19: non-board visual source supports 627x627 PNG or 1254x1254 2x2 sheets; runtime display is category-constrained. | K7: Collectible festival souvenir, charm, snack, toy, or machine part with clear rarity feel.
A8: ☐ | B8: ico_rel_sticky_sticker | C8: icons/relics/ | D8: Sticky Sticker relic icon: sticker relic that turns sticky clears into mana value. Should look like a collectible souvenir. | E8: P1 | F8: 627x627 PNG source | G8: HUD/button 24-48px; inventory 32-64px; reward/shop card 64-96px; modal 96-128px | H8: icon: 1 PNG | I8: icons/relics/ | J8: Audit: some relics use safe placeholders/switch handlers; verify final effect support. | Updated 2026-05-19: non-board visual source supports 627x627 PNG or 1254x1254 2x2 sheets; runtime display is category-constrained. | K8: Collectible festival souvenir, charm, snack, toy, or machine part with clear rarity feel.
A9: ☐ | B9: ico_rel_confetti_popper | C9: icons/relics/ | D9: Confetti Popper relic icon: party relic that may clear a random cell. Should look like a collectible souvenir. | E9: P1 | F9: 627x627 PNG source | G9: HUD/button 24-48px; inventory 32-64px; reward/shop card 64-96px; modal 96-128px | H9: icon: 1 PNG | I9: icons/relics/ | J9: Audit: some relics use safe placeholders/switch handlers; verify final effect support. | Updated 2026-05-19: non-board visual source supports 627x627 PNG or 1254x1254 2x2 sheets; runtime display is category-constrained. | K9: Collectible festival souvenir, charm, snack, toy, or machine part with clear rarity feel.
A10: ☐ | B10: ico_rel_rainbow_ticket | C10: icons/relics/ | D10: Rainbow Ticket relic icon: rare ticket granting extra reward choice. Should look like a collectible souvenir. | E10: P1 | F10: 627x627 PNG source | G10: HUD/button 24-48px; inventory 32-64px; reward/shop card 64-96px; modal 96-128px | H10: icon: 1 PNG | I10: icons/relics/ | J10: Audit: some relics use safe placeholders/switch handlers; verify final effect support. | Updated 2026-05-19: non-board visual source supports 627x627 PNG or 1254x1254 2x2 sheets; runtime display is category-constrained. | K10: Collectible festival souvenir, charm, snack, toy, or machine part with clear rarity feel.
A11: ☐ | B11: ico_rel_tiny_toolbox | C11: icons/relics/ | D11: Tiny Toolbox relic icon: small toolbox reducing bomb/gadget cost. Should look like a collectible souvenir. | E11: P1 | F11: 627x627 PNG source | G11: HUD/button 24-48px; inventory 32-64px; reward/shop card 64-96px; modal 96-128px | H11: icon: 1 PNG | I11: icons/relics/ | J11: Audit: some relics use safe placeholders/switch handlers; verify final effect support. | Updated 2026-05-19: non-board visual source supports 627x627 PNG or 1254x1254 2x2 sheets; runtime display is category-constrained. | K11: Collectible festival souvenir, charm, snack, toy, or machine part with clear rarity feel.
A12: ☐ | B12: ico_rel_plush_helmet | C12: icons/relics/ | D12: Plush Helmet relic icon: soft helmet that prevents lethal damage once. Should look like a collectible souvenir. | E12: P1 | F12: 627x627 PNG source | G12: HUD/button 24-48px; inventory 32-64px; reward/shop card 64-96px; modal 96-128px | H12: icon: 1 PNG | I12: icons/relics/ | J12: Audit: some relics use safe placeholders/switch handlers; verify final effect support. | Updated 2026-05-19: non-board visual source supports 627x627 PNG or 1254x1254 2x2 sheets; runtime display is category-constrained. | K12: Collectible festival souvenir, charm, snack, toy, or machine part with clear rarity feel.
A13: ☐ | B13: ico_rel_snowflake_charm | C13: icons/relics/ | D13: Snowflake Charm relic icon: icy charm strengthening frost spells. Should look like a collectible souvenir. | E13: P1 | F13: 627x627 PNG source | G13: HUD/button 24-48px; inventory 32-64px; reward/shop card 64-96px; modal 96-128px | H13: icon: 1 PNG | I13: icons/relics/ | J13: Audit: some relics use safe placeholders/switch handlers; verify final effect support. | Updated 2026-05-19: non-board visual source supports 627x627 PNG or 1254x1254 2x2 sheets; runtime display is category-constrained. | K13: Collectible festival souvenir, charm, snack, toy, or machine part with clear rarity feel.
A14: ☐ | B14: ico_rel_star_cookie | C14: icons/relics/ | D14: Star Cookie relic icon: star-shaped cookie increasing cascade damage. Should look like a collectible souvenir. | E14: P1 | F14: 627x627 PNG source | G14: HUD/button 24-48px; inventory 32-64px; reward/shop card 64-96px; modal 96-128px | H14: icon: 1 PNG | I14: icons/relics/ | J14: Audit: some relics use safe placeholders/switch handlers; verify final effect support. | Updated 2026-05-19: non-board visual source supports 627x627 PNG or 1254x1254 2x2 sheets; runtime display is category-constrained. | K14: Collectible festival souvenir, charm, snack, toy, or machine part with clear rarity feel.
A15: ☐ | B15: ico_rel_bouncy_boots | C15: icons/relics/ | D15: Bouncy Boots relic icon: boots that reward hard drops with mana. Should look like a collectible souvenir. | E15: P1 | F15: 627x627 PNG source | G15: HUD/button 24-48px; inventory 32-64px; reward/shop card 64-96px; modal 96-128px | H15: icon: 1 PNG | I15: icons/relics/ | J15: Audit: some relics use safe placeholders/switch handlers; verify final effect support. | Updated 2026-05-19: non-board visual source supports 627x627 PNG or 1254x1254 2x2 sheets; runtime display is category-constrained. | K15: Collectible festival souvenir, charm, snack, toy, or machine part with clear rarity feel.
... A19: ☐ | B19: ico_rel_block_o_manual | C19: icons/relics/ | D19: Block-O Manual relic icon: legendary manual that fixes or highlights a messy row once per battle. Should look like a collectible souvenir. | E19: P1 | F19: 627x627 PNG source | G19: HUD/button 24-48px; inventory 32-64px; reward/shop card 64-96px; modal 96-128px | H19: icon: 1 PNG | I19: icons/relics/ | J19: Audit: some relics use safe placeholders/switch handlers; verify final effect support. | Updated 2026-05-19: non-board visual source supports 627x627 PNG or 1254x1254 2x2 sheets; runtime display is category-constrained. | K19: Collectible festival souvenir, charm, snack, toy, or machine part with clear rarity feel.

Sheet 22 - Upgrades
A1: 22. Icon Assets — Upgrades
A2: Tracking sheet generated from the uploaded markdown. Done? is unchecked by default.
A4: Done? | B4: Asset Key | C4: Suggested Folder | D4: Designer Description | E4: Priority | F4: Source / Export Size | G4: Runtime Render Size | H4: Exact Frames / Count | I4: Final Folder Structure (relative to public/assets) | J4: Audit / Release Note | K4: GDD Theme / Prompt Note
A5: ☐ | B5: ico_upg_clean_stack | C5: icons/upgrades/ | D5: Clean Stack upgrade icon: board upgrade that slightly lowers fall speed. Use clear category visual language. | E5: P1 | F5: 627x627 PNG source | G5: HUD/button 24-48px; inventory 32-64px; reward/shop card 64-96px; modal 96-128px | H5: icon: 1 PNG | I5: icons/upgrades/ | J5: Audit: upgrade effect scaling is partial; icon should clearly show category. | Updated 2026-05-19: non-board visual source supports 627x627 PNG or 1254x1254 2x2 sheets; runtime display is category-constrained. | K5: Readable upgrade card icon: board, damage, defense, mana, combo, spell, reward, or inventory.
A6: ☐ | B6: ico_upg_sharp_sprinkles | C6: icons/upgrades/ | D6: Sharp Sprinkles upgrade icon: damage upgrade for line clears. Use clear category visual language. | E6: P1 | F6: 627x627 PNG source | G6: HUD/button 24-48px; inventory 32-64px; reward/shop card 64-96px; modal 96-128px | H6: icon: 1 PNG | I6: icons/upgrades/ | J6: Audit: upgrade effect scaling is partial; icon should clearly show category. | Updated 2026-05-19: non-board visual source supports 627x627 PNG or 1254x1254 2x2 sheets; runtime display is category-constrained. | K6: Readable upgrade card icon: board, damage, defense, mana, combo, spell, reward, or inventory.
A7: ☐ | B7: ico_upg_extra_frosting | C7: icons/upgrades/ | D7: Extra Frosting upgrade icon: defense upgrade that increases max HP. Use clear category visual language. | E7: P1 | F7: 627x627 PNG source | G7: HUD/button 24-48px; inventory 32-64px; reward/shop card 64-96px; modal 96-128px | H7: icon: 1 PNG | I7: icons/upgrades/ | J7: Audit: upgrade effect scaling is partial; icon should clearly show category. | Updated 2026-05-19: non-board visual source supports 627x627 PNG or 1254x1254 2x2 sheets; runtime display is category-constrained. | K7: Readable upgrade card icon: board, damage, defense, mana, combo, spell, reward, or inventory.
A8: ☐ | B8: ico_upg_mana_lemonade | C8: icons/upgrades/ | D8: Mana Lemonade upgrade icon: mana upgrade that increases mana gain. Use clear category visual language. | E8: P1 | F8: 627x627 PNG source | G8: HUD/button 24-48px; inventory 32-64px; reward/shop card 64-96px; modal 96-128px | H8: icon: 1 PNG | I8: icons/upgrades/ | J8: Audit: upgrade effect scaling is partial; icon should clearly show category. | Updated 2026-05-19: non-board visual source supports 627x627 PNG or 1254x1254 2x2 sheets; runtime display is category-constrained. | K8: Readable upgrade card icon: board, damage, defense, mana, combo, spell, reward, or inventory.
A9: ☐ | B9: ico_upg_combo_cheer | C9: icons/upgrades/ | D9: Combo Cheer upgrade icon: combo upgrade for cascade damage. Use clear category visual language. | E9: P1 | F9: 627x627 PNG source | G9: HUD/button 24-48px; inventory 32-64px; reward/shop card 64-96px; modal 96-128px | H9: icon: 1 PNG | I9: icons/upgrades/ | J9: Audit: upgrade effect scaling is partial; icon should clearly show category. | Updated 2026-05-19: non-board visual source supports 627x627 PNG or 1254x1254 2x2 sheets; runtime display is category-constrained. | K9: Readable upgrade card icon: board, damage, defense, mana, combo, spell, reward, or inventory.
A10: ☐ | B10: ico_upg_bigger_booms | C10: icons/upgrades/ | D10: Bigger Booms upgrade icon: spell upgrade increasing Bomb Rune radius. Use clear category visual language. | E10: P1 | F10: 627x627 PNG source | G10: HUD/button 24-48px; inventory 32-64px; reward/shop card 64-96px; modal 96-128px | H10: icon: 1 PNG | I10: icons/upgrades/ | J10: Audit: upgrade effect scaling is partial; icon should clearly show category. | Updated 2026-05-19: non-board visual source supports 627x627 PNG or 1254x1254 2x2 sheets; runtime display is category-constrained. | K10: Readable upgrade card icon: board, damage, defense, mana, combo, spell, reward, or inventory.
A11: ☐ | B11: ico_upg_hotter_oven | C11: icons/upgrades/ | D11: Hotter Oven upgrade icon: fire upgrade improving Fireball damage. Use clear category visual language. | E11: P1 | F11: 627x627 PNG source | G11: HUD/button 24-48px; inventory 32-64px; reward/shop card 64-96px; modal 96-128px | H11: icon: 1 PNG | I11: icons/upgrades/ | J11: Audit: upgrade effect scaling is partial; icon should clearly show category. | Updated 2026-05-19: non-board visual source supports 627x627 PNG or 1254x1254 2x2 sheets; runtime display is category-constrained. | K11: Readable upgrade card icon: board, damage, defense, mana, combo, spell, reward, or inventory.
A12: ☐ | B12: ico_upg_chill_zone | C12: icons/upgrades/ | D12: Chill Zone upgrade icon: frost upgrade improving Frost Lock. Use clear category visual language. | E12: P1 | F12: 627x627 PNG source | G12: HUD/button 24-48px; inventory 32-64px; reward/shop card 64-96px; modal 96-128px | H12: icon: 1 PNG | I12: icons/upgrades/ | J12: Audit: upgrade effect scaling is partial; icon should clearly show category. | Updated 2026-05-19: non-board visual source supports 627x627 PNG or 1254x1254 2x2 sheets; runtime display is category-constrained. | K12: Readable upgrade card icon: board, damage, defense, mana, combo, spell, reward, or inventory.
A13: ☐ | B13: ico_upg_pocket_snack | C13: icons/upgrades/ | D13: Pocket Snack upgrade icon: healing upgrade after each room. Use clear category visual language. | E13: P1 | F13: 627x627 PNG source | G13: HUD/button 24-48px; inventory 32-64px; reward/shop card 64-96px; modal 96-128px | H13: icon: 1 PNG | I13: icons/upgrades/ | J13: Audit: upgrade effect scaling is partial; icon should clearly show category. | Updated 2026-05-19: non-board visual source supports 627x627 PNG or 1254x1254 2x2 sheets; runtime display is category-constrained. | K13: Readable upgrade card icon: board, damage, defense, mana, combo, spell, reward, or inventory.
A14: ☐ | B14: ico_upg_bonus_preview | C14: icons/upgrades/ | D14: Bonus Preview upgrade icon: board upgrade showing extra next block. Use clear category visual language. | E14: P1 | F14: 627x627 PNG source | G14: HUD/button 24-48px; inventory 32-64px; reward/shop card 64-96px; modal 96-128px | H14: icon: 1 PNG | I14: icons/upgrades/ | J14: Audit: upgrade effect scaling is partial; icon should clearly show category. | Updated 2026-05-19: non-board visual source supports 627x627 PNG or 1254x1254 2x2 sheets; runtime display is category-constrained. | K14: Readable upgrade card icon: board, damage, defense, mana, combo, spell, reward, or inventory.
A15: ☐ | B15: ico_upg_quick_hold | C15: icons/upgrades/ | D15: Quick Hold upgrade icon: board upgrade reducing hold restrictions/cooldown. Use clear category visual language. | E15: P1 | F15: 627x627 PNG source | G15: HUD/button 24-48px; inventory 32-64px; reward/shop card 64-96px; modal 96-128px | H15: icon: 1 PNG | I15: icons/upgrades/ | J15: Audit: upgrade effect scaling is partial; icon should clearly show category. | Updated 2026-05-19: non-board visual source supports 627x627 PNG or 1254x1254 2x2 sheets; runtime display is category-constrained. | K15: Readable upgrade card icon: board, damage, defense, mana, combo, spell, reward, or inventory.
... A19: ☐ | B19: ico_upg_smooth_cascade | C19: icons/upgrades/ | D19: Smooth Cascade upgrade icon: cascade upgrade increasing mana from cascades. Use clear category visual language. | E19: P1 | F19: 627x627 PNG source | G19: HUD/button 24-48px; inventory 32-64px; reward/shop card 64-96px; modal 96-128px | H19: icon: 1 PNG | I19: icons/upgrades/ | J19: Audit: upgrade effect scaling is partial; icon should clearly show category. | Updated 2026-05-19: non-board visual source supports 627x627 PNG or 1254x1254 2x2 sheets; runtime display is category-constrained. | K19: Readable upgrade card icon: board, damage, defense, mana, combo, spell, reward, or inventory.

Sheet 23 and - Weapons
A1: 23. Icon and Sprite Assets — Weapons
A2: Tracking sheet generated from the uploaded markdown. Done? is unchecked by default.
A4: Done? | B4: Asset Key | C4: Suggested Folder | D4: Designer Description | E4: Priority | F4: Source / Export Size | G4: Runtime Render Size | H4: Exact Frames / Count | I4: Final Folder Structure (relative to public/assets) | J4: Audit / Release Note | K4: GDD Theme / Prompt Note
A5: ☐ | B5: ico_wpn_basic_wand | C5: icons/weapons/ | D5: Basic Wand weapon icon: starter wand with simple wooden/magic rune design. | E5: P1 | F5: 627x627 PNG source | G5: HUD/button 24-48px; inventory 32-64px; reward/shop card 64-96px; modal 96-128px | H5: icon: 1 PNG | I5: icons/weapons/ | J5: Audit: WeaponSystem is partial/lookup-heavy; final icons can be produced now. | Updated 2026-05-19: non-board visual source supports 627x627 PNG or 1254x1254 2x2 sheets; runtime display is category-constrained. | K5: Toy/kitchen/gadget/festival weapon; not dark or realistic.
A6: ☐ | B6: spr_wpn_basic_wand_small | C6: sprites/weapons/ | D6: Basic Wand small in-battle weapon sprite or hero overlay: starter wand with simple wooden/magic rune design. | E6: P2 | F6: 627x627 PNG source | G6: HUD/button 24-48px; inventory 32-64px; reward/shop card 64-96px; modal 96-128px | H6: Static small sprite unless animation is defined | I6: sprites/weapons/ | J6: Audit: WeaponSystem is partial/lookup-heavy; final icons can be produced now. | Updated 2026-05-19: non-board visual source supports 627x627 PNG or 1254x1254 2x2 sheets; runtime display is category-constrained. | K6: Toy/kitchen/gadget/festival weapon; not dark or realistic.
A7: ☐ | B7: ico_wpn_lemonade_wand | C7: icons/weapons/ | D7: Lemonade Wand weapon icon: wand with lemonade cup/bottle motif for mana gain. | E7: P1 | F7: 627x627 PNG source | G7: HUD/button 24-48px; inventory 32-64px; reward/shop card 64-96px; modal 96-128px | H7: icon: 1 PNG | I7: icons/weapons/ | J7: Audit: WeaponSystem is partial/lookup-heavy; final icons can be produced now. | Updated 2026-05-19: non-board visual source supports 627x627 PNG or 1254x1254 2x2 sheets; runtime display is category-constrained. | K7: Toy/kitchen/gadget/festival weapon; not dark or realistic.
A8: ☐ | B8: spr_wpn_lemonade_wand_small | C8: sprites/weapons/ | D8: Lemonade Wand small in-battle weapon sprite or hero overlay: wand with lemonade cup/bottle motif for mana gain. | E8: P2 | F8: 627x627 PNG source | G8: HUD/button 24-48px; inventory 32-64px; reward/shop card 64-96px; modal 96-128px | H8: Static small sprite unless animation is defined | I8: sprites/weapons/ | J8: Audit: WeaponSystem is partial/lookup-heavy; final icons can be produced now. | Updated 2026-05-19: non-board visual source supports 627x627 PNG or 1254x1254 2x2 sheets; runtime display is category-constrained. | K8: Toy/kitchen/gadget/festival weapon; not dark or realistic.
A9: ☐ | B9: ico_wpn_cookie_spatula | C9: icons/weapons/ | D9: Cookie Spatula weapon icon: baker spatula weapon for fire/cookie theme. | E9: P1 | F9: 627x627 PNG source | G9: HUD/button 24-48px; inventory 32-64px; reward/shop card 64-96px; modal 96-128px | H9: icon: 1 PNG | I9: icons/weapons/ | J9: Audit: WeaponSystem is partial/lookup-heavy; final icons can be produced now. | Updated 2026-05-19: non-board visual source supports 627x627 PNG or 1254x1254 2x2 sheets; runtime display is category-constrained. | K9: Toy/kitchen/gadget/festival weapon; not dark or realistic.
A10: ☐ | B10: spr_wpn_cookie_spatula_small | C10: sprites/weapons/ | D10: Cookie Spatula small in-battle weapon sprite or hero overlay: baker spatula weapon for fire/cookie theme. | E10: P2 | F10: 627x627 PNG source | G10: HUD/button 24-48px; inventory 32-64px; reward/shop card 64-96px; modal 96-128px | H10: Static small sprite unless animation is defined | I10: sprites/weapons/ | J10: Audit: WeaponSystem is partial/lookup-heavy; final icons can be produced now. | Updated 2026-05-19: non-board visual source supports 627x627 PNG or 1254x1254 2x2 sheets; runtime display is category-constrained. | K10: Toy/kitchen/gadget/festival weapon; not dark or realistic.
A11: ☐ | B11: ico_wpn_snowcone_staff | C11: icons/weapons/ | D11: Snowcone Staff weapon icon: icy staff with snowcone top for frost effects. | E11: P1 | F11: 627x627 PNG source | G11: HUD/button 24-48px; inventory 32-64px; reward/shop card 64-96px; modal 96-128px | H11: icon: 1 PNG | I11: icons/weapons/ | J11: Audit: WeaponSystem is partial/lookup-heavy; final icons can be produced now. | Updated 2026-05-19: non-board visual source supports 627x627 PNG or 1254x1254 2x2 sheets; runtime display is category-constrained. | K11: Toy/kitchen/gadget/festival weapon; not dark or realistic.
A12: ☐ | B12: spr_wpn_snowcone_staff_small | C12: sprites/weapons/ | D12: Snowcone Staff small in-battle weapon sprite or hero overlay: icy staff with snowcone top for frost effects. | E12: P2 | F12: 627x627 PNG source | G12: HUD/button 24-48px; inventory 32-64px; reward/shop card 64-96px; modal 96-128px | H12: Static small sprite unless animation is defined | I12: sprites/weapons/ | J12: Audit: WeaponSystem is partial/lookup-heavy; final icons can be produced now. | Updated 2026-05-19: non-board visual source supports 627x627 PNG or 1254x1254 2x2 sheets; runtime display is category-constrained. | K12: Toy/kitchen/gadget/festival weapon; not dark or realistic.
A13: ☐ | B13: ico_wpn_spring_hammer | C13: icons/weapons/ | D13: Spring Hammer weapon icon: goblin spring hammer for hard-drop damage. | E13: P1 | F13: 627x627 PNG source | G13: HUD/button 24-48px; inventory 32-64px; reward/shop card 64-96px; modal 96-128px | H13: icon: 1 PNG | I13: icons/weapons/ | J13: Audit: WeaponSystem is partial/lookup-heavy; final icons can be produced now. | Updated 2026-05-19: non-board visual source supports 627x627 PNG or 1254x1254 2x2 sheets; runtime display is category-constrained. | K13: Toy/kitchen/gadget/festival weapon; not dark or realistic.
A14: ☐ | B14: spr_wpn_spring_hammer_small | C14: sprites/weapons/ | D14: Spring Hammer small in-battle weapon sprite or hero overlay: goblin spring hammer for hard-drop damage. | E14: P2 | F14: 627x627 PNG source | G14: HUD/button 24-48px; inventory 32-64px; reward/shop card 64-96px; modal 96-128px | H14: Static small sprite unless animation is defined | I14: sprites/weapons/ | J14: Audit: WeaponSystem is partial/lookup-heavy; final icons can be produced now. | Updated 2026-05-19: non-board visual source supports 627x627 PNG or 1254x1254 2x2 sheets; runtime display is category-constrained. | K14: Toy/kitchen/gadget/festival weapon; not dark or realistic.
A15: ☐ | B15: ico_wpn_confetti_cannon | C15: icons/weapons/ | D15: Confetti Cannon weapon icon: party cannon gadget that suggests bomb/confetti chance. | E15: P1 | F15: 627x627 PNG source | G15: HUD/button 24-48px; inventory 32-64px; reward/shop card 64-96px; modal 96-128px | H15: icon: 1 PNG | I15: icons/weapons/ | J15: Audit: WeaponSystem is partial/lookup-heavy; final icons can be produced now. | Updated 2026-05-19: non-board visual source supports 627x627 PNG or 1254x1254 2x2 sheets; runtime display is category-constrained. | K15: Toy/kitchen/gadget/festival weapon; not dark or realistic.
... A24: ☐ | B24: spr_wpn_arcade_blaster_small | C24: sprites/weapons/ | D24: Arcade Blaster small in-battle weapon sprite or hero overlay: neon arcade blaster for Fever gain. | E24: P2 | F24: 627x627 PNG source | G24: HUD/button 24-48px; inventory 32-64px; reward/shop card 64-96px; modal 96-128px | H24: Static small sprite unless animation is defined | I24: sprites/weapons/ | J24: Audit: WeaponSystem is partial/lookup-heavy; final icons can be produced now. | Updated 2026-05-19: non-board visual source supports 627x627 PNG or 1254x1254 2x2 sheets; runtime display is category-constrained. | K24: Toy/kitchen/gadget/festival weapon; not dark or realistic.

Sheet 24 - Status Effects
A1: 24. Icon Assets — Status Effects
A2: Tracking sheet generated from the uploaded markdown. Done? is unchecked by default.
A4: Done? | B4: Asset Key | C4: Suggested Folder | D4: Designer Description | E4: Priority | F4: Source / Export Size | G4: Runtime Render Size | H4: Exact Frames / Count | I4: Final Folder Structure (relative to public/assets) | J4: Audit / Release Note | K4: GDD Theme / Prompt Note
A5: ☐ | B5: ico_status_sugar_rush | C5: icons/statuses/ | D5: Sugar Rush status icon: speed/action boost icon, candy lightning style. Keep readable at small HUD size. | E5: P1 | F5: 627x627 PNG source | G5: HUD/button 24-48px; inventory 32-64px; reward/shop card 64-96px; modal 96-128px | H5: icon: 1 PNG | I5: icons/status-effects/ | J5: Audit: verify status text/effects stay cheerful and readable. | Updated 2026-05-19: non-board visual source supports 627x627 PNG or 1254x1254 2x2 sheets; runtime display is category-constrained. | K5: Funny readable status: sugar rush, chilled, sleepy, sparkly, bubbled, confetti.
A6: ☐ | B6: ico_status_sticky | C6: icons/statuses/ | D6: Sticky status icon: goo/sticky status icon. Keep readable at small HUD size. | E6: P1 | F6: 627x627 PNG source | G6: HUD/button 24-48px; inventory 32-64px; reward/shop card 64-96px; modal 96-128px | H6: icon: 1 PNG | I6: icons/status-effects/ | J6: Audit: verify status text/effects stay cheerful and readable. | Updated 2026-05-19: non-board visual source supports 627x627 PNG or 1254x1254 2x2 sheets; runtime display is category-constrained. | K6: Funny readable status: sugar rush, chilled, sleepy, sparkly, bubbled, confetti.
A7: ☐ | B7: ico_status_chilled | C7: icons/statuses/ | D7: Chilled status icon: snowflake/cold status icon. Keep readable at small HUD size. | E7: P1 | F7: 627x627 PNG source | G7: HUD/button 24-48px; inventory 32-64px; reward/shop card 64-96px; modal 96-128px | H7: icon: 1 PNG | I7: icons/status-effects/ | J7: Audit: verify status text/effects stay cheerful and readable. | Updated 2026-05-19: non-board visual source supports 627x627 PNG or 1254x1254 2x2 sheets; runtime display is category-constrained. | K7: Funny readable status: sugar rush, chilled, sleepy, sparkly, bubbled, confetti.
A8: ☐ | B8: ico_status_sleepy | C8: icons/statuses/ | D8: Sleepy status icon: sleep bubble/z icon. Keep readable at small HUD size. | E8: P1 | F8: 627x627 PNG source | G8: HUD/button 24-48px; inventory 32-64px; reward/shop card 64-96px; modal 96-128px | H8: icon: 1 PNG | I8: icons/status-effects/ | J8: Audit: verify status text/effects stay cheerful and readable. | Updated 2026-05-19: non-board visual source supports 627x627 PNG or 1254x1254 2x2 sheets; runtime display is category-constrained. | K8: Funny readable status: sugar rush, chilled, sleepy, sparkly, bubbled, confetti.
A9: ☐ | B9: ico_status_dizzy | C9: icons/statuses/ | D9: Dizzy status icon: spiral stars icon. Keep readable at small HUD size. | E9: P1 | F9: 627x627 PNG source | G9: HUD/button 24-48px; inventory 32-64px; reward/shop card 64-96px; modal 96-128px | H9: icon: 1 PNG | I9: icons/status-effects/ | J9: Audit: verify status text/effects stay cheerful and readable. | Updated 2026-05-19: non-board visual source supports 627x627 PNG or 1254x1254 2x2 sheets; runtime display is category-constrained. | K9: Funny readable status: sugar rush, chilled, sleepy, sparkly, bubbled, confetti.
A10: ☐ | B10: ico_status_sparkly | C10: icons/statuses/ | D10: Sparkly status icon: extra mana sparkle icon. Keep readable at small HUD size. | E10: P1 | F10: 627x627 PNG source | G10: HUD/button 24-48px; inventory 32-64px; reward/shop card 64-96px; modal 96-128px | H10: icon: 1 PNG | I10: icons/status-effects/ | J10: Audit: verify status text/effects stay cheerful and readable. | Updated 2026-05-19: non-board visual source supports 627x627 PNG or 1254x1254 2x2 sheets; runtime display is category-constrained. | K10: Funny readable status: sugar rush, chilled, sleepy, sparkly, bubbled, confetti.
A11: ☐ | B11: ico_status_bubbled | C11: icons/statuses/ | D11: Bubbled status icon: shield bubble icon. Keep readable at small HUD size. | E11: P1 | F11: 627x627 PNG source | G11: HUD/button 24-48px; inventory 32-64px; reward/shop card 64-96px; modal 96-128px | H11: icon: 1 PNG | I11: icons/status-effects/ | J11: Audit: verify status text/effects stay cheerful and readable. | Updated 2026-05-19: non-board visual source supports 627x627 PNG or 1254x1254 2x2 sheets; runtime display is category-constrained. | K11: Funny readable status: sugar rush, chilled, sleepy, sparkly, bubbled, confetti.
A12: ☐ | B12: ico_status_confetti | C12: icons/statuses/ | D12: Confetti status icon: random party bonus icon. Keep readable at small HUD size. | E12: P1 | F12: 627x627 PNG source | G12: HUD/button 24-48px; inventory 32-64px; reward/shop card 64-96px; modal 96-128px | H12: icon: 1 PNG | I12: icons/status-effects/ | J12: Audit: verify status text/effects stay cheerful and readable. | Updated 2026-05-19: non-board visual source supports 627x627 PNG or 1254x1254 2x2 sheets; runtime display is category-constrained. | K12: Funny readable status: sugar rush, chilled, sleepy, sparkly, bubbled, confetti.
A13: ☐ | B13: ico_status_snack_boost | C13: icons/statuses/ | D13: Snack Boost status icon: snack/heal-over-time icon. Keep readable at small HUD size. | E13: P1 | F13: 627x627 PNG source | G13: HUD/button 24-48px; inventory 32-64px; reward/shop card 64-96px; modal 96-128px | H13: icon: 1 PNG | I13: icons/status-effects/ | J13: Audit: verify status text/effects stay cheerful and readable. | Updated 2026-05-19: non-board visual source supports 627x627 PNG or 1254x1254 2x2 sheets; runtime display is category-constrained. | K13: Funny readable status: sugar rush, chilled, sleepy, sparkly, bubbled, confetti.
A14: ☐ | B14: ico_status_overclocked | C14: icons/statuses/ | D14: Overclocked status icon: machine speed/junk reward icon. Keep readable at small HUD size. | E14: P1 | F14: 627x627 PNG source | G14: HUD/button 24-48px; inventory 32-64px; reward/shop card 64-96px; modal 96-128px | H14: icon: 1 PNG | I14: icons/status-effects/ | J14: Audit: verify status text/effects stay cheerful and readable. | Updated 2026-05-19: non-board visual source supports 627x627 PNG or 1254x1254 2x2 sheets; runtime display is category-constrained. | K14: Funny readable status: sugar rush, chilled, sleepy, sparkly, bubbled, confetti.

Sheet 25 - Oopsies
A1: 25. Icon Assets — Oopsies / Silly Drawbacks
A2: Tracking sheet generated from the uploaded markdown. Done? is unchecked by default.
A4: Done? | B4: Asset Key | C4: Suggested Folder | D4: Designer Description | E4: Priority | F4: Source / Export Size | G4: Runtime Render Size | H4: Exact Frames / Count | I4: Final Folder Structure (relative to public/assets) | J4: Audit / Release Note | K4: GDD Theme / Prompt Note
A5: ☐ | B5: ico_oops_heavy_blocks | C5: icons/oopsies/ | D5: Heavy Blocks Oopsie icon: fall speed drawback; heavy block/weight icon. Must feel silly, not cursed/dark. | E5: P1 | F5: 627x627 PNG source | G5: HUD/button 24-48px; inventory 32-64px; reward/shop card 64-96px; modal 96-128px | H5: icon: 1 PNG | I5: icons/oopsies/ | J5: Audit: tone/effect verification needed; avoid curse wording. | Updated 2026-05-19: non-board visual source supports 627x627 PNG or 1254x1254 2x2 sheets; runtime display is category-constrained. | K5: Comedic festival mishap, not curse/horror.
A6: ☐ | B6: ico_oops_slippery_buttons | C6: icons/oopsies/ | D6: Slippery Buttons Oopsie icon: input delay drawback; slippery button icon. Must feel silly, not cursed/dark. | E6: P1 | F6: 627x627 PNG source | G6: HUD/button 24-48px; inventory 32-64px; reward/shop card 64-96px; modal 96-128px | H6: icon: 1 PNG | I6: icons/oopsies/ | J6: Audit: tone/effect verification needed; avoid curse wording. | Updated 2026-05-19: non-board visual source supports 627x627 PNG or 1254x1254 2x2 sheets; runtime display is category-constrained. | K6: Comedic festival mishap, not curse/horror.
A7: ☐ | B7: ico_oops_too_much_confetti | C7: icons/oopsies/ | D7: Too Much Confetti Oopsie icon: preview flashing drawback; confetti cloud icon. Must feel silly, not cursed/dark. | E7: P1 | F7: 627x627 PNG source | G7: HUD/button 24-48px; inventory 32-64px; reward/shop card 64-96px; modal 96-128px | H7: icon: 1 PNG | I7: icons/oopsies/ | J7: Audit: tone/effect verification needed; avoid curse wording. | Updated 2026-05-19: non-board visual source supports 627x627 PNG or 1254x1254 2x2 sheets; runtime display is category-constrained. | K7: Comedic festival mishap, not curse/horror.
A8: ☐ | B8: ico_oops_snack_tax | C8: icons/oopsies/ | D8: Snack Tax Oopsie icon: shop price drawback; snack coin/tax icon. Must feel silly, not cursed/dark. | E8: P1 | F8: 627x627 PNG source | G8: HUD/button 24-48px; inventory 32-64px; reward/shop card 64-96px; modal 96-128px | H8: icon: 1 PNG | I8: icons/oopsies/ | J8: Audit: tone/effect verification needed; avoid curse wording. | Updated 2026-05-19: non-board visual source supports 627x627 PNG or 1254x1254 2x2 sheets; runtime display is category-constrained. | K8: Comedic festival mishap, not curse/horror.
A9: ☐ | B9: ico_oops_sticky_floor | C9: icons/oopsies/ | D9: Sticky Floor Oopsie icon: more sticky blocks drawback; syrup floor icon. Must feel silly, not cursed/dark. | E9: P1 | F9: 627x627 PNG source | G9: HUD/button 24-48px; inventory 32-64px; reward/shop card 64-96px; modal 96-128px | H9: icon: 1 PNG | I9: icons/oopsies/ | J9: Audit: tone/effect verification needed; avoid curse wording. | Updated 2026-05-19: non-board visual source supports 627x627 PNG or 1254x1254 2x2 sheets; runtime display is category-constrained. | K9: Comedic festival mishap, not curse/horror.
A10: ☐ | B10: ico_oops_overexcited_machine | C10: icons/oopsies/ | D10: Overexcited Machine Oopsie icon: more junk/better rewards drawback; excited machine icon. Must feel silly, not cursed/dark. | E10: P1 | F10: 627x627 PNG source | G10: HUD/button 24-48px; inventory 32-64px; reward/shop card 64-96px; modal 96-128px | H10: icon: 1 PNG | I10: icons/oopsies/ | J10: Audit: tone/effect verification needed; avoid curse wording. | Updated 2026-05-19: non-board visual source supports 627x627 PNG or 1254x1254 2x2 sheets; runtime display is category-constrained. | K10: Comedic festival mishap, not curse/horror.
A11: ☐ | B11: ico_oops_square_only | C11: icons/oopsies/ | D11: Square Only Oopsie icon: pattern challenge drawback; square-only icon. Must feel silly, not cursed/dark. | E11: P1 | F11: 627x627 PNG source | G11: HUD/button 24-48px; inventory 32-64px; reward/shop card 64-96px; modal 96-128px | H11: icon: 1 PNG | I11: icons/oopsies/ | J11: Audit: tone/effect verification needed; avoid curse wording. | Updated 2026-05-19: non-board visual source supports 627x627 PNG or 1254x1254 2x2 sheets; runtime display is category-constrained. | K11: Comedic festival mishap, not curse/horror.
A12: ☐ | B12: ico_oops_sugar_crash | C12: icons/oopsies/ | D12: Sugar Crash Oopsie icon: mana gain drawback after spell spam; broken candy icon. Must feel silly, not cursed/dark. | E12: P1 | F12: 627x627 PNG source | G12: HUD/button 24-48px; inventory 32-64px; reward/shop card 64-96px; modal 96-128px | H12: icon: 1 PNG | I12: icons/oopsies/ | J12: Audit: tone/effect verification needed; avoid curse wording. | Updated 2026-05-19: non-board visual source supports 627x627 PNG or 1254x1254 2x2 sheets; runtime display is category-constrained. | K12: Comedic festival mishap, not curse/horror.

Sheet 26 - Festival Chaos Rules
A1: 26. Icon Assets — Festival Chaos Rules
A2: Tracking sheet generated from the uploaded markdown. Done? is unchecked by default.
A4: Done? | B4: Asset Key | C4: Suggested Folder | D4: Designer Description | E4: Priority | F4: Source / Export Size | G4: Runtime Render Size | H4: Exact Frames / Count | I4: Final Folder Structure (relative to public/assets) | J4: Audit / Release Note | K4: GDD Theme / Prompt Note
A5: ☐ | B5: ico_chaos_sprinkle_storm | C5: icons/events/ | D5: Sprinkle Storm chaos-rule icon: chaos rule with sprinkle rain. | E5: P1 | F5: 627x627 PNG source | G5: HUD/button 24-48px; inventory 32-64px; reward/shop card 64-96px; modal 96-128px | H5: icon: 1 PNG | I5: icons/chaos-rules/ | J5: Audit: chaos effect coverage limited; verify supported effect handlers. | Updated 2026-05-19: non-board visual source supports 627x627 PNG or 1254x1254 2x2 sheets; runtime display is category-constrained. | K5: Temporary funny festival rule with clear visual warning.
A6: ☐ | B6: ico_chaos_wobbly_floor | C6: icons/events/ | D6: Wobbly Floor chaos-rule icon: chaos rule with shaky floor. | E6: P1 | F6: 627x627 PNG source | G6: HUD/button 24-48px; inventory 32-64px; reward/shop card 64-96px; modal 96-128px | H6: icon: 1 PNG | I6: icons/chaos-rules/ | J6: Audit: chaos effect coverage limited; verify supported effect handlers. | Updated 2026-05-19: non-board visual source supports 627x627 PNG or 1254x1254 2x2 sheets; runtime display is category-constrained. | K6: Temporary funny festival rule with clear visual warning.
A7: ☐ | B7: ico_chaos_snack_tax | C7: icons/events/ | D7: Snack Tax chaos-rule icon: chaos rule with temporary shop/economy pressure. | E7: P1 | F7: 627x627 PNG source | G7: HUD/button 24-48px; inventory 32-64px; reward/shop card 64-96px; modal 96-128px | H7: icon: 1 PNG | I7: icons/chaos-rules/ | J7: Audit: chaos effect coverage limited; verify supported effect handlers. | Updated 2026-05-19: non-board visual source supports 627x627 PNG or 1254x1254 2x2 sheets; runtime display is category-constrained. | K7: Temporary funny festival rule with clear visual warning.
A8: ☐ | B8: ico_chaos_confetti_fever | C8: icons/events/ | D8: Confetti Fever chaos-rule icon: chaos rule with party randomness/fever. | E8: P1 | F8: 627x627 PNG source | G8: HUD/button 24-48px; inventory 32-64px; reward/shop card 64-96px; modal 96-128px | H8: icon: 1 PNG | I8: icons/chaos-rules/ | J8: Audit: chaos effect coverage limited; verify supported effect handlers. | Updated 2026-05-19: non-board visual source supports 627x627 PNG or 1254x1254 2x2 sheets; runtime display is category-constrained. | K8: Temporary funny festival rule with clear visual warning.
A9: ☐ | B9: ico_chaos_goblin_safety_test | C9: icons/events/ | D9: Goblin Safety Test chaos-rule icon: chaos rule with questionable workshop hazard. | E9: P1 | F9: 627x627 PNG source | G9: HUD/button 24-48px; inventory 32-64px; reward/shop card 64-96px; modal 96-128px | H9: icon: 1 PNG | I9: icons/chaos-rules/ | J9: Audit: chaos effect coverage limited; verify supported effect handlers. | Updated 2026-05-19: non-board visual source supports 627x627 PNG or 1254x1254 2x2 sheets; runtime display is category-constrained. | K9: Temporary funny festival rule with clear visual warning.
A10: ☐ | B10: ico_chaos_freezer_draft | C10: icons/events/ | D10: Freezer Draft chaos-rule icon: chaos rule with cold/freeze pressure. | E10: P1 | F10: 627x627 PNG source | G10: HUD/button 24-48px; inventory 32-64px; reward/shop card 64-96px; modal 96-128px | H10: icon: 1 PNG | I10: icons/chaos-rules/ | J10: Audit: chaos effect coverage limited; verify supported effect handlers. | Updated 2026-05-19: non-board visual source supports 627x627 PNG or 1254x1254 2x2 sheets; runtime display is category-constrained. | K10: Temporary funny festival rule with clear visual warning.
A11: ☐ | B11: ico_chaos_royal_inspection | C11: icons/events/ | D11: Royal Inspection chaos-rule icon: chaos rule with Bloxley pattern/symmetry pressure. | E11: P1 | F11: 627x627 PNG source | G11: HUD/button 24-48px; inventory 32-64px; reward/shop card 64-96px; modal 96-128px | H11: icon: 1 PNG | I11: icons/chaos-rules/ | J11: Audit: chaos effect coverage limited; verify supported effect handlers. | Updated 2026-05-19: non-board visual source supports 627x627 PNG or 1254x1254 2x2 sheets; runtime display is category-constrained. | K11: Temporary funny festival rule with clear visual warning.
A12: ☐ | B12: ico_chaos_jelly_bounce | C12: icons/events/ | D12: Jelly Bounce chaos-rule icon: chaos rule with wobbly/jelly block movement. | E12: P1 | F12: 627x627 PNG source | G12: HUD/button 24-48px; inventory 32-64px; reward/shop card 64-96px; modal 96-128px | H12: icon: 1 PNG | I12: icons/chaos-rules/ | J12: Audit: chaos effect coverage limited; verify supported effect handlers. | Updated 2026-05-19: non-board visual source supports 627x627 PNG or 1254x1254 2x2 sheets; runtime display is category-constrained. | K12: Temporary funny festival rule with clear visual warning.

Sheet 27 - Battle Objectives
A1: 27. Icon Assets — Battle Objectives
A2: Tracking sheet generated from the uploaded markdown. Done? is unchecked by default.
A4: Done? | B4: Asset Key | C4: Suggested Folder | D4: Designer Description | E4: Priority | F4: Source / Export Size | G4: Runtime Render Size | H4: Exact Frames / Count | I4: Final Folder Structure (relative to public/assets) | J4: Audit / Release Note | K4: GDD Theme / Prompt Note
A5: ☐ | B5: ico_obj_trigger_cascade | C5: icons/objectives/ | D5: Trigger Cascade: mini-objective icon for making at least one cascade. | E5: P1 | F5: 627x627 PNG source | G5: HUD/button 24-48px; inventory 32-64px; reward/shop card 64-96px; modal 96-128px | H5: icon: 1 PNG | I5: icons/battle-objectives/ | J5: Audit: objective checks improved but need deterministic tests. | Updated 2026-05-19: non-board visual source supports 627x627 PNG or 1254x1254 2x2 sheets; runtime display is category-constrained. | K5: Small challenge marker: cascade, hold, spell, fever, low board, no spell.
A6: ☐ | B6: ico_obj_clear_two_lines | C6: icons/objectives/ | D6: Clear Two Lines: mini-objective icon for clearing two lines at once. | E6: P1 | F6: 627x627 PNG source | G6: HUD/button 24-48px; inventory 32-64px; reward/shop card 64-96px; modal 96-128px | H6: icon: 1 PNG | I6: icons/battle-objectives/ | J6: Audit: objective checks improved but need deterministic tests. | Updated 2026-05-19: non-board visual source supports 627x627 PNG or 1254x1254 2x2 sheets; runtime display is category-constrained. | K6: Small challenge marker: cascade, hold, spell, fever, low board, no spell.
A7: ☐ | B7: ico_obj_clear_sprinkles | C7: icons/objectives/ | D7: Clear Sprinkles: mini-objective icon for clearing sprinkle blocks. | E7: P1 | F7: 627x627 PNG source | G7: HUD/button 24-48px; inventory 32-64px; reward/shop card 64-96px; modal 96-128px | H7: icon: 1 PNG | I7: icons/battle-objectives/ | J7: Audit: objective checks improved but need deterministic tests. | Updated 2026-05-19: non-board visual source supports 627x627 PNG or 1254x1254 2x2 sheets; runtime display is category-constrained. | K7: Small challenge marker: cascade, hold, spell, fever, low board, no spell.
A8: ☐ | B8: ico_obj_destroy_junk | C8: icons/objectives/ | D8: Destroy Junk: mini-objective icon for cleaning all junk. | E8: P1 | F8: 627x627 PNG source | G8: HUD/button 24-48px; inventory 32-64px; reward/shop card 64-96px; modal 96-128px | H8: icon: 1 PNG | I8: icons/battle-objectives/ | J8: Audit: objective checks improved but need deterministic tests. | Updated 2026-05-19: non-board visual source supports 627x627 PNG or 1254x1254 2x2 sheets; runtime display is category-constrained. | K8: Small challenge marker: cascade, hold, spell, fever, low board, no spell.
A9: ☐ | B9: ico_obj_no_spell_win | C9: icons/objectives/ | D9: No Spell Win: mini-objective icon for winning without spells. | E9: P1 | F9: 627x627 PNG source | G9: HUD/button 24-48px; inventory 32-64px; reward/shop card 64-96px; modal 96-128px | H9: icon: 1 PNG | I9: icons/battle-objectives/ | J9: Audit: objective checks improved but need deterministic tests. | Updated 2026-05-19: non-board visual source supports 627x627 PNG or 1254x1254 2x2 sheets; runtime display is category-constrained. | K9: Small challenge marker: cascade, hold, spell, fever, low board, no spell.
A10: ☐ | B10: ico_obj_fast_win | C10: icons/objectives/ | D10: Fast Win: mini-objective icon for winning before enemy acts several times. | E10: P1 | F10: 627x627 PNG source | G10: HUD/button 24-48px; inventory 32-64px; reward/shop card 64-96px; modal 96-128px | H10: icon: 1 PNG | I10: icons/battle-objectives/ | J10: Audit: objective checks improved but need deterministic tests. | Updated 2026-05-19: non-board visual source supports 627x627 PNG or 1254x1254 2x2 sheets; runtime display is category-constrained. | K10: Small challenge marker: cascade, hold, spell, fever, low board, no spell.
A11: ☐ | B11: ico_obj_use_hold | C11: icons/objectives/ | D11: Use Hold: mini-objective icon for using hold piece. | E11: P1 | F11: 627x627 PNG source | G11: HUD/button 24-48px; inventory 32-64px; reward/shop card 64-96px; modal 96-128px | H11: icon: 1 PNG | I11: icons/battle-objectives/ | J11: Audit: objective checks improved but need deterministic tests. | Updated 2026-05-19: non-board visual source supports 627x627 PNG or 1254x1254 2x2 sheets; runtime display is category-constrained. | K11: Small challenge marker: cascade, hold, spell, fever, low board, no spell.
A12: ☐ | B12: ico_obj_cast_two_spells | C12: icons/objectives/ | D12: Cast Two Spells: mini-objective icon for casting two spells. | E12: P1 | F12: 627x627 PNG source | G12: HUD/button 24-48px; inventory 32-64px; reward/shop card 64-96px; modal 96-128px | H12: icon: 1 PNG | I12: icons/battle-objectives/ | J12: Audit: objective checks improved but need deterministic tests. | Updated 2026-05-19: non-board visual source supports 627x627 PNG or 1254x1254 2x2 sheets; runtime display is category-constrained. | K12: Small challenge marker: cascade, hold, spell, fever, low board, no spell.
A13: ☐ | B13: ico_obj_low_board | C13: icons/objectives/ | D13: Low Board: mini-objective icon for keeping board height low. | E13: P1 | F13: 627x627 PNG source | G13: HUD/button 24-48px; inventory 32-64px; reward/shop card 64-96px; modal 96-128px | H13: icon: 1 PNG | I13: icons/battle-objectives/ | J13: Audit: objective checks improved but need deterministic tests. | Updated 2026-05-19: non-board visual source supports 627x627 PNG or 1254x1254 2x2 sheets; runtime display is category-constrained. | K13: Small challenge marker: cascade, hold, spell, fever, low board, no spell.
A14: ☐ | B14: ico_obj_trigger_fever | C14: icons/objectives/ | D14: Trigger Fever: mini-objective icon for activating fever. | E14: P1 | F14: 627x627 PNG source | G14: HUD/button 24-48px; inventory 32-64px; reward/shop card 64-96px; modal 96-128px | H14: icon: 1 PNG | I14: icons/battle-objectives/ | J14: Audit: objective checks improved but need deterministic tests. | Updated 2026-05-19: non-board visual source supports 627x627 PNG or 1254x1254 2x2 sheets; runtime display is category-constrained. | K14: Small challenge marker: cascade, hold, spell, fever, low board, no spell.

Sheet 28 - Events
A1: 28. Icon Assets — Room Events and Random Gameplay Events
A2: Tracking sheet generated from the uploaded markdown. Done? is unchecked by default.
A4: Done? | B4: Asset Key | C4: Suggested Folder | D4: Designer Description | E4: Priority | F4: Source / Export Size | G4: Runtime Render Size | H4: Exact Frames / Count | I4: Final Folder Structure (relative to public/assets) | J4: Audit / Release Note | K4: GDD Theme / Prompt Note
A5: ☐ | B5: ico_evt_suspicious_button | C5: icons/events/ | D5: Suspicious Button: event icon: big red button with warning label. | E5: P1 | F5: 627x627 PNG source | G5: HUD/button 24-48px; inventory 32-64px; reward/shop card 64-96px; modal 96-128px | H5: Static unless event card animation exists | I5: icons/events/ | J5: Audit: event effects are switch-limited; avoid no-op visual promises. | Updated 2026-05-19: non-board visual source supports 627x627 PNG or 1254x1254 2x2 sheets; runtime display is category-constrained. | K5: Funny festival room-event visual with clear safe/risky choice tone.
A6: ☐ | B6: ico_evt_lost_cake_cart | C6: icons/events/ | D6: Lost Cake Cart: event icon: cake cart with missing snacks. | E6: P1 | F6: 627x627 PNG source | G6: HUD/button 24-48px; inventory 32-64px; reward/shop card 64-96px; modal 96-128px | H6: Static unless event card animation exists | I6: icons/events/ | J6: Audit: event effects are switch-limited; avoid no-op visual promises. | Updated 2026-05-19: non-board visual source supports 627x627 PNG or 1254x1254 2x2 sheets; runtime display is category-constrained. | K6: Funny festival room-event visual with clear safe/risky choice tone.
A7: ☐ | B7: ico_evt_goblin_quality_test | C7: icons/events/ | D7: Goblin Quality Test: event icon: goblin gadget test clipboard. | E7: P1 | F7: 627x627 PNG source | G7: HUD/button 24-48px; inventory 32-64px; reward/shop card 64-96px; modal 96-128px | H7: Static unless event card animation exists | I7: icons/events/ | J7: Audit: event effects are switch-limited; avoid no-op visual promises. | Updated 2026-05-19: non-board visual source supports 627x627 PNG or 1254x1254 2x2 sheets; runtime display is category-constrained. | K7: Funny festival room-event visual with clear safe/risky choice tone.
A8: ☐ | B8: ico_evt_rainbow_fountain | C8: icons/events/ | D8: Rainbow Fountain: event icon: rainbow fountain with magic water. | E8: P1 | F8: 627x627 PNG source | G8: HUD/button 24-48px; inventory 32-64px; reward/shop card 64-96px; modal 96-128px | H8: Static unless event card animation exists | I8: icons/events/ | J8: Audit: event effects are switch-limited; avoid no-op visual promises. | Updated 2026-05-19: non-board visual source supports 627x627 PNG or 1254x1254 2x2 sheets; runtime display is category-constrained. | K8: Funny festival room-event visual with clear safe/risky choice tone.
A9: ☐ | B9: ico_evt_sleepy_guard | C9: icons/events/ | D9: Sleepy Guard: event icon: guard sleeping by key. | E9: P1 | F9: 627x627 PNG source | G9: HUD/button 24-48px; inventory 32-64px; reward/shop card 64-96px; modal 96-128px | H9: Static unless event card animation exists | I9: icons/events/ | J9: Audit: event effects are switch-limited; avoid no-op visual promises. | Updated 2026-05-19: non-board visual source supports 627x627 PNG or 1254x1254 2x2 sheets; runtime display is category-constrained. | K9: Funny festival room-event visual with clear safe/risky choice tone.
A10: ☐ | B10: ico_evt_arcade_challenge | C10: icons/events/ | D10: Arcade Challenge: event icon: arcade cabinet/ticket. | E10: P1 | F10: 627x627 PNG source | G10: HUD/button 24-48px; inventory 32-64px; reward/shop card 64-96px; modal 96-128px | H10: Static unless event card animation exists | I10: icons/events/ | J10: Audit: event effects are switch-limited; avoid no-op visual promises. | Updated 2026-05-19: non-board visual source supports 627x627 PNG or 1254x1254 2x2 sheets; runtime display is category-constrained. | K10: Funny festival room-event visual with clear safe/risky choice tone.
A11: ☐ | B11: ico_evt_block_o_manual_page | C11: icons/events/ | D11: Manual Page: event icon: Block-O-Matic manual page. | E11: P1 | F11: 627x627 PNG source | G11: HUD/button 24-48px; inventory 32-64px; reward/shop card 64-96px; modal 96-128px | H11: Static unless event card animation exists | I11: icons/events/ | J11: Audit: event effects are switch-limited; avoid no-op visual promises. | Updated 2026-05-19: non-board visual source supports 627x627 PNG or 1254x1254 2x2 sheets; runtime display is category-constrained. | K11: Funny festival room-event visual with clear safe/risky choice tone.
A12: ☐ | B12: ico_evt_friendship_slime | C12: icons/events/ | D12: Friendship Slime: event icon: friendly slime with snack. | E12: P1 | F12: 627x627 PNG source | G12: HUD/button 24-48px; inventory 32-64px; reward/shop card 64-96px; modal 96-128px | H12: Static unless event card animation exists | I12: icons/events/ | J12: Audit: event effects are switch-limited; avoid no-op visual promises. | Updated 2026-05-19: non-board visual source supports 627x627 PNG or 1254x1254 2x2 sheets; runtime display is category-constrained. | K12: Funny festival room-event visual with clear safe/risky choice tone.
A13: ☐ | B13: ico_r_evt_jelly_surge | C13: icons/events/ | D13: Jelly Surge: random battle event icon: wobbly jelly burst. | E13: P1 | F13: 627x627 PNG source | G13: HUD/button 24-48px; inventory 32-64px; reward/shop card 64-96px; modal 96-128px | H13: Static unless event card animation exists | I13: icons/events/ | J13: Audit: event effects are switch-limited; avoid no-op visual promises. | Updated 2026-05-19: non-board visual source supports 627x627 PNG or 1254x1254 2x2 sheets; runtime display is category-constrained. | K13: Funny festival room-event visual with clear safe/risky choice tone.
A14: ☐ | B14: ico_r_evt_sprinkle_rain | C14: icons/events/ | D14: Sprinkle Rain: random battle event icon: sprinkles falling. | E14: P1 | F14: 627x627 PNG source | G14: HUD/button 24-48px; inventory 32-64px; reward/shop card 64-96px; modal 96-128px | H14: Static unless event card animation exists | I14: icons/events/ | J14: Audit: event effects are switch-limited; avoid no-op visual promises. | Updated 2026-05-19: non-board visual source supports 627x627 PNG or 1254x1254 2x2 sheets; runtime display is category-constrained. | K14: Funny festival room-event visual with clear safe/risky choice tone.
A15: ☐ | B15: ico_r_evt_sticky_spill | C15: icons/events/ | D15: Sticky Spill: random battle event icon: syrup spill. | E15: P1 | F15: 627x627 PNG source | G15: HUD/button 24-48px; inventory 32-64px; reward/shop card 64-96px; modal 96-128px | H15: Static unless event card animation exists | I15: icons/events/ | J15: Audit: event effects are switch-limited; avoid no-op visual promises. | Updated 2026-05-19: non-board visual source supports 627x627 PNG or 1254x1254 2x2 sheets; runtime display is category-constrained. | K15: Funny festival room-event visual with clear safe/risky choice tone.
... A32: ☐ | B32: ico_r_evt_machine_hiccup | C32: icons/events/ | D32: Machine Hiccup: random battle event icon: hiccuping machine. | E32: P1 | F32: 627x627 PNG source | G32: HUD/button 24-48px; inventory 32-64px; reward/shop card 64-96px; modal 96-128px | H32: Static unless event card animation exists | I32: icons/events/ | J32: Audit: event effects are switch-limited; avoid no-op visual promises. | Updated 2026-05-19: non-board visual source supports 627x627 PNG or 1254x1254 2x2 sheets; runtime display is category-constrained. | K32: Funny festival room-event visual with clear safe/risky choice tone.

Sheet 29 - Boss Rule Cards
A1: 29. Icon Assets — Boss Rule Cards
A2: Tracking sheet generated from the uploaded markdown. Done? is unchecked by default.
A4: Done? | B4: Asset Key | C4: Suggested Folder | D4: Designer Description | E4: Priority | F4: Source / Export Size | G4: Runtime Render Size | H4: Exact Frames / Count | I4: Final Folder Structure (relative to public/assets) | J4: Audit / Release Note | K4: GDD Theme / Prompt Note
A5: ☐ | B5: ico_boss_rule_boss_cupcake_slime_king | C5: icons/boss-rules/ | D5: Rule-card icon for Cupcake Slime King; represent the boss mechanic in one clear symbol. | E5: P1 | F5: 627x627 PNG source | G5: HUD/button 24-48px; inventory 32-64px; reward/shop card 64-96px; modal 96-128px | H5: Boss standard: idle 6, attack 8, hit 4, phase_change 8, special_attack 8, defeat 10, portrait_icon 1 | I5: icons/bosses/ | J5: Audit: boss mechanics and boss rule visuals need visible verification; import final frames. | Updated 2026-05-19: non-board visual source supports 627x627 PNG or 1254x1254 2x2 sheets; runtime display is category-constrained. | K5: Readable funny boss identity with stage mechanics: sticky, gadget, frost, sleepy, arcade, or royal.
A6: ☐ | B6: ico_boss_rule_boss_prototype_no_7 | C6: icons/boss-rules/ | D6: Rule-card icon for Prototype No. 7; represent the boss mechanic in one clear symbol. | E6: P1 | F6: 627x627 PNG source | G6: HUD/button 24-48px; inventory 32-64px; reward/shop card 64-96px; modal 96-128px | H6: Boss standard: idle 6, attack 8, hit 4, phase_change 8, special_attack 8, defeat 10, portrait_icon 1 | I6: icons/bosses/ | J6: Audit: boss mechanics and boss rule visuals need visible verification; import final frames. | Updated 2026-05-19: non-board visual source supports 627x627 PNG or 1254x1254 2x2 sheets; runtime display is category-constrained. | K6: Readable funny boss identity with stage mechanics: sticky, gadget, frost, sleepy, arcade, or royal.
A7: ☐ | B7: ico_boss_rule_boss_gelato_golem | C7: icons/boss-rules/ | D7: Rule-card icon for Gelato Golem; represent the boss mechanic in one clear symbol. | E7: P1 | F7: 627x627 PNG source | G7: HUD/button 24-48px; inventory 32-64px; reward/shop card 64-96px; modal 96-128px | H7: Boss standard: idle 6, attack 8, hit 4, phase_change 8, special_attack 8, defeat 10, portrait_icon 1 | I7: icons/bosses/ | J7: Audit: boss mechanics and boss rule visuals need visible verification; import final frames. | Updated 2026-05-19: non-board visual source supports 627x627 PNG or 1254x1254 2x2 sheets; runtime display is category-constrained. | K7: Readable funny boss identity with stage mechanics: sticky, gadget, frost, sleepy, arcade, or royal.
A8: ☐ | B8: ico_boss_rule_boss_sir_snore_a_lot | C8: icons/boss-rules/ | D8: Rule-card icon for Sir Snore-a-Lot; represent the boss mechanic in one clear symbol. | E8: P1 | F8: 627x627 PNG source | G8: HUD/button 24-48px; inventory 32-64px; reward/shop card 64-96px; modal 96-128px | H8: Boss standard: idle 6, attack 8, hit 4, phase_change 8, special_attack 8, defeat 10, portrait_icon 1 | I8: icons/bosses/ | J8: Audit: boss mechanics and boss rule visuals need visible verification; import final frames. | Updated 2026-05-19: non-board visual source supports 627x627 PNG or 1254x1254 2x2 sheets; runtime display is category-constrained. | K8: Readable funny boss identity with stage mechanics: sticky, gadget, frost, sleepy, arcade, or royal.
A9: ☐ | B9: ico_boss_rule_boss_high_score_hydra | C9: icons/boss-rules/ | D9: Rule-card icon for High Score Hydra; represent the boss mechanic in one clear symbol. | E9: P1 | F9: 627x627 PNG source | G9: HUD/button 24-48px; inventory 32-64px; reward/shop card 64-96px; modal 96-128px | H9: Boss standard: idle 6, attack 8, hit 4, phase_change 8, special_attack 8, defeat 10, portrait_icon 1 | I9: icons/bosses/ | J9: Audit: boss mechanics and boss rule visuals need visible verification; import final frames. | Updated 2026-05-19: non-board visual source supports 627x627 PNG or 1254x1254 2x2 sheets; runtime display is category-constrained. | K9: Readable funny boss identity with stage mechanics: sticky, gadget, frost, sleepy, arcade, or royal.
A10: ☐ | B10: ico_boss_rule_boss_king_bloxley | C10: icons/boss-rules/ | D10: Rule-card icon for King Bloxley; represent the boss mechanic in one clear symbol. | E10: P1 | F10: 627x627 PNG source | G10: HUD/button 24-48px; inventory 32-64px; reward/shop card 64-96px; modal 96-128px | H10: Boss standard: idle 6, attack 8, hit 4, phase_change 8, special_attack 8, defeat 10, portrait_icon 1 | I10: icons/bosses/ | J10: Audit: boss mechanics and boss rule visuals need visible verification; import final frames. | Updated 2026-05-19: non-board visual source supports 627x627 PNG or 1254x1254 2x2 sheets; runtime display is category-constrained. | K10: Readable funny boss identity with stage mechanics: sticky, gadget, frost, sleepy, arcade, or royal.

Sheet 30 - Currency Collect
A1: 30. Icon Assets — Currencies and Collectibles
A2: Tracking sheet generated from the uploaded markdown. Done? is unchecked by default.
A4: Done? | B4: Asset Key | C4: Suggested Folder | D4: Designer Description | E4: Priority | F4: Source / Export Size | G4: Runtime Render Size | H4: Exact Frames / Count | I4: Final Folder Structure (relative to public/assets) | J4: Audit / Release Note | K4: GDD Theme / Prompt Note
A5: ☐ | B5: ico_currency_gold | C5: icons/currencies/ | D5: Gold currency icon: main shop currency; coin icon with cheerful shine. | E5: P0 | F5: 627x627 PNG source | G5: HUD/button 24-48px; inventory 32-64px; reward/shop card 64-96px; modal 96-128px | H5: icon: 1 PNG | I5: icons/currencies/ | J5: Audit: meta/hub progression mostly placeholder; icons still needed. | Updated 2026-05-19: non-board visual source supports 627x627 PNG or 1254x1254 2x2 sheets; runtime display is category-constrained. | K5: Festival currency/collectible: gold, sprinkles, tickets, stars, cakes, manual pages.
A6: ☐ | B6: ico_currency_sprinkles | C6: icons/currencies/ | D6: Sprinkles currency icon: upgrade/cosmetic currency; candy sprinkles icon. | E6: P1 | F6: 627x627 PNG source | G6: HUD/button 24-48px; inventory 32-64px; reward/shop card 64-96px; modal 96-128px | H6: icon: 1 PNG | I6: icons/currencies/ | J6: Audit: meta/hub progression mostly placeholder; icons still needed. | Updated 2026-05-19: non-board visual source supports 627x627 PNG or 1254x1254 2x2 sheets; runtime display is category-constrained. | K6: Festival currency/collectible: gold, sprinkles, tickets, stars, cakes, manual pages.
A7: ☐ | B7: ico_currency_tickets | C7: icons/currencies/ | D7: Festival Tickets currency icon: meta unlock/arcade currency; ticket icon. | E7: P1 | F7: 627x627 PNG source | G7: HUD/button 24-48px; inventory 32-64px; reward/shop card 64-96px; modal 96-128px | H7: icon: 1 PNG | I7: icons/currencies/ | J7: Audit: meta/hub progression mostly placeholder; icons still needed. | Updated 2026-05-19: non-board visual source supports 627x627 PNG or 1254x1254 2x2 sheets; runtime display is category-constrained. | K7: Festival currency/collectible: gold, sprinkles, tickets, stars, cakes, manual pages.
A8: ☐ | B8: ico_currency_stars | C8: icons/currencies/ | D8: Star Tokens currency icon: rare unlock currency; star token icon. | E8: P1 | F8: 627x627 PNG source | G8: HUD/button 24-48px; inventory 32-64px; reward/shop card 64-96px; modal 96-128px | H8: icon: 1 PNG | I8: icons/currencies/ | J8: Audit: meta/hub progression mostly placeholder; icons still needed. | Updated 2026-05-19: non-board visual source supports 627x627 PNG or 1254x1254 2x2 sheets; runtime display is category-constrained. | K8: Festival currency/collectible: gold, sprinkles, tickets, stars, cakes, manual pages.
A9: ☐ | B9: ico_collectible_lost_cake | C9: icons/collectibles/ | D9: Lost Cake collectible icon: true-ending cake collectible; small rescued cake icon. | E9: P1 | F9: 627x627 PNG source | G9: HUD/button 24-48px; inventory 32-64px; reward/shop card 64-96px; modal 96-128px | H9: icon: 1 PNG | I9: icons/currencies/ | J9: Audit: meta/hub progression mostly placeholder; icons still needed. | Updated 2026-05-19: non-board visual source supports 627x627 PNG or 1254x1254 2x2 sheets; runtime display is category-constrained. | K9: Festival currency/collectible: gold, sprinkles, tickets, stars, cakes, manual pages.
A10: ☐ | B10: ico_collectible_manual_page | C10: icons/collectibles/ | D10: Manual Page collectible icon: tutorial/lore collectible; paper page icon. | E10: P1 | F10: 627x627 PNG source | G10: HUD/button 24-48px; inventory 32-64px; reward/shop card 64-96px; modal 96-128px | H10: icon: 1 PNG | I10: icons/currencies/ | J10: Audit: meta/hub progression mostly placeholder; icons still needed. | Updated 2026-05-19: non-board visual source supports 627x627 PNG or 1254x1254 2x2 sheets; runtime display is category-constrained. | K10: Festival currency/collectible: gold, sprinkles, tickets, stars, cakes, manual pages.
A11: ☐ | B11: ico_collectible_friendship_badge | C11: icons/collectibles/ | D11: Friendship Badge collectible icon: monster friendship collectible; badge/heart icon. | E11: P1 | F11: 627x627 PNG source | G11: HUD/button 24-48px; inventory 32-64px; reward/shop card 64-96px; modal 96-128px | H11: icon: 1 PNG | I11: icons/currencies/ | J11: Audit: meta/hub progression mostly placeholder; icons still needed. | Updated 2026-05-19: non-board visual source supports 627x627 PNG or 1254x1254 2x2 sheets; runtime display is category-constrained. | K11: Festival currency/collectible: gold, sprinkles, tickets, stars, cakes, manual pages.
A12: ☐ | B12: ico_collectible_arcade_token | C12: icons/collectibles/ | D12: Arcade Token collectible icon: arcade collectible; neon token icon. | E12: P1 | F12: 627x627 PNG source | G12: HUD/button 24-48px; inventory 32-64px; reward/shop card 64-96px; modal 96-128px | H12: icon: 1 PNG | I12: icons/currencies/ | J12: Audit: meta/hub progression mostly placeholder; icons still needed. | Updated 2026-05-19: non-board visual source supports 627x627 PNG or 1254x1254 2x2 sheets; runtime display is category-constrained. | K12: Festival currency/collectible: gold, sprinkles, tickets, stars, cakes, manual pages.

Sheet 31 and - Hub Buildings
A1: 31. Sprite and Icon Assets — Festival Hub Buildings
A2: Tracking sheet generated from the uploaded markdown. Done? is unchecked by default.
A4: Done? | B4: Asset Key | C4: Suggested Folder | D4: Designer Description | E4: Priority | F4: Source / Export Size | G4: Runtime Render Size | H4: Exact Frames / Count | I4: Final Folder Structure (relative to public/assets) | J4: Audit / Release Note | K4: GDD Theme / Prompt Note
A5: ☐ | B5: spr_hub_cake_stall_level_0 | C5: sprites/hub/ | D5: Cake Stall building level 0; show visible upgrade progression. Direction: festival booth for cake restoration/progression. | E5: P2 | F5: 627x627 PNG source for UI icons/badges; 627x627 frames for UI animations | G5: Small UI 24-48px; button emblem 32-64px; badge 64-128px; celebration 160-220px | H5: Static or upgrade-level variants | I5: sprites/hub-buildings/ | J5: Audit: hub progression is placeholder; one complete upgrade loop needed later. | Updated 2026-05-19: non-board visual source supports 627x627 PNG or 1254x1254 2x2 sheets; runtime display is category-constrained. | K5: Restored festival booth/building, cozy and colorful.
A6: ☐ | B6: spr_hub_cake_stall_level_1 | C6: sprites/hub/ | D6: Cake Stall building level 1; show visible upgrade progression. Direction: festival booth for cake restoration/progression. | E6: P2 | F6: 627x627 PNG source for UI icons/badges; 627x627 frames for UI animations | G6: Small UI 24-48px; button emblem 32-64px; badge 64-128px; celebration 160-220px | H6: Static or upgrade-level variants | I6: sprites/hub-buildings/ | J6: Audit: hub progression is placeholder; one complete upgrade loop needed later. | Updated 2026-05-19: non-board visual source supports 627x627 PNG or 1254x1254 2x2 sheets; runtime display is category-constrained. | K6: Restored festival booth/building, cozy and colorful.
A7: ☐ | B7: spr_hub_cake_stall_level_2 | C7: sprites/hub/ | D7: Cake Stall building level 2; show visible upgrade progression. Direction: festival booth for cake restoration/progression. | E7: P2 | F7: 627x627 PNG source for UI icons/badges; 627x627 frames for UI animations | G7: Small UI 24-48px; button emblem 32-64px; badge 64-128px; celebration 160-220px | H7: Static or upgrade-level variants | I7: sprites/hub-buildings/ | J7: Audit: hub progression is placeholder; one complete upgrade loop needed later. | Updated 2026-05-19: non-board visual source supports 627x627 PNG or 1254x1254 2x2 sheets; runtime display is category-constrained. | K7: Restored festival booth/building, cozy and colorful.
A8: ☐ | B8: spr_hub_cake_stall_level_3 | C8: sprites/hub/ | D8: Cake Stall building level 3; show visible upgrade progression. Direction: festival booth for cake restoration/progression. | E8: P2 | F8: 627x627 PNG source for UI icons/badges; 627x627 frames for UI animations | G8: Small UI 24-48px; button emblem 32-64px; badge 64-128px; celebration 160-220px | H8: Static or upgrade-level variants | I8: sprites/hub-buildings/ | J8: Audit: hub progression is placeholder; one complete upgrade loop needed later. | Updated 2026-05-19: non-board visual source supports 627x627 PNG or 1254x1254 2x2 sheets; runtime display is category-constrained. | K8: Restored festival booth/building, cozy and colorful.
A9: ☐ | B9: ico_hub_cake_stall | C9: icons/hub/ | D9: Cake Stall hub icon for menu/building upgrade UI. | E9: P2 | F9: 627x627 PNG source | G9: HUD/button 24-48px; inventory 32-64px; reward/shop card 64-96px; modal 96-128px | H9: Static or upgrade-level variants | I9: sprites/hub-buildings/ | J9: Audit: hub progression is placeholder; one complete upgrade loop needed later. | Updated 2026-05-19: non-board visual source supports 627x627 PNG or 1254x1254 2x2 sheets; runtime display is category-constrained. | K9: Restored festival booth/building, cozy and colorful.
A10: ☐ | B10: spr_hub_ice_cream_cart_level_0 | C10: sprites/hub/ | D10: Ice Cream Cart building level 0; show visible upgrade progression. Direction: Nixie-style cart for frost/heal upgrades. | E10: P2 | F10: 627x627 PNG source for UI icons/badges; 627x627 frames for UI animations | G10: Small UI 24-48px; button emblem 32-64px; badge 64-128px; celebration 160-220px | H10: Static or upgrade-level variants | I10: sprites/hub-buildings/ | J10: Audit: hub progression is placeholder; one complete upgrade loop needed later. | Updated 2026-05-19: non-board visual source supports 627x627 PNG or 1254x1254 2x2 sheets; runtime display is category-constrained. | K10: Restored festival booth/building, cozy and colorful.
A11: ☐ | B11: spr_hub_ice_cream_cart_level_1 | C11: sprites/hub/ | D11: Ice Cream Cart building level 1; show visible upgrade progression. Direction: Nixie-style cart for frost/heal upgrades. | E11: P2 | F11: 627x627 PNG source for UI icons/badges; 627x627 frames for UI animations | G11: Small UI 24-48px; button emblem 32-64px; badge 64-128px; celebration 160-220px | H11: Static or upgrade-level variants | I11: sprites/hub-buildings/ | J11: Audit: hub progression is placeholder; one complete upgrade loop needed later. | Updated 2026-05-19: non-board visual source supports 627x627 PNG or 1254x1254 2x2 sheets; runtime display is category-constrained. | K11: Restored festival booth/building, cozy and colorful.
A12: ☐ | B12: spr_hub_ice_cream_cart_level_2 | C12: sprites/hub/ | D12: Ice Cream Cart building level 2; show visible upgrade progression. Direction: Nixie-style cart for frost/heal upgrades. | E12: P2 | F12: 627x627 PNG source for UI icons/badges; 627x627 frames for UI animations | G12: Small UI 24-48px; button emblem 32-64px; badge 64-128px; celebration 160-220px | H12: Static or upgrade-level variants | I12: sprites/hub-buildings/ | J12: Audit: hub progression is placeholder; one complete upgrade loop needed later. | Updated 2026-05-19: non-board visual source supports 627x627 PNG or 1254x1254 2x2 sheets; runtime display is category-constrained. | K12: Restored festival booth/building, cozy and colorful.
A13: ☐ | B13: spr_hub_ice_cream_cart_level_3 | C13: sprites/hub/ | D13: Ice Cream Cart building level 3; show visible upgrade progression. Direction: Nixie-style cart for frost/heal upgrades. | E13: P2 | F13: 627x627 PNG source for UI icons/badges; 627x627 frames for UI animations | G13: Small UI 24-48px; button emblem 32-64px; badge 64-128px; celebration 160-220px | H13: Static or upgrade-level variants | I13: sprites/hub-buildings/ | J13: Audit: hub progression is placeholder; one complete upgrade loop needed later. | Updated 2026-05-19: non-board visual source supports 627x627 PNG or 1254x1254 2x2 sheets; runtime display is category-constrained. | K13: Restored festival booth/building, cozy and colorful.
A14: ☐ | B14: ico_hub_ice_cream_cart | C14: icons/hub/ | D14: Ice Cream Cart hub icon for menu/building upgrade UI. | E14: P2 | F14: 627x627 PNG source | G14: HUD/button 24-48px; inventory 32-64px; reward/shop card 64-96px; modal 96-128px | H14: Static or upgrade-level variants | I14: sprites/hub-buildings/ | J14: Audit: hub progression is placeholder; one complete upgrade loop needed later. | Updated 2026-05-19: non-board visual source supports 627x627 PNG or 1254x1254 2x2 sheets; runtime display is category-constrained. | K14: Restored festival booth/building, cozy and colorful.
A15: ☐ | B15: spr_hub_goblin_workshop_level_0 | C15: sprites/hub/ | D15: Goblin Workshop building level 0; show visible upgrade progression. Direction: gadget booth with tools and machines. | E15: P2 | F15: 627x627 PNG source for UI icons/badges; 627x627 frames for UI animations | G15: Small UI 24-48px; button emblem 32-64px; badge 64-128px; celebration 160-220px | H15: Static or upgrade-level variants | I15: sprites/hub-buildings/ | J15: Audit: hub progression is placeholder; one complete upgrade loop needed later. | Updated 2026-05-19: non-board visual source supports 627x627 PNG or 1254x1254 2x2 sheets; runtime display is category-constrained. | K15: Restored festival booth/building, cozy and colorful.
... A44: ☐ | B44: ico_hub_bloxley_statue | C44: icons/hub/ | D44: Bloxley Statue hub icon for menu/building upgrade UI. | E44: P2 | F44: 627x627 PNG source | G44: HUD/button 24-48px; inventory 32-64px; reward/shop card 64-96px; modal 96-128px | H44: Static or upgrade-level variants | I44: sprites/hub-buildings/ | J44: Audit: hub progression is placeholder; one complete upgrade loop needed later. | Updated 2026-05-19: non-board visual source supports 627x627 PNG or 1254x1254 2x2 sheets; runtime display is category-constrained. | K44: Restored festival booth/building, cozy and colorful.

Sheet 32 UI - Panels Frames
A1: 32. UI Assets — Panels and Frames
A2: Tracking sheet generated from the uploaded markdown. Done? is unchecked by default.
A4: Done? | B4: Asset Key | C4: Suggested Folder | D4: Designer Description | E4: Priority | F4: Source / Export Size | G4: Runtime Render Size | H4: Exact Frames / Count | I4: Final Folder Structure (relative to public/assets) | J4: Audit / Release Note | K4: GDD Theme / Prompt Note
A5: ☐ | B5: ui_panel_default | C5: ui/panels/ | D5: Default chunky pixel panel for common UI. | E5: P0 | F5: 627x627 PNG source for UI icons/badges; 627x627 frames for UI animations | G5: Small UI 24-48px; button emblem 32-64px; badge 64-128px; celebration 160-220px | H5: UI animations exact frames if listed | I5: ui/ | J5: Audit: mobile portrait smoke pending; avoid oversized UI art. | Updated 2026-05-19: non-board visual source supports 627x627 PNG or 1254x1254 2x2 sheets; runtime display is category-constrained. | K5: Chunky readable festival UI with rounded panels, bright accents.
A6: ☐ | B6: ui_panel_battle | C6: ui/panels/ | D6: Battle HUD panel frame, compact and mobile-readable. | E6: P0 | F6: 627x627 PNG source for UI icons/badges; 627x627 frames for UI animations | G6: Small UI 24-48px; button emblem 32-64px; badge 64-128px; celebration 160-220px | H6: UI animations exact frames if listed | I6: ui/ | J6: Audit: mobile portrait smoke pending; avoid oversized UI art. | Updated 2026-05-19: non-board visual source supports 627x627 PNG or 1254x1254 2x2 sheets; runtime display is category-constrained. | K6: Chunky readable festival UI with rounded panels, bright accents.
A7: ☐ | B7: ui_panel_reward | C7: ui/panels/ | D7: Reward screen panel with card slots and sparkle trim. | E7: P0 | F7: 627x627 PNG source for UI icons/badges; 627x627 frames for UI animations | G7: Small UI 24-48px; button emblem 32-64px; badge 64-128px; celebration 160-220px | H7: UI animations exact frames if listed | I7: ui/ | J7: Audit: mobile portrait smoke pending; avoid oversized UI art. | Updated 2026-05-19: non-board visual source supports 627x627 PNG or 1254x1254 2x2 sheets; runtime display is category-constrained. | K7: Chunky readable festival UI with rounded panels, bright accents.
A8: ☐ | B8: ui_panel_shop | C8: ui/panels/ | D8: Shop panel with merchant-friendly trim and price readability. | E8: P1 | F8: 627x627 PNG source for UI icons/badges; 627x627 frames for UI animations | G8: Small UI 24-48px; button emblem 32-64px; badge 64-128px; celebration 160-220px | H8: UI animations exact frames if listed | I8: ui/ | J8: Audit: mobile portrait smoke pending; avoid oversized UI art. | Updated 2026-05-19: non-board visual source supports 627x627 PNG or 1254x1254 2x2 sheets; runtime display is category-constrained. | K8: Chunky readable festival UI with rounded panels, bright accents.
A9: ☐ | B9: ui_panel_event | C9: ui/panels/ | D9: Event choice panel with flexible text area. | E9: P1 | F9: 627x627 PNG source for UI icons/badges; 627x627 frames for UI animations | G9: Small UI 24-48px; button emblem 32-64px; badge 64-128px; celebration 160-220px | H9: UI animations exact frames if listed | I9: ui/ | J9: Audit: mobile portrait smoke pending; avoid oversized UI art. | Updated 2026-05-19: non-board visual source supports 627x627 PNG or 1254x1254 2x2 sheets; runtime display is category-constrained. | K9: Chunky readable festival UI with rounded panels, bright accents.
A10: ☐ | B10: ui_panel_dialogue | C10: ui/panels/ | D10: Dialogue box panel with portrait slot and skip affordance. | E10: P1 | F10: 627x627 PNG source for UI icons/badges; 627x627 frames for UI animations | G10: Small UI 24-48px; button emblem 32-64px; badge 64-128px; celebration 160-220px | H10: UI animations exact frames if listed | I10: ui/ | J10: Audit: mobile portrait smoke pending; avoid oversized UI art. | Updated 2026-05-19: non-board visual source supports 627x627 PNG or 1254x1254 2x2 sheets; runtime display is category-constrained. | K10: Chunky readable festival UI with rounded panels, bright accents.
A11: ☐ | B11: ui_panel_settings | C11: ui/panels/ | D11: Settings panel with simple rows/toggles. | E11: P1 | F11: 627x627 PNG source for UI icons/badges; 627x627 frames for UI animations | G11: Small UI 24-48px; button emblem 32-64px; badge 64-128px; celebration 160-220px | H11: UI animations exact frames if listed | I11: ui/ | J11: Audit: mobile portrait smoke pending; avoid oversized UI art. | Updated 2026-05-19: non-board visual source supports 627x627 PNG or 1254x1254 2x2 sheets; runtime display is category-constrained. | K11: Chunky readable festival UI with rounded panels, bright accents.
A12: ☐ | B12: ui_panel_inventory_compact | C12: ui/panels/ | D12: Small inventory overlay panel for portrait battle board. | E12: P0 | F12: 627x627 PNG source for UI icons/badges; 627x627 frames for UI animations | G12: Small UI 24-48px; button emblem 32-64px; badge 64-128px; celebration 160-220px | H12: UI animations exact frames if listed | I12: ui/ | J12: Audit: mobile portrait smoke pending; avoid oversized UI art. | Updated 2026-05-19: non-board visual source supports 627x627 PNG or 1254x1254 2x2 sheets; runtime display is category-constrained. | K12: Chunky readable festival UI with rounded panels, bright accents.
